Workbook
Name _?: #N/A
Name ______R3_t: #N/A
Name _￡A￡´1: #N/A
Name _108_???14: #N/A
Name _109_???14: #N/A
Name _110_???14: #N/A
Name _111_???14: #N/A
Name _114_???15: #N/A
Name _115_???15: #N/A
Name _116_???15: #N/A
Name _117_???15: #N/A
Name _120_???16: #N/A
Name _121_???16: #N/A
Name _122_???16: #N/A
Name _123_???16: #N/A
Name _126_???17: #N/A
Name _127_???17: #N/A
Name _128_???17: #N/A
Name _129_???17: #N/A
Name _132_???6: #N/A
Name _133_???6: #N/A
Name _134_???6: #N/A
Name _135_???6: #N/A
Name _138_???7: #N/A
Name _139_???7: #N/A
Name _14_???: #N/A
Name _140_???7: #N/A
Name _141_???7: #N/A
Name _164_??1: #N/A
Name _165_??1: #N/A
Name _166_??1: #N/A
Name _167_??1: #N/A
Name _210_??M: #N/A
Name _211_??M: #N/A
Name _212_??M: #N/A
Name _213_??M: #N/A
Name _216_??MD?: #N/A
Name _217_??MD?: #N/A
Name _218_??MD?: #N/A
Name _219_??MD?: #N/A
Name _232_???14: #N/A
Name _243_???15: #N/A
Name _254_???16: #N/A
Name _265_???17: #N/A
Name _268K1_: #N/A
Name _27_???: #N/A
Name _270k113_: {"구분",0,"Auto","Auto","";"발의부서",0,"Auto","Auto",""}
Name _270k113__1: {"구분",0,"Auto","Auto","";"발의부서",0,"Auto","Auto",""}
Name _270k113__1_1: {"구분",0,"Auto","Auto","";"발의부서",0,"Auto","Auto",""}
Name _270k113__2: {"구분",0,"Auto","Auto","";"발의부서",0,"Auto","Auto",""}
Name _270k113__2_1: {"구분",0,"Auto","Auto","";"발의부서",0,"Auto","Auto",""}
Name _270k113__3: {"구분",0,"Auto","Auto","";"발의부서",0,"Auto","Auto",""}
Name _274K150_: {"994시행","SUM(994시행)","YNNNN",FALSE;"9일분기시행","SUM(9일분기시행)","YNNNN",FALSE;"이분기","SUM(이분기)","YNNNN",FALSE}
Name _274K150__1: {"994시행","SUM(994시행)","YNNNN",FALSE;"9일분기시행","SUM(9일분기시행)","YNNNN",FALSE;"이분기","SUM(이분기)","YNNNN",FALSE}
Name _274K150__1_1: {"994시행","SUM(994시행)","YNNNN",FALSE;"9일분기시행","SUM(9일분기시행)","YNNNN",FALSE;"이분기","SUM(이분기)","YNNNN",FALSE}
Name _274K150__2: {"994시행","SUM(994시행)","YNNNN",FALSE;"9일분기시행","SUM(9일분기시행)","YNNNN",FALSE;"이분기","SUM(이분기)","YNNNN",FALSE}
Name _274K150__2_1: {"994시행","SUM(994시행)","YNNNN",FALSE;"9일분기시행","SUM(9일분기시행)","YNNNN",FALSE;"이분기","SUM(이분기)","YNNNN",FALSE}
Name _274K150__3: {"994시행","SUM(994시행)","YNNNN",FALSE;"9일분기시행","SUM(9일분기시행)","YNNNN",FALSE;"이분기","SUM(이분기)","YNNNN",FALSE}
Name _276_???6: #N/A
Name _28_???: #N/A

Sheet 目录1
A1: 目 录
A2: 项目信息 | B2: =HYPERLINK("#'"&A2&"'!A1",A2)
A3: 辅助检查汇总表 | B3: =HYPERLINK("#'"&A3&"'!A1",A3)
A4: 历资表 | B4: =HYPERLINK("#'"&A4&"'!A1",A4)
A5: 历利表 | B5: =HYPERLINK("#'"&A5&"'!A1",A5)
A6: 历现表 | B6: =HYPERLINK("#'"&A6&"'!A1",A6)
A7: 历资调整后表 | B7: =HYPERLINK("#'"&A7&"'!A1",A7)
A8: 历利调整后表 | B8: =HYPERLINK("#'"&A8&"'!A1",A8)
A9: 评估结果汇总表 | B9: =HYPERLINK("#'"&A9&"'!A1",A9)
A10: 净现金流计算表 | B10: =HYPERLINK("#'"&A10&"'!A1",A10)
A11: 主要产品及服务 | B11: =HYPERLINK("#'"&A11&"'!A1",A11)
A12: 营业收入表 | B12: =HYPERLINK("#'"&A12&"'!A1",A12)
A13: 营业收入附表 | B13: =HYPERLINK("#'"&A13&"'!A1",A13)
... A42: 付息负债明细表 | B42: =HYPERLINK("#'"&A42&"'!A1",A42)

Sheet 目录2
A1: 目 录 导 航
N3: =HYPERLINK("#'历资表'!A1","历资表") | P3: =HYPERLINK("#'历利表'!A1","历利表") | R3: =HYPERLINK("#'历现表'!A1","历现表")
N4: ↓ | P4: ↓
N5: =HYPERLINK("#'历资调整后表'!A1","历资调整后表") | P5: =HYPERLINK("#'历利调整后表'!A1","历利调整后表")
N6: ↓ | P6: ↓
F7: 折旧摊销、资本性支出表 | N7: =HYPERLINK("#'营运资金表'!A1","营运资金表") | X7: =HYPERLINK("#'溢余资产、非经营资产负债表'!A1","溢余资产、非经营资产负债表") | AB7: =HYPERLINK("#'付息负债明细表'!A1","付息负债明细表") | AD7: =HYPERLINK("#'长期股权投资表'!A1","长期股权投资表")
H8: ↓ | O8: ↓ | Y8: ↓ | AB8: ↓ | AD8: ↓
B9: =HYPERLINK("#'折现率计算表'!A1","折现率计算表") | C9: → | D9: =HYPERLINK("#'净现金流计算表'!A1","净现金流计算表")
D10: ↑ | F10: ↑ | H10: ↑ | J10: ↑ | L10: ↑ | N10: ↑ | P10: ↑ | R10: ↑ | T10: ↑ | V10: ↑ | X10: ↑ | Z10: ↑ | AB10: ↑ | AD10: ↑ | AF10: ↑ | AH10: ↑ | AJ10: ↑ | AL10: ↑
D11: =HYPERLINK("#'营业收入表'!A1","营业收入表") | F11: =HYPERLINK("#'营业成本表'!A1","营业成本表") | H11: =HYPERLINK("#'税金及附加表'!A1","税金及附加表") | J11: =HYPERLINK("#'销售费用表'!A1","销售费用表") | L11: =HYPERLINK("#'管理费用表'!A1","管理费用表") | N11: =HYPERLINK("#'研发费用表'!A1","研发费用表") | P11: =HYPERLINK("#'财务费用表'!A1","财务费用表") | R11: =HYPERLINK("#'其他收益表'!A1","其他收益表") | T11: =HYPERLINK("#'投资收益表'!A1","投资收益表") | V11: =HYPERLINK("#'汇兑收益表'!A1","汇兑收益表") | X11: =HYPERLINK("#'净敞口套期收益表'!A1","净敞口套期收益表") | Z11: =HYPERLINK("#'公允价值变动收益表'!A1","公允价值变动收益表") | AB11: =HYPERLINK("#'信用减值损失表'!A1","信用减值损失表") | AD11: =HYPERLINK("#'资产减值损失表'!A1","资产减值损失表") | AF11: =HYPERLINK("#'资产处置收益表'!A1","资产处置收益表") | AH11: =HYPERLINK("#'营业外收入表'!A1","营业外收入表") | AJ11: =HYPERLINK("#'营业外支出表'!A1","营业外支出表") | AL11: =HYPERLINK("#'所得税表'!A1","所得税表")
D12: ↑ | F12: ↑ | H12: ↑ | J12: ↑↓ | L12: ↑↓ | N12: ↑↓
D13: =HYPERLINK("#'营业收入附表'!A1","营业收入附表") | F13: =HYPERLINK("#'营业成本附表'!A1","营业成本附表") | H13: =HYPERLINK("#'增值税表'!A1","增值税表") | J13: =HYPERLINK("#'折旧摊销、资本性支出表'!A1","折旧摊销、资本性支出表") | O13: ← → | P13: =HYPERLINK("#'制造费用表'!A1","制造费用表")
D14: ↑ | F14: ↑ | J14: ↑ | L14: ↑
D15: =HYPERLINK("#'主要产品及服务'!A1","主要产品及服务") | H15: =HYPERLINK("#'人工成本表'!A1","人工成本表") | J15: =HYPERLINK("#'折旧摊销附表'!A1","折旧摊销附表") | L15: =HYPERLINK("#'资本性支出附表'!A1","资本性支出附表")

Sheet 撤销保护记录
A1: 申请日期 | B1: Sheet名称 | C1: 撤销保护的原因

Sheet 项目信息
A1: 收益法预测表 | C1: =HYPERLINK("#目录1!A1","返回目录")
A2: 评估基准日：{{VALUATION_BASE_DATE}}
A3: ="被评估单位："&项目信息!B5&"" | B3: ="金额单位："&项目信息!B8&""
A4: 项目信息 | B4: 值
A5: 被评估企业 | B5: {{COMPANY_NAME}}
A6: 企业类型 | B6: 待补充评估参数
A7: 评估基准日 | B7: {{VALUATION_BASE_DATE}}
A8: 单位 | B8: 万元
A9: 被评估单位是否永续 | B9: 待补充评估参数
A10: 是否永续增长 | B10: 待补充评估参数
A11: 永续增长率 | B11: 待补充评估参数
A12: 最后一期评估期 | B12: 待补充评估参数
A13: 现金流模型 | B13: 待补充评估参数
A14: 折现方式 | B14: 待补充评估参数
A15: 使用资本结构 | B15: 待补充评估参数
... A17: 项目类型 | B17: 待补充评估参数

Sheet 辅助检查汇总表
A1: 辅助检查汇总表 | O1: =HYPERLINK("#目录1!A1","返回目录")
A2: 评估基准日：{{VALUATION_BASE_DATE}}
A3: ="被评估单位："&项目信息!B5&"" | N3: ="金额单位："&项目信息!B8&""
A5: 历资表
A6: =历资表!A101 | B6: =历资表!B101 | C6: =历资表!C101 | D6: =历资表!D101 | E6: =历资表!E101
A8: 历资调整后表
A9: =历资调整后表!A101 | B9: =历资调整后表!B101 | C9: =历资调整后表!C101 | D9: =历资调整后表!D101 | E9: =历资调整后表!E101 | F9: =历资调整后表!F101 | G9: =历资调整后表!G101 | H9: =历资调整后表!H101 | ... N9: =历资调整后表!N101
A11: 评估结果汇总表
A12: =评估结果汇总表!A32 | B12: =评估结果汇总表!B32
A14: 营业收入表
A15: =营业收入表!A19 | B15: =营业收入表!B19 | C15: =营业收入表!C19 | D15: =营业收入表!D19 | E15: =营业收入表!E19 | F15: =营业收入表!F19 | G15: =营业收入表!G19 | H15: =营业收入表!H19 | ... M15: =营业收入表!M19
A16: =营业收入表!A20 | B16: =营业收入表!B20 | C16: =营业收入表!C20 | D16: =营业收入表!D20 | E16: =营业收入表!E20 | F16: =营业收入表!F20 | G16: =营业收入表!G20 | H16: =营业收入表!H20 | ... M16: =营业收入表!M20
A17: =营业收入表!A21 | B17: =营业收入表!B21 | C17: =营业收入表!C21 | D17: =营业收入表!D21 | E17: =营业收入表!E21 | F17: =营业收入表!F21 | G17: =营业收入表!G21 | H17: =营业收入表!H21 | ... M17: =营业收入表!M21
A18: =营业收入表!A22 | B18: =营业收入表!B22 | C18: =营业收入表!C22 | D18: =营业收入表!D22 | E18: =营业收入表!E22 | F18: =营业收入表!F22 | G18: =营业收入表!G22 | H18: =营业收入表!H22 | ... M18: =营业收入表!M22
A19: =营业收入表!A23 | B19: =营业收入表!B23 | C19: =营业收入表!C23 | D19: =营业收入表!D23 | E19: =营业收入表!E23 | F19: =营业收入表!F23 | G19: =营业收入表!G23 | H19: =营业收入表!H23 | ... M19: =营业收入表!M23
A20: =营业收入表!A24 | B20: =营业收入表!B24 | C20: =营业收入表!C24 | D20: =营业收入表!D24 | E20: =营业收入表!E24 | F20: =营业收入表!F24 | G20: =营业收入表!G24 | H20: =营业收入表!H24 | ... M20: =营业收入表!M24
A21: =营业收入表!A25 | B21: =营业收入表!B25 | C21: =营业收入表!C25 | D21: =营业收入表!D25 | E21: =营业收入表!E25 | F21: =营业收入表!F25 | G21: =营业收入表!G25 | H21: =营业收入表!H25 | ... M21: =营业收入表!M25
A23: 营业收入附表
A24: =营业收入附表!A25 | B24: =营业收入附表!B25 | C24: =营业收入附表!C25 | D24: =营业收入附表!D25 | E24: =营业收入附表!E25 | F24: =营业收入附表!F25
A25: =营业收入附表!A26 | B25: =营业收入附表!B26 | C25: =营业收入附表!C26 | D25: =营业收入附表!D26 | E25: =营业收入附表!E26 | F25: =营业收入附表!F26
A26: =营业收入附表!A27 | B26: =营业收入附表!B27 | C26: =营业收入附表!C27 | D26: =营业收入附表!D27 | E26: =营业收入附表!E27 | F26: =营业收入附表!F27
A28: 营业成本表
A29: =营业成本表!A19 | B29: =营业成本表!B19 | C29: =营业成本表!C19 | D29: =营业成本表!D19 | E29: =营业成本表!E19 | F29: =营业成本表!F19 | G29: =营业成本表!G19 | H29: =营业成本表!H19 | ... M29: =营业成本表!M19
A30: =营业成本表!A20 | B30: =营业成本表!B20 | C30: =营业成本表!C20 | D30: =营业成本表!D20 | E30: =营业成本表!E20 | F30: =营业成本表!F20 | G30: =营业成本表!G20 | H30: =营业成本表!H20 | ... M30: =营业成本表!M20
A31: =营业成本表!A21 | B31: =营业成本表!B21 | C31: =营业成本表!C21 | D31: =营业成本表!D21 | E31: =营业成本表!E21 | F31: =营业成本表!F21 | G31: =营业成本表!G21 | H31: =营业成本表!H21 | ... M31: =营业成本表!M21
A32: =营业成本表!A22 | B32: =营业成本表!B22 | C32: =营业成本表!C22 | D32: =营业成本表!D22 | E32: =营业成本表!E22 | F32: =营业成本表!F22 | G32: =营业成本表!G22 | H32: =营业成本表!H22 | ... M32: =营业成本表!M22
A33: =营业成本表!A23 | B33: =营业成本表!B23 | C33: =营业成本表!C23 | D33: =营业成本表!D23 | E33: =营业成本表!E23 | F33: =营业成本表!F23 | G33: =营业成本表!G23 | H33: =营业成本表!H23 | ... M33: =营业成本表!M23
A34: =营业成本表!A24 | B34: =营业成本表!B24 | C34: =营业成本表!C24 | D34: =营业成本表!D24 | E34: =营业成本表!E24 | F34: =营业成本表!F24 | G34: =营业成本表!G24 | H34: =营业成本表!H24 | ... M34: =营业成本表!M24
A35: =营业成本表!A25 | B35: =营业成本表!B25 | C35: =营业成本表!C25 | D35: =营业成本表!D25 | E35: =营业成本表!E25 | F35: =营业成本表!F25 | G35: =营业成本表!G25 | H35: =营业成本表!H25 | ... M35: =营业成本表!M25
A36: =营业成本表!A26 | B36: =营业成本表!B26 | C36: =营业成本表!C26 | D36: =营业成本表!D26 | E36: =营业成本表!E26 | F36: =营业成本表!F26 | G36: =营业成本表!G26 | H36: =营业成本表!H26 | ... M36: =营业成本表!M26
A37: =营业成本表!A27 | B37: =营业成本表!B27 | C37: =营业成本表!C27 | D37: =营业成本表!D27 | E37: =营业成本表!E27 | F37: =营业成本表!F27 | G37: =营业成本表!G27 | H37: =营业成本表!H27 | ... M37: =营业成本表!M27
A39: 营业成本附表
A40: =营业成本附表!A33 | B40: =营业成本附表!B33 | C40: =营业成本附表!C33 | D40: =营业成本附表!D33 | E40: =营业成本附表!E33 | F40: =营业成本附表!F33
A41: =营业成本附表!A34 | B41: =营业成本附表!B34 | C41: =营业成本附表!C34 | D41: =营业成本附表!D34 | E41: =营业成本附表!E34 | F41: =营业成本附表!F34
A42: =营业成本附表!A35 | B42: =营业成本附表!B35 | C42: =营业成本附表!C35 | D42: =营业成本附表!D35 | E42: =营业成本附表!E35 | F42: =营业成本附表!F35
A43: =营业成本附表!A36 | B43: =营业成本附表!B36 | C43: =营业成本附表!C36 | D43: =营业成本附表!D36 | E43: =营业成本附表!E36 | F43: =营业成本附表!F36 | G43: =营业成本附表!G36 | H43: =营业成本附表!H36 | ... M43: =营业成本附表!M36
A44: =营业成本附表!A37 | B44: =营业成本附表!B37 | C44: =营业成本附表!C37 | D44: =营业成本附表!D37 | E44: =营业成本附表!E37 | F44: =营业成本附表!F37 | G44: =营业成本附表!G37 | H44: =营业成本附表!H37 | ... M44: =营业成本附表!M37
A45: =营业成本附表!A38 | B45: =营业成本附表!B38 | C45: =营业成本附表!C38 | D45: =营业成本附表!D38 | E45: =营业成本附表!E38 | F45: =营业成本附表!F38 | G45: =营业成本附表!G38 | H45: =营业成本附表!H38 | ... M45: =营业成本附表!M38
A46: =营业成本附表!A39 | B46: =营业成本附表!B39 | C46: =营业成本附表!C39 | D46: =营业成本附表!D39 | E46: =营业成本附表!E39 | F46: =营业成本附表!F39 | G46: =营业成本附表!G39 | H46: =营业成本附表!H39 | ... M46: =营业成本附表!M39
A48: 制造费用表
A49: =制造费用表!A64 | B49: =制造费用表!B64 | C49: =制造费用表!C64 | D49: =制造费用表!D64 | E49: =制造费用表!E64 | F49: =制造费用表!F64 | G49: =制造费用表!G64 | H49: =制造费用表!H64 | ... M49: =制造费用表!M64
A50: =制造费用表!A65 | B50: =制造费用表!B65 | C50: =制造费用表!C65 | D50: =制造费用表!D65 | E50: =制造费用表!E65 | F50: =制造费用表!F65 | G50: =制造费用表!G65 | H50: =制造费用表!H65 | ... M50: =制造费用表!M65
A51: =制造费用表!A66 | B51: =制造费用表!B66 | C51: =制造费用表!C66 | D51: =制造费用表!D66 | E51: =制造费用表!E66 | F51: =制造费用表!F66 | G51: =制造费用表!G66 | H51: =制造费用表!H66 | ... M51: =制造费用表!M66
A52: =制造费用表!A67 | B52: =制造费用表!B67 | C52: =制造费用表!C67 | D52: =制造费用表!D67 | E52: =制造费用表!E67 | F52: =制造费用表!F67 | G52: =制造费用表!G67 | H52: =制造费用表!H67 | ... M52: =制造费用表!M67
A54: 税金及附加表
A55: =税金及附加表!A29 | B55: =税金及附加表!B29 | C55: =税金及附加表!C29 | D55: =税金及附加表!D29 | E55: =税金及附加表!E29 | F55: =税金及附加表!F29
A56: =税金及附加表!A30 | B56: =税金及附加表!B30 | C56: =税金及附加表!C30 | D56: =税金及附加表!D30 | E56: =税金及附加表!E30 | F56: =税金及附加表!F30 | G56: =税金及附加表!G30 | H56: =税金及附加表!H30 | ... M56: =税金及附加表!M30
A57: =税金及附加表!A31 | B57: =税金及附加表!B31 | C57: =税金及附加表!C31 | D57: =税金及附加表!D31 | E57: =税金及附加表!E31 | F57: =税金及附加表!F31 | G57: =税金及附加表!G31 | H57: =税金及附加表!H31 | ... M57: =税金及附加表!M31
A59: 增值税表
A60: =增值税表!A164 | B60: =增值税表!B164 | C60: =增值税表!C164 | D60: =增值税表!D164 | E60: =增值税表!E164 | F60: =增值税表!F164 | G60: =增值税表!G164 | H60: =增值税表!H164 | ... M60: =增值税表!M164
A61: =增值税表!A165 | B61: =增值税表!B165 | C61: =增值税表!C165 | D61: =增值税表!D165 | E61: =增值税表!E165 | F61: =增值税表!F165 | G61: =增值税表!G165 | H61: =增值税表!H165 | ... M61: =增值税表!M165
A62: =增值税表!A166 | B62: =增值税表!B166 | C62: =增值税表!C166 | D62: =增值税表!D166 | E62: =增值税表!E166 | F62: =增值税表!F166 | G62: =增值税表!G166 | H62: =增值税表!H166 | ... M62: =增值税表!M166
A63: =增值税表!A167 | B63: =增值税表!B167 | C63: =增值税表!C167 | D63: =增值税表!D167 | E63: =增值税表!E167 | F63: =增值税表!F167 | G63: =增值税表!G167 | H63: =增值税表!H167 | ... M63: =增值税表!M167
A65: 销售费用表
A66: =销售费用表!A64 | B66: =销售费用表!B64 | C66: =销售费用表!C64 | D66: =销售费用表!D64 | E66: =销售费用表!E64 | F66: =销售费用表!F64
A67: =销售费用表!A65 | B67: =销售费用表!B65 | C67: =销售费用表!C65 | D67: =销售费用表!D65 | E67: =销售费用表!E65 | F67: =销售费用表!F65 | G67: =销售费用表!G65 | H67: =销售费用表!H65 | ... M67: =销售费用表!M65
A68: =销售费用表!A66 | B68: =销售费用表!B66 | C68: =销售费用表!C66 | D68: =销售费用表!D66 | E68: =销售费用表!E66 | F68: =销售费用表!F66 | G68: =销售费用表!G66 | H68: =销售费用表!H66 | ... M68: =销售费用表!M66
A70: 管理费用表
A71: =管理费用表!A64 | B71: =管理费用表!B64 | C71: =管理费用表!C64 | D71: =管理费用表!D64 | E71: =管理费用表!E64 | F71: =管理费用表!F64
A72: =管理费用表!A65 | B72: =管理费用表!B65 | C72: =管理费用表!C65 | D72: =管理费用表!D65 | E72: =管理费用表!E65 | F72: =管理费用表!F65 | G72: =管理费用表!G65 | H72: =管理费用表!H65 | ... M72: =管理费用表!M65
A73: =管理费用表!A66 | B73: =管理费用表!B66 | C73: =管理费用表!C66 | D73: =管理费用表!D66 | E73: =管理费用表!E66 | F73: =管理费用表!F66 | G73: =管理费用表!G66 | H73: =管理费用表!H66 | ... M73: =管理费用表!M66
A75: 研发费用表
A76: =研发费用表!A65 | B76: =研发费用表!B65 | C76: =研发费用表!C65 | D76: =研发费用表!D65 | E76: =研发费用表!E65 | F76: =研发费用表!F65
A77: =研发费用表!A66 | B77: =研发费用表!B66 | C77: =研发费用表!C66 | D77: =研发费用表!D66 | E77: =研发费用表!E66 | F77: =研发费用表!F66 | G77: =研发费用表!G66 | H77: =研发费用表!H66 | ... M77: =研发费用表!M66
A78: =研发费用表!A67 | B78: =研发费用表!B67 | C78: =研发费用表!C67 | D78: =研发费用表!D67 | E78: =研发费用表!E67 | F78: =研发费用表!F67 | G78: =研发费用表!G67 | H78: =研发费用表!H67 | ... M78: =研发费用表!M67
A80: 财务费用表
A81: =财务费用表!A17 | B81: =财务费用表!B17 | C81: =财务费用表!C17 | D81: =财务费用表!D17 | E81: =财务费用表!E17 | F81: =财务费用表!F17
A82: =财务费用表!A18 | B82: =财务费用表!B18 | C82: =财务费用表!C18 | D82: =财务费用表!D18 | E82: =财务费用表!E18 | F82: =财务费用表!F18 | G82: =财务费用表!G18 | H82: =财务费用表!H18 | ... M82: =财务费用表!M18
A84: 其他收益表
A85: =其他收益表!A11 | B85: =其他收益表!B11 | C85: =其他收益表!C11 | D85: =其他收益表!D11 | E85: =其他收益表!E11 | F85: =其他收益表!F11
A86: =其他收益表!A12 | B86: =其他收益表!B12 | C86: =其他收益表!C12 | D86: =其他收益表!D12 | E86: =其他收益表!E12 | F86: =其他收益表!F12 | G86: =其他收益表!G12 | H86: =其他收益表!H12 | ... M86: =其他收益表!M12
A88: 投资收益表
A89: =投资收益表!A11 | B89: =投资收益表!B11 | C89: =投资收益表!C11 | D89: =投资收益表!D11 | E89: =投资收益表!E11 | F89: =投资收益表!F11
A90: =投资收益表!A12 | B90: =投资收益表!B12 | C90: =投资收益表!C12 | D90: =投资收益表!D12 | E90: =投资收益表!E12 | F90: =投资收益表!F12 | G90: =投资收益表!G12 | H90: =投资收益表!H12 | ... M90: =投资收益表!M12
A92: 汇兑收益表
A93: =汇兑收益表!A11 | B93: =汇兑收益表!B11 | C93: =汇兑收益表!C11 | D93: =汇兑收益表!D11 | E93: =汇兑收益表!E11 | F93: =汇兑收益表!F11
A94: =汇兑收益表!A12 | B94: =汇兑收益表!B12 | C94: =汇兑收益表!C12 | D94: =汇兑收益表!D12 | E94: =汇兑收益表!E12 | F94: =汇兑收益表!F12 | G94: =汇兑收益表!G12 | H94: =汇兑收益表!H12 | ... M94: =汇兑收益表!M12
A96: 净敞口套期收益表
A97: =净敞口套期收益表!A11 | B97: =净敞口套期收益表!B11 | C97: =净敞口套期收益表!C11 | D97: =净敞口套期收益表!D11 | E97: =净敞口套期收益表!E11 | F97: =净敞口套期收益表!F11
A98: =净敞口套期收益表!A12 | B98: =净敞口套期收益表!B12 | C98: =净敞口套期收益表!C12 | D98: =净敞口套期收益表!D12 | E98: =净敞口套期收益表!E12 | F98: =净敞口套期收益表!F12 | G98: =净敞口套期收益表!G12 | H98: =净敞口套期收益表!H12 | ... M98: =净敞口套期收益表!M12
A100: 公允价值变动收益表
A101: =公允价值变动收益表!A11 | B101: =公允价值变动收益表!B11 | C101: =公允价值变动收益表!C11 | D101: =公允价值变动收益表!D11 | E101: =公允价值变动收益表!E11 | F101: =公允价值变动收益表!F11
A102: =公允价值变动收益表!A12 | B102: =公允价值变动收益表!B12 | C102: =公允价值变动收益表!C12 | D102: =公允价值变动收益表!D12 | E102: =公允价值变动收益表!E12 | F102: =公允价值变动收益表!F12 | G102: =公允价值变动收益表!G12 | H102: =公允价值变动收益表!H12 | ... M102: =公允价值变动收益表!M12
A104: 信用减值损失表
A105: =信用减值损失表!A11 | B105: =信用减值损失表!B11 | C105: =信用减值损失表!C11 | D105: =信用减值损失表!D11 | E105: =信用减值损失表!E11 | F105: =信用减值损失表!F11
A106: =信用减值损失表!A12 | B106: =信用减值损失表!B12 | C106: =信用减值损失表!C12 | D106: =信用减值损失表!D12 | E106: =信用减值损失表!E12 | F106: =信用减值损失表!F12 | G106: =信用减值损失表!G12 | H106: =信用减值损失表!H12 | ... M106: =信用减值损失表!M12
A108: 资产减值损失表
A109: =资产减值损失表!A11 | B109: =资产减值损失表!B11 | C109: =资产减值损失表!C11 | D109: =资产减值损失表!D11 | E109: =资产减值损失表!E11 | F109: =资产减值损失表!F11
A110: =资产减值损失表!A12 | B110: =资产减值损失表!B12 | C110: =资产减值损失表!C12 | D110: =资产减值损失表!D12 | E110: =资产减值损失表!E12 | F110: =资产减值损失表!F12 | G110: =资产减值损失表!G12 | H110: =资产减值损失表!H12 | ... M110: =资产减值损失表!M12
A112: 资产处置收益表
A113: =资产处置收益表!A11 | B113: =资产处置收益表!B11 | C113: =资产处置收益表!C11 | D113: =资产处置收益表!D11 | E113: =资产处置收益表!E11 | F113: =资产处置收益表!F11
A114: =资产处置收益表!A12 | B114: =资产处置收益表!B12 | C114: =资产处置收益表!C12 | D114: =资产处置收益表!D12 | E114: =资产处置收益表!E12 | F114: =资产处置收益表!F12 | G114: =资产处置收益表!G12 | H114: =资产处置收益表!H12 | ... M114: =资产处置收益表!M12
A116: 营业外收入表
A117: =营业外收入表!A11 | B117: =营业外收入表!B11 | C117: =营业外收入表!C11 | D117: =营业外收入表!D11 | E117: =营业外收入表!E11 | F117: =营业外收入表!F11
A118: =营业外收入表!A12 | B118: =营业外收入表!B12 | C118: =营业外收入表!C12 | D118: =营业外收入表!D12 | E118: =营业外收入表!E12 | F118: =营业外收入表!F12 | G118: =营业外收入表!G12 | H118: =营业外收入表!H12 | ... M118: =营业外收入表!M12
A120: 营业外支出表
A121: =营业外支出表!A11 | B121: =营业外支出表!B11 | C121: =营业外支出表!C11 | D121: =营业外支出表!D11 | E121: =营业外支出表!E11 | F121: =营业外支出表!F11
A122: =营业外支出表!A12 | B122: =营业外支出表!B12 | C122: =营业外支出表!C12 | D122: =营业外支出表!D12 | E122: =营业外支出表!E12 | F122: =营业外支出表!F12 | G122: =营业外支出表!G12 | H122: =营业外支出表!H12 | ... M122: =营业外支出表!M12
A124: 所得税表
A125: =所得税表!A45 | B125: =所得税表!B45 | C125: =所得税表!C45 | D125: =所得税表!D45 | E125: =所得税表!E45 | F125: =所得税表!F45
...

Sheet 历资表
A1: 历史资产负债表 | F1: =HYPERLINK("#目录1!A1","返回目录")
A2: 评估基准日：{{VALUATION_BASE_DATE}}
A3: ="被评估单位："&项目信息!B5&"" | E3: ="金额单位："&项目信息!B8&""
A4: 项目\年份 | B4: 2022年度 | C4: 2023年度 | D4: 2024年度 | E4: 2025年1-6月
A6: 流动资产：
A7: 货币资金
A8: 结算备付金
A9: 拆出资金
A10: 交易性金融资产
A11: 衍生金融资产
A12: 应收票据
A13: 应收账款
A14: 应收款项融资
A15: 预付款项
A16: 应收保费
A17: 应收分保账款
... A25: 其他流动资产
A26: 一、流动资产合计 | B26: =SUM(B7:B25) | C26: =SUM(C7:C25) | D26: =SUM(D7:D25) | E26: =SUM(E7:E25)
A27: 非流动资产：
A28: 可供出售金融资产
A29: 债权投资
A30: 其他债权投资
A31: 长期应收款
A32: 长期股权投资
A33: 其他权益工具投资
A34: 其他非流动金融资产
A35: 投资性房地产
A36: 固定资产
A37: 在建工程
A38: 工程物资
... A45: 其他非流动资产
A46: 二、非流动资产合计 | B46: =SUM(B28:B45) | C46: =SUM(C28:C45) | D46: =SUM(D28:D45) | E46: =SUM(E28:E45)
A47: 三、资产总计 | B47: =B26+B46 | C47: =C26+C46 | D47: =D26+D46 | E47: =E26+E46
A48: 流动负债：
A49: 短期借款
A50: 向中央银行借款
A51: 拆入资金
A52: 交易性金融负债
A53: 衍生金融负债
A54: 应付票据
A55: 应付账款
A56: 预收款项
A57: 合同负债
A58: 卖出回购金融资产款
A59: 吸收存款及同业存放
... A69: 其他流动负债
A70: 四、流动负债合计 | B70: =SUM(B49:B69) | C70: =SUM(C49:C69) | D70: =SUM(D49:D69) | E70: =SUM(E49:E69)
A71: 非流动负债：
A72: 长期借款
A73: 应付债券
A74: 其中：优先股
A75: 永续债
A76: 租赁负债
A77: 长期应付款
A78: 预计负债
A79: 递延收益
A80: 递延所得税负债
A81: 其他非流动负债
A82: 五、非流动负债合计 | B82: =SUM(B72:B73,B76:B81) | C82: =SUM(C72:C73,C76:C81) | D82: =SUM(D72:D73,D76:D81) | E82: =SUM(E72:E73,E76:E81)
A83: 六、负债合计 | B83: =B70+B82 | C83: =C70+C82 | D83: =D70+D82 | E83: =E70+E82
A84: 所有者权益或净资产：
A85: 股本
A86: 其他权益工具
A87: 其中：优先股
A88: 永续债
A89: 资本公积
A90: 减：库存股
A91: 其他综合收益
A92: 专项储备
A93: 盈余公积
A94: 一般风险准备
A95: 未分配利润
A96: 归属于母公司所有者权益合计 | B96: =B85+B86+B89-B90+B91+B92+B93+B94+B95 | C96: =C85+C86+C89-C90+C91+C92+C93+C94+C95 | D96: =D85+D86+D89-D90+D91+D92+D93+D94+D95 | E96: =E85+E86+E89-E90+E91+E92+E93+E94+E95
A97: 少数股东权益
A98: 七、所有者权益合计 | B98: =SUM(B96:B97) | C98: =SUM(C96:C97) | D98: =SUM(D96:D97) | E98: =SUM(E96:E97)
A99: 八、负债和所有者权益总计 | B99: =B83+B98 | C99: =C83+C98 | D99: =D83+D98 | E99: =E83+E98
A101: 核对 | B101: =B47-B99 | C101: =C47-C99 | D101: =D47-D99 | E101: =E47-E99

Sheet 历利表
A1: 历史利润表 | F1: =HYPERLINK("#目录1!A1","返回目录")
A2: 评估基准日：{{VALUATION_BASE_DATE}}
A3: ="被评估单位："&项目信息!B5&"" | E3: ="金额单位："&项目信息!B8&""
A4: 项目\年份 | B4: 2022年度 | C4: 2023年度 | D4: 2024年度 | E4: 2025年1-6月
A6: 一、营业总收入 | B6: =B7+SUM(B10:B12) | C6: =C7+SUM(C10:C12) | D6: =D7+SUM(D10:D12) | E6: =E7+SUM(E10:E12)
A7: 其中：营业收入 | B7: =B8+B9 | C7: =C8+C9 | D7: =D8+D9 | E7: =E8+E9
A8: 其中：主营业务收入
A9: 其他业务收入
A10: 利息收入
A11: 已赚保费
A12: 手续费及佣金收入
A13: 二、营业总成本 | B13: =B14+SUM(B17:B28) | C13: =C14+SUM(C17:C28) | D13: =D14+SUM(D17:D28) | E13: =E14+SUM(E17:E28)
A14: 其中：营业成本 | B14: =B15+B16 | C14: =C15+C16 | D14: =D15+D16 | E14: =E15+E16
A15: 其中：主营业务成本
A16: 其他业务成本
A17: 利息支出
A18: 手续费及佣金支出
A19: 退保金
A20: 赔付支出净额
A21: 提取保险责任准备金净额
A22: 保单红利支出
A23: 分保费用
A24: 税金及附加
A25: 销售费用
A26: 管理费用
... A40: 资产处置收益（损失以“-”号填列）
A41: 三、营业利润 | B41: =B6-B13+SUM(B31:B32)+SUM(B35:B40) | C41: =C6-C13+SUM(C31:C32)+SUM(C35:C40) | D41: =D6-D13+SUM(D31:D32)+SUM(D35:D40) | E41: =E6-E13+SUM(E31:E32)+SUM(E35:E40)
A42: 加：营业外收入
A43: 减：营业外支出
A44: 四、利润总额 | B44: =B41+B42-B43 | C44: =C41+C42-C43 | D44: =D41+D42-D43 | E44: =E41+E42-E43
A45: 减: 所得税费用
A46: 五、净利润 | B46: =B44-B45 | C46: =C44-C45 | D46: =D44-D45 | E46: =E44-E45
A47: （一）持续经营净利润
A48: （二）终止经营净利润
A49: 减：少数股东损益
A50: 六、归属于母公司损益 | B50: =B46-B49 | C50: =C46-C49 | D50: =D46-D49 | E50: =E46-E49

Sheet 历现表
A1: 历史现金流量表 | F1: =HYPERLINK("#目录1!A1","返回目录")
A2: 评估基准日：{{VALUATION_BASE_DATE}}
A3: ="被评估单位："&项目信息!B5&"" | E3: ="金额单位："&项目信息!B8&""
A4: 项目\年份 | B4: 2022年度 | C4: 2023年度 | D4: 2024年度 | E4: 2025年1-6月
A5: 一、经营活动产生的现金流量：
A6: 销售商品、提供劳务收到的现金
A7: 收到的税费返还
A8: 收到其他与经营活动有关的现金
A9: 经营活动现金流入小计 | B9: =SUM(B6:B8) | C9: =SUM(C6:C8) | D9: =SUM(D6:D8) | E9: =SUM(E6:E8)
A10: 购买商品、接受劳务支付的现金
A11: 支付给职工以及为职工支付的现金
A12: 支付的各项税费
A13: 支付其他与经营活动有关的现金
A14: 经营活动现金流出小计 | B14: =SUM(B10:B13) | C14: =SUM(C10:C13) | D14: =SUM(D10:D13) | E14: =SUM(E10:E13)
A15: 经营活动产生的现金流量净额 | B15: =B9-B14 | C15: =C9-C14 | D15: =D9-D14 | E15: =E9-E14
A16: 二、投资活动产生的现金流量：
A17: 收回投资收到的现金
A18: 取得投资收益收到的现金
A19: 处置固定资产、无形资产和其他长期资产收回的现金净额
A20: 处置子公司及其他营业单位收到的现金净额
A21: 收到其他与投资活动有关的现金
A22: 投资活动现金流入小计 | B22: =SUM(B17:B21) | C22: =SUM(C17:C21) | D22: =SUM(D17:D21) | E22: =SUM(E17:E21)
A23: 购建固定资产、无形资产和其他长期资产支付的现金
A24: 投资支付的现金
A25: 取得子公司及其他营业单位支付的现金净额
A26: 支付其他与投资活动有关的现金
A27: 投资活动现金流出小计 | B27: =SUM(B23:B26) | C27: =SUM(C23:C26) | D27: =SUM(D23:D26) | E27: =SUM(E23:E26)
A28: 投资活动产生的现金流量净额 | B28: =B22-B27 | C28: =C22-C27 | D28: =D22-D27 | E28: =E22-E27
A29: 三、筹资活动产生的现金流量：
A30: 吸收投资收到的现金
A31: 取得借款收到的现金
A32: 收到其他与筹资活动有关的现金
A33: 筹资活动现金流入小计 | B33: =SUM(B30:B32) | C33: =SUM(C30:C32) | D33: =SUM(D30:D32) | E33: =SUM(E30:E32)
A34: 偿还债务支付的现金
A35: 分配股利、利润或偿付利息支付的现金
A36: 支付其他与筹资活动有关的现金
A37: 筹资活动现金流出小计 | B37: =SUM(B34:B36) | C37: =SUM(C34:C36) | D37: =SUM(D34:D36) | E37: =SUM(E34:E36)
A38: 筹资活动产生的现金流量净额 | B38: =B33-B37 | C38: =C33-C37 | D38: =D33-D37 | E38: =E33-E37
A39: 四、汇率变动对现金及现金等价物的影响
A40: 五、现金及现金等价物净增加额 | B40: =B15+B28+B38+B39 | C40: =C15+C28+C38+C39 | D40: =D15+D28+D38+D39 | E40: =E15+E28+E38+E39
A41: 加：期初现金及现金等价物余额
A42: 六、期末现金及现金等价物余额 | B42: =B41+B40 | C42: =C41+C40 | D42: =D41+D40 | E42: =E41+E40

Sheet 历资调整后表
A1: 历史资产负债分析调整表 | O1: =HYPERLINK("#目录1!A1","返回目录")
A2: 评估基准日：{{VALUATION_BASE_DATE}}
A3: ="被评估单位："&项目信息!B5&"" | N3: ="金额单位："&项目信息!B8&""
A4: 项目\年份 | B4: 2022年度 | E4: 2023年度 | H4: 2024年度 | K4: 2025年1-6月 | N4: 调整分析说明
B5: 账面值/审定值 | C5: 其中：非经营性资产，或者重分类调整 | D5: 调整后经营性资产 | E5: 账面值/审定值 | F5: 其中：非经营性资产，或者重分类调整 | G5: 调整后经营性资产 | H5: 账面值/审定值 | I5: 其中：非经营性资产，或者重分类调整 | J5: 调整后经营性资产 | K5: 账面值/审定值 | L5: 其中：非经营性资产，或者重分类调整 | M5: 调整后经营性资产
A6: =历资表!A6
A7: =历资表!A7 | B7: =历资表!B7 | D7: =B7-C7 | E7: =历资表!C7 | G7: =E7-F7 | H7: =历资表!D7 | J7: =H7-I7 | K7: =历资表!E7 | M7: =K7-L7
A8: =历资表!A8 | B8: =历资表!B8 | D8: =B8-C8 | E8: =历资表!C8 | G8: =E8-F8 | H8: =历资表!D8 | J8: =H8-I8 | K8: =历资表!E8 | M8: =K8-L8
A9: =历资表!A9 | B9: =历资表!B9 | D9: =B9-C9 | E9: =历资表!C9 | G9: =E9-F9 | H9: =历资表!D9 | J9: =H9-I9 | K9: =历资表!E9 | M9: =K9-L9
A10: =历资表!A10 | B10: =历资表!B10 | D10: =B10-C10 | E10: =历资表!C10 | G10: =E10-F10 | H10: =历资表!D10 | J10: =H10-I10 | K10: =历资表!E10 | M10: =K10-L10
A11: =历资表!A11 | B11: =历资表!B11 | D11: =B11-C11 | E11: =历资表!C11 | G11: =E11-F11 | H11: =历资表!D11 | J11: =H11-I11 | K11: =历资表!E11 | M11: =K11-L11
A12: =历资表!A12 | B12: =历资表!B12 | D12: =B12-C12 | E12: =历资表!C12 | G12: =E12-F12 | H12: =历资表!D12 | J12: =H12-I12 | K12: =历资表!E12 | M12: =K12-L12
A13: =历资表!A13 | B13: =历资表!B13 | D13: =B13-C13 | E13: =历资表!C13 | G13: =E13-F13 | H13: =历资表!D13 | J13: =H13-I13 | K13: =历资表!E13 | M13: =K13-L13
A14: =历资表!A14 | B14: =历资表!B14 | D14: =B14-C14 | E14: =历资表!C14 | G14: =E14-F14 | H14: =历资表!D14 | J14: =H14-I14 | K14: =历资表!E14 | M14: =K14-L14
A15: =历资表!A15 | B15: =历资表!B15 | D15: =B15-C15 | E15: =历资表!C15 | G15: =E15-F15 | H15: =历资表!D15 | J15: =H15-I15 | K15: =历资表!E15 | M15: =K15-L15
A16: =历资表!A16 | B16: =历资表!B16 | D16: =B16-C16 | E16: =历资表!C16 | G16: =E16-F16 | H16: =历资表!D16 | J16: =H16-I16 | K16: =历资表!E16 | M16: =K16-L16
A17: =历资表!A17 | B17: =历资表!B17 | D17: =B17-C17 | E17: =历资表!C17 | G17: =E17-F17 | H17: =历资表!D17 | J17: =H17-I17 | K17: =历资表!E17 | M17: =K17-L17
A18: =历资表!A18 | B18: =历资表!B18 | D18: =B18-C18 | E18: =历资表!C18 | G18: =E18-F18 | H18: =历资表!D18 | J18: =H18-I18 | K18: =历资表!E18 | M18: =K18-L18
A19: =历资表!A19 | B19: =历资表!B19 | D19: =B19-C19 | E19: =历资表!C19 | G19: =E19-F19 | H19: =历资表!D19 | J19: =H19-I19 | K19: =历资表!E19 | L19: =K19 | M19: =K19-L19
A20: =历资表!A20 | B20: =历资表!B20 | D20: =B20-C20 | E20: =历资表!C20 | G20: =E20-F20 | H20: =历资表!D20 | J20: =H20-I20 | K20: =历资表!E20 | M20: =K20-L20
A21: =历资表!A21 | B21: =历资表!B21 | D21: =B21-C21 | E21: =历资表!C21 | G21: =E21-F21 | H21: =历资表!D21 | J21: =H21-I21 | K21: =历资表!E21 | M21: =K21-L21
A22: =历资表!A22 | B22: =历资表!B22 | D22: =B22-C22 | E22: =历资表!C22 | G22: =E22-F22 | H22: =历资表!D22 | J22: =H22-I22 | K22: =历资表!E22 | M22: =K22-L22
A23: =历资表!A23 | B23: =历资表!B23 | D23: =B23-C23 | E23: =历资表!C23 | G23: =E23-F23 | H23: =历资表!D23 | J23: =H23-I23 | K23: =历资表!E23 | M23: =K23-L23
A24: =历资表!A24 | B24: =历资表!B24 | D24: =B24-C24 | E24: =历资表!C24 | G24: =E24-F24 | H24: =历资表!D24 | J24: =H24-I24 | K24: =历资表!E24 | M24: =K24-L24
A25: =历资表!A25 | B25: =历资表!B25 | D25: =B25-C25 | E25: =历资表!C25 | G25: =E25-F25 | H25: =历资表!D25 | J25: =H25-I25 | K25: =历资表!E25 | M25: =K25-L25
A26: =历资表!A26 | B26: =历资表!B26 | C26: =SUM(C7:C25) | D26: =B26-C26 | E26: =历资表!C26 | F26: =SUM(F7:F25) | G26: =E26-F26 | H26: =历资表!D26 | I26: =SUM(I7:I25) | J26: =H26-I26 | K26: =历资表!E26 | L26: =SUM(L7:L25) | M26: =K26-L26
A27: =历资表!A27
A28: =历资表!A28 | B28: =历资表!B28 | D28: =B28-C28 | E28: =历资表!C28 | G28: =E28-F28 | H28: =历资表!D28 | J28: =H28-I28 | K28: =历资表!E28 | M28: =K28-L28
A29: =历资表!A29 | B29: =历资表!B29 | D29: =B29-C29 | E29: =历资表!C29 | G29: =E29-F29 | H29: =历资表!D29 | J29: =H29-I29 | K29: =历资表!E29 | M29: =K29-L29
A30: =历资表!A30 | B30: =历资表!B30 | D30: =B30-C30 | E30: =历资表!C30 | G30: =E30-F30 | H30: =历资表!D30 | J30: =H30-I30 | K30: =历资表!E30 | M30: =K30-L30
A31: =历资表!A31 | B31: =历资表!B31 | D31: =B31-C31 | E31: =历资表!C31 | G31: =E31-F31 | H31: =历资表!D31 | J31: =H31-I31 | K31: =历资表!E31 | M31: =K31-L31
A32: =历资表!A32 | B32: =历资表!B32 | D32: =B32-C32 | E32: =历资表!C32 | G32: =E32-F32 | H32: =历资表!D32 | J32: =H32-I32 | K32: =历资表!E32 | L32: =K32 | M32: =K32-L32
A33: =历资表!A33 | B33: =历资表!B33 | D33: =B33-C33 | E33: =历资表!C33 | G33: =E33-F33 | H33: =历资表!D33 | J33: =H33-I33 | K33: =历资表!E33 | M33: =K33-L33
A34: =历资表!A34 | B34: =历资表!B34 | D34: =B34-C34 | E34: =历资表!C34 | G34: =E34-F34 | H34: =历资表!D34 | J34: =H34-I34 | K34: =历资表!E34 | M34: =K34-L34
A35: =历资表!A35 | B35: =历资表!B35 | D35: =B35-C35 | E35: =历资表!C35 | G35: =E35-F35 | H35: =历资表!D35 | J35: =H35-I35 | K35: =历资表!E35 | M35: =K35-L35
A36: =历资表!A36 | B36: =历资表!B36 | D36: =B36-C36 | E36: =历资表!C36 | G36: =E36-F36 | H36: =历资表!D36 | J36: =H36-I36 | K36: =历资表!E36 | M36: =K36-L36
A37: =历资表!A37 | B37: =历资表!B37 | D37: =B37-C37 | E37: =历资表!C37 | G37: =E37-F37 | H37: =历资表!D37 | J37: =H37-I37 | K37: =历资表!E37 | M37: =K37-L37
A38: =历资表!A38 | B38: =历资表!B38 | D38: =B38-C38 | E38: =历资表!C38 | G38: =E38-F38 | H38: =历资表!D38 | J38: =H38-I38 | K38: =历资表!E38 | M38: =K38-L38
A39: =历资表!A39 | B39: =历资表!B39 | D39: =B39-C39 | E39: =历资表!C39 | G39: =E39-F39 | H39: =历资表!D39 | J39: =H39-I39 | K39: =历资表!E39 | M39: =K39-L39
A40: =历资表!A40 | B40: =历资表!B40 | D40: =B40-C40 | E40: =历资表!C40 | G40: =E40-F40 | H40: =历资表!D40 | J40: =H40-I40 | K40: =历资表!E40 | M40: =K40-L40
A41: =历资表!A41 | B41: =历资表!B41 | D41: =B41-C41 | E41: =历资表!C41 | G41: =E41-F41 | H41: =历资表!D41 | J41: =H41-I41 | K41: =历资表!E41 | M41: =K41-L41
A42: =历资表!A42 | B42: =历资表!B42 | D42: =B42-C42 | E42: =历资表!C42 | G42: =E42-F42 | H42: =历资表!D42 | J42: =H42-I42 | K42: =历资表!E42 | M42: =K42-L42
A43: =历资表!A43 | B43: =历资表!B43 | D43: =B43-C43 | E43: =历资表!C43 | G43: =E43-F43 | H43: =历资表!D43 | J43: =H43-I43 | K43: =历资表!E43 | M43: =K43-L43
A44: =历资表!A44 | B44: =历资表!B44 | D44: =B44-C44 | E44: =历资表!C44 | G44: =E44-F44 | H44: =历资表!D44 | J44: =H44-I44 | K44: =历资表!E44 | L44: =K44 | M44: =K44-L44
A45: =历资表!A45 | B45: =历资表!B45 | D45: =B45-C45 | E45: =历资表!C45 | G45: =E45-F45 | H45: =历资表!D45 | J45: =H45-I45 | K45: =历资表!E45 | M45: =K45-L45
A46: =历资表!A46 | B46: =历资表!B46 | C46: =SUM(C28:C45) | D46: =B46-C46 | E46: =历资表!C46 | F46: =SUM(F28:F45) | G46: =E46-F46 | H46: =历资表!D46 | I46: =SUM(I28:I45) | J46: =H46-I46 | K46: =历资表!E46 | L46: =SUM(L28:L45) | M46: =K46-L46
A47: =历资表!A47 | B47: =历资表!B47 | C47: =C26+C46 | D47: =B47-C47 | E47: =历资表!C47 | F47: =F26+F46 | G47: =E47-F47 | H47: =历资表!D47 | I47: =I26+I46 | J47: =H47-I47 | K47: =历资表!E47 | L47: =L26+L46 | M47: =K47-L47
A48: =历资表!A48
A49: =历资表!A49 | B49: =历资表!B49 | D49: =B49-C49 | E49: =历资表!C49 | G49: =E49-F49 | H49: =历资表!D49 | J49: =H49-I49 | K49: =历资表!E49 | M49: =K49-L49
A50: =历资表!A50 | B50: =历资表!B50 | D50: =B50-C50 | E50: =历资表!C50 | G50: =E50-F50 | H50: =历资表!D50 | J50: =H50-I50 | K50: =历资表!E50 | M50: =K50-L50
A51: =历资表!A51 | B51: =历资表!B51 | D51: =B51-C51 | E51: =历资表!C51 | G51: =E51-F51 | H51: =历资表!D51 | J51: =H51-I51 | K51: =历资表!E51 | M51: =K51-L51
A52: =历资表!A52 | B52: =历资表!B52 | D52: =B52-C52 | E52: =历资表!C52 | G52: =E52-F52 | H52: =历资表!D52 | J52: =H52-I52 | K52: =历资表!E52 | M52: =K52-L52
A53: =历资表!A53 | B53: =历资表!B53 | D53: =B53-C53 | E53: =历资表!C53 | G53: =E53-F53 | H53: =历资表!D53 | J53: =H53-I53 | K53: =历资表!E53 | M53: =K53-L53
A54: =历资表!A54 | B54: =历资表!B54 | D54: =B54-C54 | E54: =历资表!C54 | G54: =E54-F54 | H54: =历资表!D54 | J54: =H54-I54 | K54: =历资表!E54 | M54: =K54-L54
A55: =历资表!A55 | B55: =历资表!B55 | D55: =B55-C55 | E55: =历资表!C55 | G55: =E55-F55 | H55: =历资表!D55 | J55: =H55-I55 | K55: =历资表!E55 | M55: =K55-L55
A56: =历资表!A56 | B56: =历资表!B56 | D56: =B56-C56 | E56: =历资表!C56 | G56: =E56-F56 | H56: =历资表!D56 | J56: =H56-I56 | K56: =历资表!E56 | M56: =K56-L56
A57: =历资表!A57 | B57: =历资表!B57 | D57: =B57-C57 | E57: =历资表!C57 | G57: =E57-F57 | H57: =历资表!D57 | J57: =H57-I57 | K57: =历资表!E57 | M57: =K57-L57
A58: =历资表!A58 | B58: =历资表!B58 | D58: =B58-C58 | E58: =历资表!C58 | G58: =E58-F58 | H58: =历资表!D58 | J58: =H58-I58 | K58: =历资表!E58 | M58: =K58-L58
A59: =历资表!A59 | B59: =历资表!B59 | D59: =B59-C59 | E59: =历资表!C59 | G59: =E59-F59 | H59: =历资表!D59 | J59: =H59-I59 | K59: =历资表!E59 | M59: =K59-L59
A60: =历资表!A60 | B60: =历资表!B60 | D60: =B60-C60 | E60: =历资表!C60 | G60: =E60-F60 | H60: =历资表!D60 | J60: =H60-I60 | K60: =历资表!E60 | M60: =K60-L60
... A65: =历资表!A65 | B65: =历资表!B65 | D65: =B65-C65 | E65: =历资表!C65 | G65: =E65-F65 | H65: =历资表!D65 | J65: =H65-I65 | K65: =历资表!E65 | M65: =K65-L65
A66: =历资表!A66 | B66: =历资表!B66 | D66: =B66-C66 | E66: =历资表!C66 | G66: =E66-F66 | H66: =历资表!D66 | J66: =H66-I66 | K66: =历资表!E66 | L66: =K66 | M66: =K66-L66
A67: =历资表!A67 | B67: =历资表!B67 | D67: =B67-C67 | E67: =历资表!C67 | G67: =E67-F67 | H67: =历资表!D67 | J67: =H67-I67 | K67: =历资表!E67 | M67: =K67-L67
A68: =历资表!A68 | B68: =历资表!B68 | D68: =B68-C68 | E68: =历资表!C68 | G68: =E68-F68 | H68: =历资表!D68 | J68: =H68-I68 | K68: =历资表!E68 | M68: =K68-L68
A69: =历资表!A69 | B69: =历资表!B69 | D69: =B69-C69 | E69: =历资表!C69 | G69: =E69-F69 | H69: =历资表!D69 | J69: =H69-I69 | K69: =历资表!E69 | M69: =K69-L69
A70: =历资表!A70 | B70: =历资表!B70 | C70: =SUM(C49:C69) | D70: =B70-C70 | E70: =历资表!C70 | F70: =SUM(F49:F69) | G70: =E70-F70 | H70: =历资表!D70 | I70: =SUM(I49:I69) | J70: =H70-I70 | K70: =历资表!E70 | L70: =SUM(L49:L69) | M70: =K70-L70
A71: =历资表!A71
A72: =历资表!A72 | B72: =历资表!B72 | D72: =B72-C72 | E72: =历资表!C72 | G72: =E72-F72 | H72: =历资表!D72 | J72: =H72-I72 | K72: =历资表!E72 | M72: =K72-L72
A73: =历资表!A73 | B73: =历资表!B73 | D73: =B73-C73 | E73: =历资表!C73 | G73: =E73-F73 | H73: =历资表!D73 | J73: =H73-I73 | K73: =历资表!E73 | M73: =K73-L73
A74: =历资表!A74 | B74: =历资表!B74 | D74: =B74-C74 | E74: =历资表!C74 | G74: =E74-F74 | H74: =历资表!D74 | J74: =H74-I74 | K74: =历资表!E74 | M74: =K74-L74
A75: =历资表!A75 | B75: =历资表!B75 | D75: =B75-C75 | E75: =历资表!C75 | G75: =E75-F75 | H75: =历资表!D75 | J75: =H75-I75 | K75: =历资表!E75 | M75: =K75-L75
A76: =历资表!A76 | B76: =历资表!B76 | D76: =B76-C76 | E76: =历资表!C76 | G76: =E76-F76 | H76: =历资表!D76 | J76: =H76-I76 | K76: =历资表!E76 | M76: =K76-L76
A77: =历资表!A77 | B77: =历资表!B77 | D77: =B77-C77 | E77: =历资表!C77 | G77: =E77-F77 | H77: =历资表!D77 | J77: =H77-I77 | K77: =历资表!E77 | M77: =K77-L77
A78: =历资表!A78 | B78: =历资表!B78 | D78: =B78-C78 | E78: =历资表!C78 | G78: =E78-F78 | H78: =历资表!D78 | J78: =H78-I78 | K78: =历资表!E78 | M78: =K78-L78
A79: =历资表!A79 | B79: =历资表!B79 | D79: =B79-C79 | E79: =历资表!C79 | G79: =E79-F79 | H79: =历资表!D79 | J79: =H79-I79 | K79: =历资表!E79 | M79: =K79-L79
A80: =历资表!A80 | B80: =历资表!B80 | D80: =B80-C80 | E80: =历资表!C80 | G80: =E80-F80 | H80: =历资表!D80 | J80: =H80-I80 | K80: =历资表!E80 | L80: =K80 | M80: =K80-L80
A81: =历资表!A81 | B81: =历资表!B81 | D81: =B81-C81 | E81: =历资表!C81 | G81: =E81-F81 | H81: =历资表!D81 | J81: =H81-I81 | K81: =历资表!E81 | M81: =K81-L81
A82: =历资表!A82 | B82: =历资表!B82 | C82: =SUM(C72:C73,C76:C81) | D82: =B82-C82 | E82: =历资表!C82 | F82: =SUM(F72:F73,F76:F81) | G82: =E82-F82 | H82: =历资表!D82 | I82: =SUM(I72:I73,I76:I81) | J82: =H82-I82 | K82: =历资表!E82 | L82: =SUM(L72:L73,L76:L81) | M82: =K82-L82
A83: =历资表!A83 | B83: =历资表!B83 | C83: =C70+C82 | D83: =B83-C83 | E83: =历资表!C83 | F83: =F70+F82 | G83: =E83-F83 | H83: =历资表!D83 | I83: =I70+I82 | J83: =H83-I83 | K83: =历资表!E83 | L83: =L70+L82 | M83: =K83-L83
A84: =历资表!A84
A85: =历资表!A85 | B85: =历资表!B85 | D85: =B85-C85 | E85: =历资表!C85 | G85: =E85-F85 | H85: =历资表!D85 | J85: =H85-I85 | K85: =历资表!E85 | M85: =K85-L85
A86: =历资表!A86 | B86: =历资表!B86 | D86: =B86-C86 | E86: =历资表!C86 | G86: =E86-F86 | H86: =历资表!D86 | J86: =H86-I86 | K86: =历资表!E86 | M86: =K86-L86
A87: =历资表!A87 | B87: =历资表!B87 | D87: =B87-C87 | E87: =历资表!C87 | G87: =E87-F87 | H87: =历资表!D87 | J87: =H87-I87 | K87: =历资表!E87 | M87: =K87-L87
A88: =历资表!A88 | B88: =历资表!B88 | D88: =B88-C88 | E88: =历资表!C88 | G88: =E88-F88 | H88: =历资表!D88 | J88: =H88-I88 | K88: =历资表!E88 | M88: =K88-L88
A89: =历资表!A89 | B89: =历资表!B89 | D89: =B89-C89 | E89: =历资表!C89 | G89: =E89-F89 | H89: =历资表!D89 | J89: =H89-I89 | K89: =历资表!E89 | M89: =K89-L89
A90: =历资表!A90 | B90: =历资表!B90 | D90: =B90-C90 | E90: =历资表!C90 | G90: =E90-F90 | H90: =历资表!D90 | J90: =H90-I90 | K90: =历资表!E90 | M90: =K90-L90
A91: =历资表!A91 | B91: =历资表!B91 | D91: =B91-C91 | E91: =历资表!C91 | G91: =E91-F91 | H91: =历资表!D91 | J91: =H91-I91 | K91: =历资表!E91 | M91: =K91-L91
A92: =历资表!A92 | B92: =历资表!B92 | D92: =B92-C92 | E92: =历资表!C92 | G92: =E92-F92 | H92: =历资表!D92 | J92: =H92-I92 | K92: =历资表!E92 | M92: =K92-L92
A93: =历资表!A93 | B93: =历资表!B93 | D93: =B93-C93 | E93: =历资表!C93 | G93: =E93-F93 | H93: =历资表!D93 | J93: =H93-I93 | K93: =历资表!E93 | M93: =K93-L93
A94: =历资表!A94 | B94: =历资表!B94 | D94: =B94-C94 | E94: =历资表!C94 | G94: =E94-F94 | H94: =历资表!D94 | J94: =H94-I94 | K94: =历资表!E94 | M94: =K94-L94
A95: =历资表!A95 | B95: =历资表!B95 | D95: =B95-C95 | E95: =历资表!C95 | G95: =E95-F95 | H95: =历资表!D95 | J95: =H95-I95 | K95: =历资表!E95 | M95: =K95-L95
A96: =历资表!A96 | B96: =历资表!B96 | C96: =C85+C86+C89-C90+C91+C92+C93+C94+C95 | D96: =B96-C96 | E96: =历资表!C96 | F96: =F85+F86+F89-F90+F91+F92+F93+F94+F95 | G96: =E96-F96 | H96: =历资表!D96 | I96: =I85+I86+I89-I90+I91+I92+I93+I94+I95 | J96: =H96-I96 | K96: =历资表!E96 | L96: =L85+L86+L89-L90+L91+L92+L93+L94+L95 | M96: =K96-L96
A97: =历资表!A97 | B97: =历资表!B97 | D97: =B97-C97 | E97: =历资表!C97 | G97: =E97-F97 | H97: =历资表!D97 | J97: =H97-I97 | K97: =历资表!E97 | M97: =K97-L97
A98: =历资表!A98 | B98: =历资表!B98 | C98: =SUM(C96:C97) | D98: =B98-C98 | E98: =历资表!C98 | F98: =SUM(F96:F97) | G98: =E98-F98 | H98: =历资表!D98 | I98: =SUM(I96:I97) | J98: =H98-I98 | K98: =历资表!E98 | L98: =SUM(L96:L97) | M98: =K98-L98
A99: =历资表!A99 | B99: =历资表!B99 | C99: =C83+C98 | D99: =B99-C99 | E99: =历资表!C99 | F99: =F83+F98 | G99: =E99-F99 | H99: =历资表!D99 | I99: =I83+I98 | J99: =H99-I99 | K99: =历资表!E99 | L99: =L83+L98 | M99: =K99-L99
A101: 核对 | B101: =SUM(历资表!B6:'历资表'!B99)-SUM(B6:B99) | D101: =D47-D99 | E101: =SUM(历资表!C6:'历资表'!C99)-SUM(E6:E99) | G101: =G47-G99 | H101: =SUM(历资表!D6:'历资表'!D99)-SUM(H6:H99) | J101: =J47-J99 | K101: =SUM(历资表!E6:'历资表'!E99)-SUM(K6:K99) | M101: =M47-M99

Sheet 历利调整后表
A1: 历史损益调整分析表 | O1: =HYPERLINK("#目录1!A1","返回目录")
A2: 评估基准日：{{VALUATION_BASE_DATE}}
A3: ="被评估单位："&项目信息!B5&"" | N3: ="金额单位："&项目信息!B8&""
A4: 项目\年份 | B4: 2022年度 | E4: 2023年度 | H4: 2024年度 | K4: 2025年1-6月 | N4: 调整分析说明
B5: 账面值/审定值 | C5: 其中：非经营性资产产生的损益 | D5: 调整后损益数据 | E5: 账面值/审定值 | F5: 其中：非经营性资产产生的损益 | G5: 调整后损益数据 | H5: 账面值/审定值 | I5: 其中：非经营性资产产生的损益 | J5: 调整后损益数据 | K5: 账面值/审定值 | L5: 其中：非经营性资产产生的损益 | M5: 调整后损益数据
A6: =历利表!A6 | B6: =历利表!B6 | C6: =C7+SUM(C10:C12) | D6: =B6-C6 | E6: =历利表!C6 | F6: =F7+SUM(F10:F12) | G6: =E6-F6 | H6: =历利表!D6 | I6: =I7+SUM(I10:I12) | J6: =H6-I6 | K6: =历利表!E6 | L6: =L7+SUM(L10:L12) | M6: =K6-L6
A7: =历利表!A7 | B7: =历利表!B7 | C7: =C8+C9 | D7: =B7-C7 | E7: =历利表!C7 | F7: =F8+F9 | G7: =E7-F7 | H7: =历利表!D7 | I7: =I8+I9 | J7: =H7-I7 | K7: =历利表!E7 | L7: =L8+L9 | M7: =K7-L7
A8: =历利表!A8 | B8: =历利表!B8 | D8: =B8-C8 | E8: =历利表!C8 | G8: =E8-F8 | H8: =历利表!D8 | J8: =H8-I8 | K8: =历利表!E8 | M8: =K8-L8
A9: =历利表!A9 | B9: =历利表!B9 | D9: =B9-C9 | E9: =历利表!C9 | G9: =E9-F9 | H9: =历利表!D9 | J9: =H9-I9 | K9: =历利表!E9 | M9: =K9-L9
A10: =历利表!A10 | B10: =历利表!B10 | D10: =B10-C10 | E10: =历利表!C10 | G10: =E10-F10 | H10: =历利表!D10 | J10: =H10-I10 | K10: =历利表!E10 | M10: =K10-L10
A11: =历利表!A11 | B11: =历利表!B11 | D11: =B11-C11 | E11: =历利表!C11 | G11: =E11-F11 | H11: =历利表!D11 | J11: =H11-I11 | K11: =历利表!E11 | M11: =K11-L11
A12: =历利表!A12 | B12: =历利表!B12 | D12: =B12-C12 | E12: =历利表!C12 | G12: =E12-F12 | H12: =历利表!D12 | J12: =H12-I12 | K12: =历利表!E12 | M12: =K12-L12
A13: =历利表!A13 | B13: =历利表!B13 | C13: =C14+SUM(C17:C28) | D13: =B13-C13 | E13: =历利表!C13 | F13: =F14+SUM(F17:F28) | G13: =E13-F13 | H13: =历利表!D13 | I13: =I14+SUM(I17:I28) | J13: =H13-I13 | K13: =历利表!E13 | L13: =L14+SUM(L17:L28) | M13: =K13-L13
A14: =历利表!A14 | B14: =历利表!B14 | C14: =C15+C16 | D14: =B14-C14 | E14: =历利表!C14 | F14: =F15+F16 | G14: =E14-F14 | H14: =历利表!D14 | I14: =I15+I16 | J14: =H14-I14 | K14: =历利表!E14 | L14: =L15+L16 | M14: =K14-L14
A15: =历利表!A15 | B15: =历利表!B15 | D15: =B15-C15 | E15: =历利表!C15 | G15: =E15-F15 | H15: =历利表!D15 | J15: =H15-I15 | K15: =历利表!E15 | M15: =K15-L15
A16: =历利表!A16 | B16: =历利表!B16 | D16: =B16-C16 | E16: =历利表!C16 | G16: =E16-F16 | H16: =历利表!D16 | J16: =H16-I16 | K16: =历利表!E16 | M16: =K16-L16
A17: =历利表!A17 | B17: =历利表!B17 | D17: =B17-C17 | E17: =历利表!C17 | G17: =E17-F17 | H17: =历利表!D17 | J17: =H17-I17 | K17: =历利表!E17 | M17: =K17-L17
A18: =历利表!A18 | B18: =历利表!B18 | D18: =B18-C18 | E18: =历利表!C18 | G18: =E18-F18 | H18: =历利表!D18 | J18: =H18-I18 | K18: =历利表!E18 | M18: =K18-L18
A19: =历利表!A19 | B19: =历利表!B19 | D19: =B19-C19 | E19: =历利表!C19 | G19: =E19-F19 | H19: =历利表!D19 | J19: =H19-I19 | K19: =历利表!E19 | M19: =K19-L19
A20: =历利表!A20 | B20: =历利表!B20 | D20: =B20-C20 | E20: =历利表!C20 | G20: =E20-F20 | H20: =历利表!D20 | J20: =H20-I20 | K20: =历利表!E20 | M20: =K20-L20
A21: =历利表!A21 | B21: =历利表!B21 | D21: =B21-C21 | E21: =历利表!C21 | G21: =E21-F21 | H21: =历利表!D21 | J21: =H21-I21 | K21: =历利表!E21 | M21: =K21-L21
A22: =历利表!A22 | B22: =历利表!B22 | D22: =B22-C22 | E22: =历利表!C22 | G22: =E22-F22 | H22: =历利表!D22 | J22: =H22-I22 | K22: =历利表!E22 | M22: =K22-L22
A23: =历利表!A23 | B23: =历利表!B23 | D23: =B23-C23 | E23: =历利表!C23 | G23: =E23-F23 | H23: =历利表!D23 | J23: =H23-I23 | K23: =历利表!E23 | M23: =K23-L23
A24: =历利表!A24 | B24: =历利表!B24 | D24: =B24-C24 | E24: =历利表!C24 | G24: =E24-F24 | H24: =历利表!D24 | J24: =H24-I24 | K24: =历利表!E24 | M24: =K24-L24
A25: =历利表!A25 | B25: =历利表!B25 | D25: =B25-C25 | E25: =历利表!C25 | G25: =E25-F25 | H25: =历利表!D25 | J25: =H25-I25 | K25: =历利表!E25 | M25: =K25-L25
A26: =历利表!A26 | B26: =历利表!B26 | D26: =B26-C26 | E26: =历利表!C26 | G26: =E26-F26 | H26: =历利表!D26 | J26: =H26-I26 | K26: =历利表!E26 | M26: =K26-L26
... A40: =历利表!A40 | B40: =历利表!B40 | D40: =B40-C40 | E40: =历利表!C40 | G40: =E40-F40 | H40: =历利表!D40 | J40: =H40-I40 | K40: =历利表!E40 | M40: =K40-L40
A41: =历利表!A41 | B41: =历利表!B41 | C41: =C6-C13+SUM(C31:C32)+SUM(C35:C40) | D41: =B41-C41 | E41: =历利表!C41 | F41: =F6-F13+SUM(F31:F32)+SUM(F35:F40) | G41: =E41-F41 | H41: =历利表!D41 | I41: =I6-I13+SUM(I31:I32)+SUM(I35:I40) | J41: =H41-I41 | K41: =历利表!E41 | L41: =L6-L13+SUM(L31:L32)+SUM(L35:L40) | M41: =K41-L41
A42: =历利表!A42 | B42: =历利表!B42 | D42: =B42-C42 | E42: =历利表!C42 | G42: =E42-F42 | H42: =历利表!D42 | J42: =H42-I42 | K42: =历利表!E42 | M42: =K42-L42
A43: =历利表!A43 | B43: =历利表!B43 | D43: =B43-C43 | E43: =历利表!C43 | G43: =E43-F43 | H43: =历利表!D43 | J43: =H43-I43 | K43: =历利表!E43 | M43: =K43-L43
A44: =历利表!A44 | B44: =历利表!B44 | C44: =C41+C42-C43 | D44: =B44-C44 | E44: =历利表!C44 | F44: =F41+F42-F43 | G44: =E44-F44 | H44: =历利表!D44 | I44: =I41+I42-I43 | J44: =H44-I44 | K44: =历利表!E44 | L44: =L41+L42-L43 | M44: =K44-L44
A45: =历利表!A45 | B45: =历利表!B45 | D45: =B45-C45 | E45: =历利表!C45 | G45: =E45-F45 | H45: =历利表!D45 | J45: =H45-I45 | K45: =历利表!E45 | M45: =K45-L45
A46: =历利表!A46 | B46: =历利表!B46 | C46: =C44-C45 | D46: =B46-C46 | E46: =历利表!C46 | F46: =F44-F45 | G46: =E46-F46 | H46: =历利表!D46 | I46: =I44-I45 | J46: =H46-I46 | K46: =历利表!E46 | L46: =L44-L45 | M46: =K46-L46
A47: =历利表!A47 | B47: =历利表!B47 | D47: =B47-C47 | E47: =历利表!C47 | G47: =E47-F47 | H47: =历利表!D47 | J47: =H47-I47 | K47: =历利表!E47 | M47: =K47-L47
A48: =历利表!A48 | B48: =历利表!B48 | D48: =B48-C48 | E48: =历利表!C48 | G48: =E48-F48 | H48: =历利表!D48 | J48: =H48-I48 | K48: =历利表!E48 | M48: =K48-L48
A49: =历利表!A49 | B49: =历利表!B49 | D49: =B49-C49 | E49: =历利表!C49 | G49: =E49-F49 | H49: =历利表!D49 | J49: =H49-I49 | K49: =历利表!E49 | M49: =K49-L49
A50: =历利表!A50 | B50: =历利表!B50 | C50: =C46-C49 | D50: =B50-C50 | E50: =历利表!C50 | F50: =F46-F49 | G50: =E50-F50 | H50: =历利表!D50 | I50: =I46-I49 | J50: =H50-I50 | K50: =历利表!E50 | L50: =L46-L49 | M50: =K50-L50
A52: 核对 | B52: =SUM(历利表!B6:'历利表'!B50)-SUM(B6:B50) | E52: =SUM(历利表!C6:'历利表'!C50)-SUM(E6:E50) | H52: =SUM(历利表!D6:'历利表'!D50)-SUM(H6:H50) | K52: =SUM(历利表!E6:'历利表'!E50)-SUM(K6:K50)

Sheet 评估结果汇总表
A1: 评估结果汇总表 | F1: =HYPERLINK("#目录1!A1","返回目录")
A2: 评估基准日：{{VALUATION_BASE_DATE}}
A3: ="被评估单位："&项目信息!B5&"" | E3: ="金额单位："&项目信息!B8&""
A4: 项目 | B4: 账面值 | C4: 评估值 | D4: 评估增减值 | E4: 增减值率(%)
A5: 流动资产 | B5: =历资表!E26
A6: 非流动资产 | B6: =历资表!E46
A7: 其中：可供出售金融资产 | B7: =历资表!E28
A8: 债权投资 | B8: =历资表!E29
A9: 其他债权投资 | B9: =历资表!E30
A10: 长期应收款 | B10: =历资表!E31
A11: 长期股权投资 | B11: =历资表!E32
A12: 其他权益工具投资 | B12: =历资表!E33
A13: 其他非流动金融资产 | B13: =历资表!E34
A14: 投资性房地产 | B14: =历资表!E35
A15: 固定资产净额 | B15: =历资表!E36
A16: 在建工程 | B16: =历资表!E37
A17: 工程物资 | B17: =历资表!E38
A18: 使用权资产 | B18: =历资表!E39
... A24: 其他非流动资产 | B24: =历资表!E45
A25: 资产总计 | B25: =B5+B6
A26: 流动负债 | B26: =历资表!E70
A27: 非流动负债 | B27: =历资表!E82
A28: 负债总计 | B28: =B27+B26
A29: 净资产（所有者权益） | B29: =历资表!E98
A30: 归属母公司所有者权益 | B30: =历资表!E96 | D30: =C30-B30 | E30: =D30/B30
A32: 核对 | B32: =B25-B28-B29

Sheet 净现金流计算表
A1: 净现金流计算表 | N1: =HYPERLINK("#目录1!A1","返回目录")
A2: 评估基准日：{{VALUATION_BASE_DATE}}
A3: ="被评估单位："&项目信息!B5&"" | M3: ="金额单位："&项目信息!B8&""
A4: 项目名称 | C4: 历史数据 | G4: 未来预测
C5: 2022年度 | D5: 2023年度 | E5: 2024年度 | F5: 2025年1-6月 | G5: 2025年7-12月 | H5: 2026年度 | I5: 2027年度 | J5: 2028年度 | K5: 2029年度 | L5: 2030年度 | M5: 永续年度
A6: 一、营业总收入 | C6: =SUM(C7) | D6: =SUM(D7) | E6: =SUM(E7) | F6: =SUM(F7) | G6: =SUM(G7) | H6: =SUM(H7) | I6: =SUM(I7) | J6: =SUM(J7) | ... M6: =SUM(M7)
A7: 其中：营业收入 | C7: =营业收入表!C17 | D7: =营业收入表!D17 | E7: =营业收入表!E17 | F7: =营业收入表!F17 | G7: =营业收入表!G17 | H7: =营业收入表!H17 | I7: =营业收入表!I17 | J7: =营业收入表!J17 | ... M7: =营业收入表!M17
A8: 二、营业总成本 | C8: =SUM(C9:C14) | D8: =SUM(D9:D14) | E8: =SUM(E9:E14) | F8: =SUM(F9:F14) | G8: =SUM(G9:G14) | H8: =SUM(H9:H14) | I8: =SUM(I9:I14) | J8: =SUM(J9:J14) | ... M8: =SUM(M9:M14)
A9: 其中：营业成本 | C9: =营业成本表!C17 | D9: =营业成本表!D17 | E9: =营业成本表!E17 | F9: =营业成本表!F17 | G9: =营业成本表!G17 | H9: =营业成本表!H17 | I9: =营业成本表!I17 | J9: =营业成本表!J17 | ... M9: =营业成本表!M17
A10: 税金及附加 | C10: =税金及附加表!C27 | D10: =税金及附加表!D27 | E10: =税金及附加表!E27 | F10: =税金及附加表!F27 | G10: =税金及附加表!G27 | H10: =税金及附加表!H27 | I10: =税金及附加表!I27 | J10: =税金及附加表!J27 | ... M10: =税金及附加表!M27
A11: 销售费用 | C11: =销售费用表!C62 | D11: =销售费用表!D62 | E11: =销售费用表!E62 | F11: =销售费用表!F62 | G11: =销售费用表!G62 | H11: =销售费用表!H62 | I11: =销售费用表!I62 | J11: =销售费用表!J62 | ... M11: =销售费用表!M62
A12: 管理费用 | C12: =管理费用表!C62 | D12: =管理费用表!D62 | E12: =管理费用表!E62 | F12: =管理费用表!F62 | G12: =管理费用表!G62 | H12: =管理费用表!H62 | I12: =管理费用表!I62 | J12: =管理费用表!J62 | ... M12: =管理费用表!M62
A13: 研发费用 | C13: =研发费用表!C63 | D13: =研发费用表!D63 | E13: =研发费用表!E63 | F13: =研发费用表!F63 | G13: =研发费用表!G63 | H13: =研发费用表!H63 | I13: =研发费用表!I63 | J13: =研发费用表!J63 | ... M13: =研发费用表!M63
A14: 财务费用 | C14: =财务费用表!C15 | D14: =财务费用表!D15 | E14: =财务费用表!E15 | F14: =财务费用表!F15 | G14: =财务费用表!G15 | H14: =财务费用表!H15 | I14: =财务费用表!I15 | J14: =财务费用表!J15 | ... M14: =财务费用表!M15
A15: 加：其他收益 | C15: =其他收益表!C9 | D15: =其他收益表!D9 | E15: =其他收益表!E9 | F15: =其他收益表!F9 | G15: =其他收益表!G9 | H15: =其他收益表!H9 | I15: =其他收益表!I9 | J15: =其他收益表!J9 | ... M15: =其他收益表!M9
A16: 投资收益（损失以“-”号填列） | C16: =投资收益表!C9 | D16: =投资收益表!D9 | E16: =投资收益表!E9 | F16: =投资收益表!F9 | G16: =投资收益表!G9 | H16: =投资收益表!H9 | I16: =投资收益表!I9 | J16: =投资收益表!J9 | ... M16: =投资收益表!M9
A17: 汇兑收益（损失以“-”号填列） | C17: =汇兑收益表!C9 | D17: =汇兑收益表!D9 | E17: =汇兑收益表!E9 | F17: =汇兑收益表!F9 | G17: =汇兑收益表!G9 | H17: =汇兑收益表!H9 | I17: =汇兑收益表!I9 | J17: =汇兑收益表!J9 | ... M17: =汇兑收益表!M9
A18: 净敞口套期收益（损失以“-”号填列） | C18: =净敞口套期收益表!C9 | D18: =净敞口套期收益表!D9 | E18: =净敞口套期收益表!E9 | F18: =净敞口套期收益表!F9 | G18: =净敞口套期收益表!G9 | H18: =净敞口套期收益表!H9 | I18: =净敞口套期收益表!I9 | J18: =净敞口套期收益表!J9 | ... M18: =净敞口套期收益表!M9
A19: 公允价值变动收益（损失以“-”号填列） | C19: =公允价值变动收益表!C9 | D19: =公允价值变动收益表!D9 | E19: =公允价值变动收益表!E9 | F19: =公允价值变动收益表!F9 | G19: =公允价值变动收益表!G9 | H19: =公允价值变动收益表!H9 | I19: =公允价值变动收益表!I9 | J19: =公允价值变动收益表!J9 | ... M19: =公允价值变动收益表!M9
A20: 信用减值损失（损失以“-”号填列） | C20: =-信用减值损失表!C9 | D20: =-信用减值损失表!D9 | E20: =-信用减值损失表!E9 | F20: =-信用减值损失表!F9 | G20: =-信用减值损失表!G9 | H20: =-信用减值损失表!H9 | I20: =-信用减值损失表!I9 | J20: =-信用减值损失表!J9 | ... M20: =-信用减值损失表!M9
A21: 资产减值损失（损失以“-”号填列） | C21: =-资产减值损失表!C9 | D21: =-资产减值损失表!D9 | E21: =-资产减值损失表!E9 | F21: =-资产减值损失表!F9 | G21: =-资产减值损失表!G9 | H21: =-资产减值损失表!H9 | I21: =-资产减值损失表!I9 | J21: =-资产减值损失表!J9 | ... M21: =-资产减值损失表!M9
A22: 资产处置收益（损失以“-”号填列） | C22: =资产处置收益表!C9 | D22: =资产处置收益表!D9 | E22: =资产处置收益表!E9 | F22: =资产处置收益表!F9 | G22: =资产处置收益表!G9 | H22: =资产处置收益表!H9 | I22: =资产处置收益表!I9 | J22: =资产处置收益表!J9 | ... M22: =资产处置收益表!M9
A23: 三、营业利润（亏损以“-”号填列） | C23: =C6-C8+SUM(C15:C16,C17:C22) | D23: =D6-D8+SUM(D15:D16,D17:D22) | E23: =E6-E8+SUM(E15:E16,E17:E22) | F23: =F6-F8+SUM(F15:F16,F17:F22) | G23: =G6-G8+SUM(G15:G16,G17:G22) | H23: =H6-H8+SUM(H15:H16,H17:H22) | I23: =I6-I8+SUM(I15:I16,I17:I22) | J23: =J6-J8+SUM(J15:J16,J17:J22) | ... M23: =M6-M8+SUM(M15:M16,M17:M22)
A24: 加：营业外收入 | C24: =营业外收入表!C9 | D24: =营业外收入表!D9 | E24: =营业外收入表!E9 | F24: =营业外收入表!F9 | G24: =营业外收入表!G9 | H24: =营业外收入表!H9 | I24: =营业外收入表!I9 | J24: =营业外收入表!J9 | ... M24: =营业外收入表!M9
A25: 减：营业外支出 | C25: =营业外支出表!C9 | D25: =营业外支出表!D9 | E25: =营业外支出表!E9 | F25: =营业外支出表!F9 | G25: =营业外支出表!G9 | H25: =营业外支出表!H9 | I25: =营业外支出表!I9 | J25: =营业外支出表!J9 | ... M25: =营业外支出表!M9
A26: 四、利润总额（亏损总额以“-”号填列） | C26: =C23+C24-C25 | D26: =D23+D24-D25 | E26: =E23+E24-E25 | F26: =F23+F24-F25 | G26: =G23+G24-G25 | H26: =H23+H24-H25 | I26: =I23+I24-I25 | J26: =J23+J24-J25 | ... M26: =M23+M24-M25
A27: 减：所得税费用 | C27: =所得税表!C43 | D27: =所得税表!D43 | E27: =所得税表!E43 | F27: =所得税表!F43 | G27: =所得税表!G43 | H27: =所得税表!H43 | I27: =所得税表!I43 | J27: =所得税表!J43 | ... M27: =所得税表!M43
A28: 五、净利润（净亏损以“-”号填列） | C28: =C26-C27 | D28: =D26-D27 | E28: =E26-E27 | F28: =F26-F27 | G28: =G26-G27 | H28: =H26-H27 | I28: =I26-I27 | J28: =J26-J27 | ... M28: =M26-M27
A29: 1．归属于母公司股东的净利润（净亏损以“-”号填列） | C29: =C28-C30 | D29: =D28-D30 | E29: =E28-E30 | F29: =F28-F30 | G29: =G28-G30 | H29: =H28-H30 | I29: =I28-I30 | J29: =J28-J30 | ... M29: =M28-M30
A30: 2．少数股东损益（净亏损以“-”号填列）
A31: 加：折旧与摊销 | C31: =折旧摊销、资本性支出表!C19 | D31: =折旧摊销、资本性支出表!D19 | E31: =折旧摊销、资本性支出表!E19 | F31: =折旧摊销、资本性支出表!F19 | G31: =折旧摊销、资本性支出表!G19 | H31: =折旧摊销、资本性支出表!H19 | I31: =折旧摊销、资本性支出表!I19 | J31: =折旧摊销、资本性支出表!J19 | ... M31: =折旧摊销、资本性支出表!M19
A32: 经营现金流 | C32: =SUM(C29+C31) | D32: =SUM(D29+D31) | E32: =SUM(E29+E31) | F32: =SUM(F29+F31) | G32: =SUM(G29+G31) | H32: =SUM(H29+H31) | I32: =SUM(I29+I31) | J32: =SUM(J29+J31) | ... M32: =SUM(M29+M31)
A33: 加：税后付息债务利息 | C33: =(财务费用表!C6+财务费用表!C11)*(1-所得税表!C42) | D33: =(财务费用表!D6+财务费用表!D11)*(1-所得税表!D42) | E33: =(财务费用表!E6+财务费用表!E11)*(1-所得税表!E42) | F33: =(财务费用表!F6+财务费用表!F11)*(1-所得税表!F42) | G33: =(财务费用表!G6+财务费用表!G11)*(1-所得税表!G42) | H33: =(财务费用表!H6+财务费用表!H11)*(1-所得税表!H42) | I33: =(财务费用表!I6+财务费用表!I11)*(1-所得税表!I42) | J33: =(财务费用表!J6+财务费用表!J11)*(1-所得税表!J42) | ... M33: =(财务费用表!M6+财务费用表!M11)*(1-所得税表!M42)
A34: 减：资本性支出 | C34: =折旧摊销、资本性支出表!C29 | D34: =折旧摊销、资本性支出表!D29 | E34: =折旧摊销、资本性支出表!E29 | F34: =折旧摊销、资本性支出表!F29 | G34: =折旧摊销、资本性支出表!G29 | H34: =折旧摊销、资本性支出表!H29 | I34: =折旧摊销、资本性支出表!I29 | J34: =折旧摊销、资本性支出表!J29 | ... M34: =折旧摊销、资本性支出表!M29
A35: 减：营运资金增加（减少） | C35: =营运资金表!C76 | D35: =营运资金表!D76 | E35: =营运资金表!E76 | F35: =营运资金表!F76 | G35: =营运资金表!G78 | H35: =营运资金表!H78 | I35: =营运资金表!I78 | J35: =营运资金表!J78 | K35: =营运资金表!K78 | L35: =营运资金表!L78 | M35: =营运资金表!M76
A36: 净现金流 | C36: =C32+C33-C34-C35 | D36: =D32+D33-D34-D35 | E36: =E32+E33-E34-E35 | F36: =F32+F33-F34-F35 | G36: =G32+G33-G34-G35 | H36: =H32+H33-H34-H35 | I36: =I32+I33-I34-I35 | J36: =J32+J33-J34-J35 | ... M36: =M32+M33-M34-M35
A37: 折现年限 | G37: 0.2500 | H37: 1.0000 | I37: 2.0000 | J37: 3.0000 | K37: 4.0000 | L37: 5.0000
A38: 折现系数 | G38: =ROUND(1/(1+折现率计算表!C24)^G37,4) | H38: =ROUND(1/(1+折现率计算表!C24)^H37,4) | I38: =ROUND(1/(1+折现率计算表!C24)^I37,4) | J38: =ROUND(1/(1+折现率计算表!C24)^J37,4) | K38: =ROUND(1/(1+折现率计算表!C24)^K37,4) | L38: =ROUND(1/(1+折现率计算表!C24)^L37,4) | M38: =ROUND(L38/折现率计算表!C24,4)
A39: 净现金流量现值 | G39: =ROUND(G36*G38,2) | H39: =ROUND(H36*H38,2) | I39: =ROUND(I36*I38,2) | J39: =ROUND(J36*J38,2) | K39: =ROUND(K36*K38,2) | L39: =ROUND(L36*L38,2) | M39: =ROUND(M36*M38,2)
A40: 经营性资产现值之和 | G40: =ROUND(SUM(G39:M39),2)
A42: 评估结果计算表 | D42: 取整位数
A43: 经营性资产现值之和 | C43: =ROUND(G40,D43)
A44: 加：溢余资产 | C44: =溢余资产、非经营资产负债表!E26
A45: 非经营性资产 | C45: =溢余资产、非经营资产负债表!E48
A46: 长期股权投资 | C46: =长期股权投资表!D55
A47: 减：非经营性负债 | C47: =溢余资产、非经营资产负债表!E70
A48: 企业整体价值 | C48: =C43+C44+C45+C46-C47
A49: 减：付息负债 | C49: =付息负债明细表!G193
A50: 股东全部权益价值 | C50: =ROUND(C48-C49,D50)

Sheet 主要产品及服务
A1: 主要产品及服务 | H1: =HYPERLINK("#目录1!A1","返回目录")
A2: 评估基准日：{{VALUATION_BASE_DATE}}
A3: ="被评估单位："&项目信息!B5&"" | G3: ="金额单位："&项目信息!B8&""
A4: 板块 | B4: 序号 | C4: 产品或服务名称 | D4: 增值税率（%） | E4: 营业收入预测方式 | F4: 营业成本预测方式 | G4: 备注

Sheet 营业收入表
A1: 营业收入分析预测表 | N1: =HYPERLINK("#目录1!A1","返回目录")
A2: 评估基准日：{{VALUATION_BASE_DATE}}
A3: ="被评估单位："&项目信息!B5&"" | M3: ="金额单位："&项目信息!B8&""
A4: 产品/服务名称 | C4: 历史数据 | G4: 未来预测
C5: 2022年度 | D5: 2023年度 | E5: 2024年度 | F5: 2025年1-6月 | G5: 2025年7-12月 | H5: 2026年度 | I5: 2027年度 | J5: 2028年度 | K5: 2029年度 | L5: 2030年度 | M5: 永续年度
A6: 主营业务收入：
C7: =营业收入附表!C9 | D7: =营业收入附表!D9 | E7: =营业收入附表!E9 | F7: =营业收入附表!F9 | G7: =营业收入附表!G9 | H7: =营业收入附表!H9 | I7: =营业收入附表!I9 | J7: =营业收入附表!J9 | ... M7: =营业收入附表!M9
A8: 其他 | C8: =营业收入附表!C12 | D8: =营业收入附表!D12 | E8: =营业收入附表!E12 | F8: =营业收入附表!F12 | G8: =营业收入附表!G12 | H8: =营业收入附表!H12 | I8: =营业收入附表!I12 | J8: =营业收入附表!J12 | ... M8: =营业收入附表!M12
A11: 主营业务收入小计 | C11: =SUM(C6:C10) | D11: =SUM(D6:D10) | E11: =SUM(E6:E10) | F11: =SUM(F6:F10) | G11: =SUM(G6:G10) | H11: =SUM(H6:H10) | I11: =SUM(I6:I10) | J11: =SUM(J6:J10) | ... M11: =SUM(M6:M10)
A12: 其他业务收入：
A13: 其他 | C13: =营业收入附表!C19 | D13: =营业收入附表!D19 | E13: =营业收入附表!E19 | F13: =营业收入附表!F19 | G13: =营业收入附表!G19 | H13: =营业收入附表!H19 | I13: =营业收入附表!I19 | J13: =营业收入附表!J19 | ... M13: =营业收入附表!M19
A16: 其他业务收入小计 | C16: =SUM(C12:C15) | D16: =SUM(D12:D15) | E16: =SUM(E12:E15) | F16: =SUM(F12:F15) | G16: =SUM(G12:G15) | H16: =SUM(H12:H15) | I16: =SUM(I12:I15) | J16: =SUM(J12:J15) | ... M16: =SUM(M12:M15)
A17: 营业收入合计 | C17: =C11+C16 | D17: =D11+D16 | E17: =E11+E16 | F17: =F11+F16 | G17: =G11+G16 | H17: =H11+H16 | I17: =I11+I16 | J17: =J11+J16 | ... M17: =M11+M16
A19: 主营业务收入 | C19: 增长率（%） | D19: =ROUND((D11-C11)/C11,4) | E19: =ROUND((E11-D11)/D11,4) | F19: =ROUND((F11/6*12-E11)/E11,4) | G19: =ROUND((G11+F11-E11)/E11,4) | H19: =ROUND((H11-(G11+F11))/(G11+F11),4) | I19: =ROUND((I11-H11)/H11,4) | J19: =ROUND((J11-I11)/I11,4) | K19: =ROUND((K11-J11)/J11,4) | L19: =ROUND((L11-K11)/K11,4) | M19: =ROUND((M11-L11)/L11,4)
C20: 复合增长率（%） | F20: =ROUND(((F11/6*12)/C11)^(1/3),4)-1 | L20: =ROUND((L11/(G11+F11))^(1/5),4)-1
A21: 其他业务收入 | C21: 增长率（%） | D21: =ROUND((D16-C16)/C16,4) | E21: =ROUND((E16-D16)/D16,4) | F21: =ROUND((F16/6*12-E16)/E16,4) | G21: =ROUND((G16+F16-E16)/E16,4) | H21: =ROUND((H16-(G16+F16))/(G16+F16),4) | I21: =ROUND((I16-H16)/H16,4) | J21: =ROUND((J16-I16)/I16,4) | K21: =ROUND((K16-J16)/J16,4) | L21: =ROUND((L16-K16)/K16,4) | M21: =ROUND((M16-L16)/L16,4)
C22: 复合增长率（%） | F22: =ROUND(((F16/6*12)/C16)^(1/3),4)-1 | L22: =ROUND((L16/(G16+F16))^(1/5),4)-1
A23: 营业收入 | C23: 增长率（%） | D23: =ROUND((D17-C17)/C17,4) | E23: =ROUND((E17-D17)/D17,4) | F23: =ROUND((F17/6*12-E17)/E17,4) | G23: =ROUND((G17+F17-E17)/E17,4) | H23: =ROUND((H17-(G17+F17))/(G17+F17),4) | I23: =ROUND((I17-H17)/H17,4) | J23: =ROUND((J17-I17)/I17,4) | K23: =ROUND((K17-J17)/J17,4) | L23: =ROUND((L17-K17)/K17,4) | M23: =ROUND((M17-L17)/L17,4)
C24: 复合增长率（%） | F24: =ROUND(((F17/6*12)/C17)^(1/3),4)-1 | L24: =ROUND((L17/(G17+F17))^(1/5),4)-1
A25: 核对 | C25: =C17-营业收入附表!C23 | D25: =D17-营业收入附表!D23 | E25: =E17-营业收入附表!E23 | F25: =F17-营业收入附表!F23 | G25: =G17-营业收入附表!G23 | H25: =H17-营业收入附表!H23 | I25: =I17-营业收入附表!I23 | J25: =J17-营业收入附表!J23 | ... M25: =M17-营业收入附表!M23

Sheet 营业收入附表
A1: 营业收入分析预测表 | N1: =HYPERLINK("#目录1!A1","返回目录")
A2: 评估基准日：{{VALUATION_BASE_DATE}}
A3: ="被评估单位："&项目信息!B5&"" | M3: ="金额单位："&项目信息!B8&""
A4: 产品/服务名称 | B4: 项目 | C4: 历史数据 | G4: 未来预测
C5: 2022年度 | D5: 2023年度 | E5: 2024年度 | F5: 2025年1-6月 | G5: 2025年7-12月 | H5: 2026年度 | I5: 2027年度 | J5: 2028年度 | K5: 2029年度 | L5: 2030年度 | M5: 永续年度
A6: 主营业务收入：
B7: 数量
B8: 单价 | C8: =ROUND(C9/C7,2) | D8: =ROUND(D9/D7,2) | E8: =ROUND(E9/E7,2) | F8: =ROUND(F9/F7,2) | M8: =L8
B9: 收入 | G9: =ROUND(G7*G8,2) | H9: =ROUND(H7*H8,2) | I9: =ROUND(I7*I8,2) | J9: =ROUND(J7*J8,2) | K9: =ROUND(K7*K8,2) | L9: =ROUND(L7*L8,2) | M9: =ROUND(M7*M8,2)
A10: 其他 | B10: 数量
B11: 单价 | C11: =ROUND(C12/C10,2) | D11: =ROUND(D12/D10,2) | E11: =ROUND(E12/E10,2) | F11: =ROUND(F12/F10,2)
B12: 收入 | G12: =ROUND(G10*G11,2) | H12: =ROUND(H10*H11,2) | I12: =ROUND(I10*I11,2) | J12: =ROUND(J10*J11,2) | K12: =ROUND(K10*K11,2) | L12: =ROUND(L10*L11,2) | M12: =ROUND(M10*M11,2)
A15: 主营业务收入小计 | C15: =SUMIF($B7:$B14,"收入",C7:C14) | D15: =SUMIF($B7:$B14,"收入",D7:D14) | E15: =SUMIF($B7:$B14,"收入",E7:E14) | F15: =SUMIF($B7:$B14,"收入",F7:F14) | G15: =SUMIF($B7:$B14,"收入",G7:G14) | H15: =SUMIF($B7:$B14,"收入",H7:H14) | I15: =SUMIF($B7:$B14,"收入",I7:I14) | J15: =SUMIF($B7:$B14,"收入",J7:J14) | ... M15: =SUMIF($B7:$B14,"收入",M7:M14)
A16: 其他业务收入：
A17: 其他 | B17: 数量
B18: 单价 | C18: =ROUND(C19/C17,2) | D18: =ROUND(D19/D17,2) | E18: =ROUND(E19/E17,2) | F18: =ROUND(F19/F17,2)
B19: 收入 | G19: =ROUND(G17*G18,2) | H19: =ROUND(H17*H18,2) | I19: =ROUND(I17*I18,2) | J19: =ROUND(J17*J18,2) | K19: =ROUND(K17*K18,2) | L19: =ROUND(L17*L18,2) | M19: =ROUND(M17*M18,2)
A22: 其他业务收入小计 | C22: =SUMIF($B17:$B21,"收入",C17:C21) | D22: =SUMIF($B17:$B21,"收入",D17:D21) | E22: =SUMIF($B17:$B21,"收入",E17:E21) | F22: =SUMIF($B17:$B21,"收入",F17:F21) | G22: =SUMIF($B17:$B21,"收入",G17:G21) | H22: =SUMIF($B17:$B21,"收入",H17:H21) | I22: =SUMIF($B17:$B21,"收入",I17:I21) | J22: =SUMIF($B17:$B21,"收入",J17:J21) | ... M22: =SUMIF($B17:$B21,"收入",M17:M21)
A23: 营业收入合计 | C23: =C15+C22 | D23: =D15+D22 | E23: =E15+E22 | F23: =F15+F22 | G23: =G15+G22 | H23: =H15+H22 | I23: =I15+I22 | J23: =J15+J22 | ... M23: =M15+M22
A25: 【HD】主营业务收入核对 | C25: =C15-历利调整后表!D8 | D25: =D15-历利调整后表!G8 | E25: =E15-历利调整后表!J8 | F25: =F15-历利调整后表!M8
A26: 【HD】其他业务收入核对 | C26: =C22-历利调整后表!D9 | D26: =D22-历利调整后表!G9 | E26: =E22-历利调整后表!J9 | F26: =F22-历利调整后表!M9
A27: 【HD】营业收入核对 | C27: =C23-历利调整后表!D7 | D27: =D23-历利调整后表!G7 | E27: =E23-历利调整后表!J7 | F27: =F23-历利调整后表!M7

Sheet 营业成本表
A1: 营业成本分析预测表 | N1: =HYPERLINK("#目录1!A1","返回目录")
A2: 评估基准日：{{VALUATION_BASE_DATE}}
A3: ="被评估单位："&项目信息!B5&"" | M3: ="金额单位："&项目信息!B8&""
A4: 产品/服务名称 | C4: 历史数据 | G4: 未来预测
C5: 2022年度 | D5: 2023年度 | E5: 2024年度 | F5: 2025年1-6月 | G5: 2025年7-12月 | H5: 2026年度 | I5: 2027年度 | J5: 2028年度 | K5: 2029年度 | L5: 2030年度 | M5: 永续年度
A6: 主营业务成本：
C7: =营业成本附表!C17 | D7: =营业成本附表!D17 | E7: =营业成本附表!E17 | F7: =营业成本附表!F17 | G7: =营业成本附表!G17 | H7: =营业成本附表!H17 | I7: =营业成本附表!I17 | J7: =营业成本附表!J17 | ... M7: =营业成本附表!M17
A8: 其他 | C8: =营业成本附表!C20 | D8: =营业成本附表!D20 | E8: =营业成本附表!E20 | F8: =营业成本附表!F20 | G8: =营业成本附表!G20 | H8: =营业成本附表!H20 | I8: =营业成本附表!I20 | J8: =营业成本附表!J20 | ... M8: =营业成本附表!M20
A11: 主营业务成本小计 | C11: =SUM(C7:C10) | D11: =SUM(D7:D10) | E11: =SUM(E7:E10) | F11: =SUM(F7:F10) | G11: =SUM(G7:G10) | H11: =SUM(H7:H10) | I11: =SUM(I7:I10) | J11: =SUM(J7:J10) | ... M11: =SUM(M7:M10)
A12: 其他业务成本：
A13: 其他 | C13: =营业成本附表!C27 | D13: =营业成本附表!D27 | E13: =营业成本附表!E27 | F13: =营业成本附表!F27 | G13: =营业成本附表!G27 | H13: =营业成本附表!H27 | I13: =营业成本附表!I27 | J13: =营业成本附表!J27 | ... M13: =营业成本附表!M27
A16: 其他业务成本小计 | C16: =SUM(C13:C15) | D16: =SUM(D13:D15) | E16: =SUM(E13:E15) | F16: =SUM(F13:F15) | G16: =SUM(G13:G15) | H16: =SUM(H13:H15) | I16: =SUM(I13:I15) | J16: =SUM(J13:J15) | ... M16: =SUM(M13:M15)
A17: 营业成本合计 | C17: =C11+C16 | D17: =D11+D16 | E17: =E11+E16 | F17: =F11+F16 | G17: =G11+G16 | H17: =H11+H16 | I17: =I11+I16 | J17: =J11+J16 | ... M17: =M11+M16
A19: 主营业务成本 | C19: 增长率（%） | D19: =ROUND((D11-C11)/C11,4) | E19: =ROUND((E11-D11)/D11,4) | F19: =ROUND((F11/6*12-E11)/E11,4) | G19: =ROUND((G11+F11-E11)/E11,4) | H19: =ROUND((H11-(G11+F11))/(G11+F11),4) | I19: =ROUND((I11-H11)/H11,4) | J19: =ROUND((J11-I11)/I11,4) | K19: =ROUND((K11-J11)/J11,4) | L19: =ROUND((L11-K11)/K11,4) | M19: =ROUND((M11-L11)/L11,4)
C20: 复合增长率（%） | F20: =ROUND(((F11/6*12)/C11)^(1/3),4)-1 | L20: =ROUND((L11/(G11+F11))^(1/5),4)-1
A21: 其他业务成本 | C21: 增长率（%） | D21: =ROUND((D16-C16)/C16,4) | E21: =ROUND((E16-D16)/D16,4) | F21: =ROUND((F16/6*12-E16)/E16,4) | G21: =ROUND((G16+F16-E16)/E16,4) | H21: =ROUND((H16-(G16+F16))/(G16+F16),4) | I21: =ROUND((I16-H16)/H16,4) | J21: =ROUND((J16-I16)/I16,4) | K21: =ROUND((K16-J16)/J16,4) | L21: =ROUND((L16-K16)/K16,4) | M21: =ROUND((M16-L16)/L16,4)
C22: 复合增长率（%） | F22: =ROUND(((F16/6*12)/C16)^(1/3),4)-1 | L22: =ROUND((L16/(G16+F16))^(1/5),4)-1
A23: 营业成本 | C23: 增长率（%） | D23: =ROUND((D17-C17)/C17,4) | E23: =ROUND((E17-D17)/D17,4) | F23: =ROUND((F17/6*12-E17)/E17,4) | G23: =ROUND((G17+F17-E17)/E17,4) | H23: =ROUND((H17-(G17+F17))/(G17+F17),4) | I23: =ROUND((I17-H17)/H17,4) | J23: =ROUND((J17-I17)/I17,4) | K23: =ROUND((K17-J17)/J17,4) | L23: =ROUND((L17-K17)/K17,4) | M23: =ROUND((M17-L17)/L17,4)
C24: 复合增长率（%） | F24: =ROUND(((F17/6*12)/C17)^(1/3),4)-1 | L24: =ROUND((L17/(G17+F17))^(1/5),4)-1
A25: 主营业务毛利率 | C25: =ROUND((1-C11/营业收入表!C11),4) | D25: =ROUND((1-D11/营业收入表!D11),4) | E25: =ROUND((1-E11/营业收入表!E11),4) | F25: =ROUND((1-F11/营业收入表!F11),4) | G25: =ROUND((1-G11/营业收入表!G11),4) | H25: =ROUND((1-H11/营业收入表!H11),4) | I25: =ROUND((1-I11/营业收入表!I11),4) | J25: =ROUND((1-J11/营业收入表!J11),4) | ... M25: =ROUND((1-M11/营业收入表!M11),4)
A26: 其他业务毛利率 | C26: =ROUND((1-C16/营业收入表!C16),4) | D26: =ROUND((1-D16/营业收入表!D16),4) | E26: =ROUND((1-E16/营业收入表!E16),4) | F26: =ROUND((1-F16/营业收入表!F16),4) | G26: =ROUND((1-G16/营业收入表!G16),4) | H26: =ROUND((1-H16/营业收入表!H16),4) | I26: =ROUND((1-I16/营业收入表!I16),4) | J26: =ROUND((1-J16/营业收入表!J16),4) | ... M26: =ROUND((1-M16/营业收入表!M16),4)
A27: 核对 | C27: =C17-营业成本附表!C31 | D27: =D17-营业成本附表!D31 | E27: =E17-营业成本附表!E31 | F27: =F17-营业成本附表!F31 | G27: =G17-营业成本附表!G31 | H27: =H17-营业成本附表!H31 | I27: =I17-营业成本附表!I31 | J27: =J17-营业成本附表!J31 | ... M27: =M17-营业成本附表!M31

Sheet 营业成本附表
A1: 营业成本分析预测表 | N1: =HYPERLINK("#目录1!A1","返回目录")
A2: 评估基准日：{{VALUATION_BASE_DATE}}
A3: ="被评估单位："&项目信息!B5&"" | M3: ="金额单位："&项目信息!B8&""
A4: 产品/服务名称 | B4: 项目 | C4: 历史数据 | G4: 未来预测
C5: 2022年度 | D5: 2023年度 | E5: 2024年度 | F5: 2025年1-6月 | G5: 2025年7-12月 | H5: 2026年度 | I5: 2027年度 | J5: 2028年度 | K5: 2029年度 | L5: 2030年度 | M5: 永续年度
A6: 主营业务成本：
B7: 材料 | M7: =L7
B8: 人工 | M8: =L8
B9: 制造费用 | M9: =L9
B10: 折旧 | M10: =L10
B11: 摊销
B17: 成本 | C17: =SUM(C7:C16) | D17: =SUM(D7:D16) | E17: =SUM(E7:E16) | F17: =SUM(F7:F16) | G17: =SUM(G7:G16) | H17: =SUM(H7:H16) | I17: =SUM(I7:I16) | J17: =SUM(J7:J16) | ... M17: =SUM(M7:M16)
A18: 其他 | B18: 数量 | C18: =营业收入附表!C10 | D18: =营业收入附表!D10 | E18: =营业收入附表!E10 | F18: =营业收入附表!F10 | G18: =营业收入附表!G10 | H18: =营业收入附表!H10 | I18: =营业收入附表!I10 | J18: =营业收入附表!J10 | ... M18: =营业收入附表!M10
B19: 单价 | C19: =ROUND(C20/C18,2) | D19: =ROUND(D20/D18,2) | E19: =ROUND(E20/E18,2) | F19: =ROUND(F20/F18,2)
B20: 成本 | G20: =ROUND(G18*G19,2) | H20: =ROUND(H18*H19,2) | I20: =ROUND(I18*I19,2) | J20: =ROUND(J18*J19,2) | K20: =ROUND(K18*K19,2) | L20: =ROUND(L18*L19,2) | M20: =ROUND(M18*M19,2)
A23: 主营业务成本小计 | C23: =SUMIF($B7:$B22,"成本",C7:C22) | D23: =SUMIF($B7:$B22,"成本",D7:D22) | E23: =SUMIF($B7:$B22,"成本",E7:E22) | F23: =SUMIF($B7:$B22,"成本",F7:F22) | G23: =SUMIF($B7:$B22,"成本",G7:G22) | H23: =SUMIF($B7:$B22,"成本",H7:H22) | I23: =SUMIF($B7:$B22,"成本",I7:I22) | J23: =SUMIF($B7:$B22,"成本",J7:J22) | ... M23: =SUMIF($B7:$B22,"成本",M7:M22)
A24: 其他业务成本：
A25: 其他 | B25: 数量 | C25: =营业收入附表!C17 | D25: =营业收入附表!D17 | E25: =营业收入附表!E17 | F25: =营业收入附表!F17 | G25: =营业收入附表!G17 | H25: =营业收入附表!H17 | I25: =营业收入附表!I17 | J25: =营业收入附表!J17 | ... M25: =营业收入附表!M17
B26: 单价 | C26: =ROUND(C27/C25,2) | D26: =ROUND(D27/D25,2) | E26: =ROUND(E27/E25,2) | F26: =ROUND(F27/F25,2)
B27: 成本 | G27: =ROUND(G25*G26,2) | H27: =ROUND(H25*H26,2) | I27: =ROUND(I25*I26,2) | J27: =ROUND(J25*J26,2) | K27: =ROUND(K25*K26,2) | L27: =ROUND(L25*L26,2) | M27: =ROUND(M25*M26,2)
A30: 其他业务成本小计 | C30: =SUMIF($B25:$B29,"成本",C25:C29) | D30: =SUMIF($B25:$B29,"成本",D25:D29) | E30: =SUMIF($B25:$B29,"成本",E25:E29) | F30: =SUMIF($B25:$B29,"成本",F25:F29) | G30: =SUMIF($B25:$B29,"成本",G25:G29) | H30: =SUMIF($B25:$B29,"成本",H25:H29) | I30: =SUMIF($B25:$B29,"成本",I25:I29) | J30: =SUMIF($B25:$B29,"成本",J25:J29) | ... M30: =SUMIF($B25:$B29,"成本",M25:M29)
A31: 营业成本合计 | C31: =C23+C30 | D31: =D23+D30 | E31: =E23+E30 | F31: =F23+F30 | G31: =G23+G30 | H31: =H23+H30 | I31: =I23+I30 | J31: =J23+J30 | ... M31: =M23+M30
A33: 【HD】主营业务成本核对 | C33: =C23-历利调整后表!D15 | D33: =D23-历利调整后表!G15 | E33: =E23-历利调整后表!J15 | F33: =F23-历利调整后表!M15
A34: 【HD】其他业务成本核对 | C34: =C30-历利调整后表!D16 | D34: =D30-历利调整后表!G16 | E34: =E30-历利调整后表!J16 | F34: =F30-历利调整后表!M16
A35: 【HD】营业成本核对 | C35: =C31-历利调整后表!D14 | D35: =D31-历利调整后表!G14 | E35: =E31-历利调整后表!J14 | F35: =F31-历利调整后表!M14
A36: 制造费用核对 | C36: =SUMIF(B7:B29,"制造费用",C7:C29)-制造费用表!C62 | D36: =SUMIF(B7:B29,"制造费用",D7:D29)-制造费用表!D62 | E36: =SUMIF(B7:B29,"制造费用",E7:E29)-制造费用表!E62 | F36: =SUMIF(B7:B29,"制造费用",F7:F29)-制造费用表!F62 | G36: =SUMIF(B7:B29,"制造费用",G7:G29)-制造费用表!G62 | H36: =SUMIF(B7:B29,"制造费用",H7:H29)-制造费用表!H62 | I36: =SUMIF(B7:B29,"制造费用",I7:I29)-制造费用表!I62 | J36: =SUMIF(B7:B29,"制造费用",J7:J29)-制造费用表!J62 | K36: =SUMIF(B7:B29,"制造费用",K7:K29)-制造费用表!K62 | L36: =SUMIF(B7:B29,"制造费用",L7:L29)-制造费用表!L62 | M36: =SUMIF(B7:B29,"制造费用",M7:M29)-制造费用表!M62
A37: 人工核对 | C37: =SUMIF(B7:B29,"人工",C7:C29)-人工成本表!C27 | D37: =SUMIF(B7:B29,"人工",D7:D29)-人工成本表!D27 | E37: =SUMIF(B7:B29,"人工",E7:E29)-人工成本表!E27 | F37: =SUMIF(B7:B29,"人工",F7:F29)-人工成本表!F27 | G37: =SUMIF(B7:B29,"人工",G7:G29)-人工成本表!G27 | H37: =SUMIF(B7:B29,"人工",H7:H29)-人工成本表!H27 | I37: =SUMIF(B7:B29,"人工",I7:I29)-人工成本表!I27 | J37: =SUMIF(B7:B29,"人工",J7:J29)-人工成本表!J27 | K37: =SUMIF(B7:B29,"人工",K7:K29)-人工成本表!K27 | L37: =SUMIF(B7:B29,"人工",L7:L29)-人工成本表!L27 | M37: =SUMIF(B7:B29,"人工",M7:M29)-人工成本表!M27
A38: 折旧核对 | C38: =SUMIF(B7:B29,"折旧",C7:C29)-折旧摊销、资本性支出表!C7 | D38: =SUMIF(B7:B29,"折旧",D7:D29)-折旧摊销、资本性支出表!D7 | E38: =SUMIF(B7:B29,"折旧",E7:E29)-折旧摊销、资本性支出表!E7 | F38: =SUMIF(B7:B29,"折旧",F7:F29)-折旧摊销、资本性支出表!F7 | G38: =SUMIF(B7:B29,"折旧",G7:G29)-折旧摊销、资本性支出表!G7 | H38: =SUMIF(B7:B29,"折旧",H7:H29)-折旧摊销、资本性支出表!H7 | I38: =SUMIF(B7:B29,"折旧",I7:I29)-折旧摊销、资本性支出表!I7 | J38: =SUMIF(B7:B29,"折旧",J7:J29)-折旧摊销、资本性支出表!J7 | K38: =SUMIF(B7:B29,"折旧",K7:K29)-折旧摊销、资本性支出表!K7 | L38: =SUMIF(B7:B29,"折旧",L7:L29)-折旧摊销、资本性支出表!L7 | M38: =SUMIF(B7:B29,"折旧",M7:M29)-折旧摊销、资本性支出表!M7
A39: 摊销核对 | C39: =SUMIF(B7:B29,"摊销",C7:C29)-折旧摊销、资本性支出表!C8 | D39: =SUMIF(B7:B29,"摊销",D7:D29)-折旧摊销、资本性支出表!D8 | E39: =SUMIF(B7:B29,"摊销",E7:E29)-折旧摊销、资本性支出表!E8 | F39: =SUMIF(B7:B29,"摊销",F7:F29)-折旧摊销、资本性支出表!F8 | G39: =SUMIF(B7:B29,"摊销",G7:G29)-折旧摊销、资本性支出表!G8 | H39: =SUMIF(B7:B29,"摊销",H7:H29)-折旧摊销、资本性支出表!H8 | I39: =SUMIF(B7:B29,"摊销",I7:I29)-折旧摊销、资本性支出表!I8 | J39: =SUMIF(B7:B29,"摊销",J7:J29)-折旧摊销、资本性支出表!J8 | K39: =SUMIF(B7:B29,"摊销",K7:K29)-折旧摊销、资本性支出表!K8 | L39: =SUMIF(B7:B29,"摊销",L7:L29)-折旧摊销、资本性支出表!L8 | M39: =SUMIF(B7:B29,"摊销",M7:M29)-折旧摊销、资本性支出表!M8

Sheet 人工成本表
A1: 人工及工资预测表 | N1: =HYPERLINK("#目录1!A1","返回目录")
A2: 评估基准日：{{VALUATION_BASE_DATE}}
A3: ="被评估单位："&项目信息!B5&"" | M3: ="金额单位："&项目信息!B8&""
A4: 一、人员数量
A5: 人员类别 | B5: 核算科目 | C5: 历史数据 | G5: 未来预测
C6: 2022年度 | D6: 2023年度 | E6: 2024年度 | F6: 2025年1-6月 | G6: 2025年7-12月 | H6: 2026年度 | I6: 2027年度 | J6: 2028年度 | K6: 2029年度 | L6: 2030年度 | M6: 永续年度
A7: 生产人员 | B7: 营业成本 | H7: =G7 | I7: =H7 | J7: =I7 | K7: =J7 | L7: =K7 | M7: =L7
A8: 制造人员 | B8: 制造费用
A9: 销售人员 | B9: 销售费用
A10: 管理人员及其他人员 | B10: 管理费用
A11: 研发人员 | B11: 研发费用
A12: 员工人数合计 | C12: =SUM(C7:C11) | D12: =SUM(D7:D11) | E12: =SUM(E7:E11) | F12: =SUM(F7:F11) | G12: =SUM(G7:G11) | H12: =SUM(H7:H11) | I12: =SUM(I7:I11) | J12: =SUM(J7:J11) | ... M12: =SUM(M7:M11)
A14: 二、平均工资
A15: 人员类别 | B15: 核算科目 | C15: 历史数据 | G15: 未来预测
C16: 2022年度 | D16: 2023年度 | E16: 2024年度 | F16: 2025年1-6月 | G16: 2025年7-12月 | H16: 2026年度 | I16: 2027年度 | J16: 2028年度 | K16: 2029年度 | L16: 2030年度 | M16: 永续年度
A17: 生产人员 | B17: 营业成本 | C17: =ROUND((C27/C7),2) | D17: =ROUND((D27/D7),2) | E17: =ROUND((E27/E7),2) | F17: =ROUND((F27/F7),2) | M17: =L17
A18: 制造人员 | B18: 制造费用 | C18: =ROUND((C28/C8),2) | D18: =ROUND((D28/D8),2) | E18: =ROUND((E28/E8),2) | F18: =ROUND((F28/F8),2)
A19: 销售人员 | B19: 销售费用 | C19: =ROUND((C29/C9),2) | D19: =ROUND((D29/D9),2) | E19: =ROUND((E29/E9),2) | F19: =ROUND((F29/F9),2)
A20: 管理人员及其他人员 | B20: 管理费用 | C20: =ROUND((C30/C10),2) | D20: =ROUND((D30/D10),2) | E20: =ROUND((E30/E10),2) | F20: =ROUND((F30/F10),2)
A21: 研发人员 | B21: 研发费用 | C21: =ROUND((C31/C11),2) | D21: =ROUND((D31/D11),2) | E21: =ROUND((E31/E11),2) | F21: =ROUND((F31/F11),2)
A22: 平均工资 | C22: =AVERAGE(C17:C21) | D22: =AVERAGE(D17:D21) | E22: =AVERAGE(E17:E21) | F22: =AVERAGE(F17:F21) | G22: =AVERAGE(G17:G21) | H22: =AVERAGE(H17:H21) | I22: =AVERAGE(I17:I21) | J22: =AVERAGE(J17:J21) | ... M22: =AVERAGE(M17:M21)
A24: 三、工资总额
A25: 人员类别 | B25: 核算科目 | C25: 历史数据 | G25: 未来预测
C26: 2022年度 | D26: 2023年度 | E26: 2024年度 | F26: 2025年1-6月 | G26: 2025年7-12月 | H26: 2026年度 | I26: 2027年度 | J26: 2028年度 | K26: 2029年度 | L26: 2030年度 | M26: 永续年度
A27: 生产人员 | B27: 营业成本 | G27: =ROUND(G7*G17,2) | H27: =ROUND(H7*H17,2) | I27: =ROUND(I7*I17,2) | J27: =ROUND(J7*J17,2) | K27: =ROUND(K7*K17,2) | L27: =ROUND(L7*L17,2) | M27: =ROUND(M7*M17,2)
A28: 制造人员 | B28: 制造费用 | C28: =制造费用表!C6 | D28: =制造费用表!D6 | E28: =制造费用表!E6 | F28: =制造费用表!F6 | G28: =ROUND(G8*G18,2) | H28: =ROUND(H8*H18,2) | I28: =ROUND(I8*I18,2) | J28: =ROUND(J8*J18,2) | K28: =ROUND(K8*K18,2) | L28: =ROUND(L8*L18,2) | M28: =ROUND(M8*M18,2)
A29: 销售人员 | B29: 销售费用 | C29: =销售费用表!C6 | D29: =销售费用表!D6 | E29: =销售费用表!E6 | F29: =销售费用表!F6 | G29: =ROUND(G9*G19,2) | H29: =ROUND(H9*H19,2) | I29: =ROUND(I9*I19,2) | J29: =ROUND(J9*J19,2) | K29: =ROUND(K9*K19,2) | L29: =ROUND(L9*L19,2) | M29: =ROUND(M9*M19,2)
A30: 管理人员及其他人员 | B30: 管理费用 | C30: =管理费用表!C6 | D30: =管理费用表!D6 | E30: =管理费用表!E6 | F30: =管理费用表!F6 | G30: =ROUND(G10*G20,2) | H30: =ROUND(H10*H20,2) | I30: =ROUND(I10*I20,2) | J30: =ROUND(J10*J20,2) | K30: =ROUND(K10*K20,2) | L30: =ROUND(L10*L20,2) | M30: =ROUND(M10*M20,2)
A31: 研发人员 | B31: 研发费用 | C31: =研发费用表!C6 | D31: =研发费用表!D6 | E31: =研发费用表!E6 | F31: =研发费用表!F6 | G31: =ROUND(G11*G21,2) | H31: =ROUND(H11*H21,2) | I31: =ROUND(I11*I21,2) | J31: =ROUND(J11*J21,2) | K31: =ROUND(K11*K21,2) | L31: =ROUND(L11*L21,2) | M31: =ROUND(M11*M21,2)
A32: 工资总额合计 | C32: =SUM(C27:C31) | D32: =SUM(D27:D31) | E32: =SUM(E27:E31) | F32: =SUM(F27:F31) | G32: =SUM(G27:G31) | H32: =SUM(H27:H31) | I32: =SUM(I27:I31) | J32: =SUM(J27:J31) | ... M32: =SUM(M27:M31)

Sheet 制造费用表
A1: 制造费用分析预测表 | N1: =HYPERLINK("#目录1!A1","返回目录")
A2: 评估基准日：{{VALUATION_BASE_DATE}}
A3: ="被评估单位："&项目信息!B5&"" | M3: ="金额单位："&项目信息!B8&""
A4: 项目 | C4: 历史数据 | G4: 未来预测
C5: 2022年度 | D5: 2023年度 | E5: 2024年度 | F5: 2025年1-6月 | G5: 2025年7-12月 | H5: 2026年度 | I5: 2027年度 | J5: 2028年度 | K5: 2029年度 | L5: 2030年度 | M5: 永续年度
A6: 人工
A7: 材料
A8: 折旧 | G8: =折旧摊销、资本性支出表!G9 | H8: =折旧摊销、资本性支出表!H9 | I8: =折旧摊销、资本性支出表!I9 | J8: =折旧摊销、资本性支出表!J9 | K8: =折旧摊销、资本性支出表!K9 | L8: =折旧摊销、资本性支出表!L9 | M8: =折旧摊销、资本性支出表!M9
A9: 摊销 | G9: =折旧摊销、资本性支出表!G10 | H9: =折旧摊销、资本性支出表!H10 | I9: =折旧摊销、资本性支出表!I10 | J9: =折旧摊销、资本性支出表!J10 | K9: =折旧摊销、资本性支出表!K10 | L9: =折旧摊销、资本性支出表!L10 | M9: =折旧摊销、资本性支出表!M10
A10: 业务招待费
A11: 使用权资产折旧
A12: 房屋租赁费
A13: 运输费
A62: 合计 | C62: =SUM(C6:C61) | D62: =SUM(D6:D61) | E62: =SUM(E6:E61) | F62: =SUM(F6:F61) | G62: =SUM(G6:G61) | H62: =SUM(H6:H61) | I62: =SUM(I6:I61) | J62: =SUM(J6:J61) | ... M62: =SUM(M6:M61)
A64: 增长率（%） | D64: =ROUND((D62-C62)/C62,4) | E64: =ROUND((E62-D62)/D62,4) | F64: =ROUND((F62/6*12-E62)/E62,4) | G64: =ROUND((G62+F62-E62)/E62,4) | H64: =ROUND((H62-(G62+F62))/(G62+F62),4) | I64: =ROUND((I62-H62)/H62,4) | J64: =ROUND((J62-I62)/I62,4) | K64: =ROUND((K62-J62)/J62,4) | L64: =ROUND((L62-K62)/K62,4) | M64: =ROUND((M62-L62)/L62,4)
A65: 占主营业务收入的比例（%） | C65: =ROUND(C62/营业收入表!C11,4) | D65: =ROUND(D62/营业收入表!D11,4) | E65: =ROUND(E62/营业收入表!E11,4) | F65: =ROUND(F62/营业收入表!F11,4) | G65: =ROUND(G62/营业收入表!G11,4) | H65: =ROUND(H62/营业收入表!H11,4) | I65: =ROUND(I62/营业收入表!I11,4) | J65: =ROUND(J62/营业收入表!J11,4) | ... M65: =ROUND(M62/营业收入表!M11,4)
A66: 占营业收入比例（%） | C66: =ROUND(C62/营业收入表!C17,4) | D66: =ROUND(D62/营业收入表!D17,4) | E66: =ROUND(E62/营业收入表!E17,4) | F66: =ROUND(F62/营业收入表!F17,4) | G66: =ROUND(G62/营业收入表!G17,4) | H66: =ROUND(H62/营业收入表!H17,4) | I66: =ROUND(I62/营业收入表!I17,4) | J66: =ROUND(J62/营业收入表!J17,4) | ... M66: =ROUND(M62/营业收入表!M17,4)
A67: 人工核对 | C67: =C6-人工成本表!C28 | D67: =D6-人工成本表!D28 | E67: =E6-人工成本表!E28 | F67: =F6-人工成本表!F28 | G67: =G6-人工成本表!G28 | H67: =H6-人工成本表!H28 | I67: =I6-人工成本表!I28 | J67: =J6-人工成本表!J28 | ... M67: =M6-人工成本表!M28

Sheet 税金及附加表
A1: 税金及附加分析预测表 | N1: =HYPERLINK("#目录1!A1","返回目录")
A2: 评估基准日：{{VALUATION_BASE_DATE}}
A3: ="被评估单位："&项目信息!B5&"" | M3: ="金额单位："&项目信息!B8&""
A4: 税种 | B4: 税率（%） | C4: 历史数据 | G4: 未来预测
C5: 2022年度 | D5: 2023年度 | E5: 2024年度 | F5: 2025年1-6月 | G5: 2025年7-12月 | H5: 2026年度 | I5: 2027年度 | J5: 2028年度 | K5: 2029年度 | L5: 2030年度 | M5: 永续年度
A6: 城建税 | G6: =IF(增值税表!G162>0,ROUND(增值税表!G162*税金及附加表!B6,2),0) | H6: =IF(增值税表!H162>0,ROUND(增值税表!H162*税金及附加表!B6,2),0) | I6: =IF(增值税表!I162>0,ROUND(增值税表!I162*税金及附加表!B6,2),0) | J6: =IF(增值税表!J162>0,ROUND(增值税表!J162*税金及附加表!B6,2),0) | K6: =IF(增值税表!K162>0,ROUND(增值税表!K162*税金及附加表!B6,2),0) | L6: =IF(增值税表!L162>0,ROUND(增值税表!L162*税金及附加表!B6,2),0) | M6: =IF(增值税表!M162>0,ROUND(增值税表!M162*税金及附加表!B6,2),0)
A7: 教育费附加 | G7: =IF(增值税表!G162>0,ROUND(增值税表!G162*税金及附加表!B7,2),0) | H7: =IF(增值税表!H162>0,ROUND(增值税表!H162*税金及附加表!B7,2),0) | I7: =IF(增值税表!I162>0,ROUND(增值税表!I162*税金及附加表!B7,2),0) | J7: =IF(增值税表!J162>0,ROUND(增值税表!J162*税金及附加表!B7,2),0) | K7: =IF(增值税表!K162>0,ROUND(增值税表!K162*税金及附加表!B7,2),0) | L7: =IF(增值税表!L162>0,ROUND(增值税表!L162*税金及附加表!B7,2),0) | M7: =IF(增值税表!M162>0,ROUND(增值税表!M162*税金及附加表!B7,2),0)
A8: 地方教育费附加 | G8: =IF(增值税表!G162>0,ROUND(增值税表!G162*税金及附加表!B8,2),0) | H8: =IF(增值税表!H162>0,ROUND(增值税表!H162*税金及附加表!B8,2),0) | I8: =IF(增值税表!I162>0,ROUND(增值税表!I162*税金及附加表!B8,2),0) | J8: =IF(增值税表!J162>0,ROUND(增值税表!J162*税金及附加表!B8,2),0) | K8: =IF(增值税表!K162>0,ROUND(增值税表!K162*税金及附加表!B8,2),0) | L8: =IF(增值税表!L162>0,ROUND(增值税表!L162*税金及附加表!B8,2),0) | M8: =IF(增值税表!M162>0,ROUND(增值税表!M162*税金及附加表!B8,2),0)
A9: 印花税
A10: 房产税
A11: 土地使用税
A12: 车船使用税
A13: 环保税
A14: 消费税
A27: 合计 | C27: =SUM(C6:C26) | D27: =SUM(D6:D26) | E27: =SUM(E6:E26) | F27: =SUM(F6:F26) | G27: =SUM(G6:G26) | H27: =SUM(H6:H26) | I27: =SUM(I6:I26) | J27: =SUM(J6:J26) | ... M27: =SUM(M6:M26)
A29: 【HD】核对 | C29: =C27-历利调整后表!D24 | D29: =D27-历利调整后表!G24 | E29: =E27-历利调整后表!J24 | F29: =F27-历利调整后表!M24
A30: 占主营业务收入的比例（%） | C30: =ROUND(C27/营业收入表!C11,4) | D30: =ROUND(D27/营业收入表!D11,4) | E30: =ROUND(E27/营业收入表!E11,4) | F30: =ROUND(F27/营业收入表!F11,4) | G30: =ROUND(G27/营业收入表!G11,4) | H30: =ROUND(H27/营业收入表!H11,4) | I30: =ROUND(I27/营业收入表!I11,4) | J30: =ROUND(J27/营业收入表!J11,4) | ... M30: =ROUND(M27/营业收入表!M11,4)
A31: 占营业收入比例（%） | C31: =ROUND(C27/营业收入表!C17,4) | D31: =ROUND(D27/营业收入表!D17,4) | E31: =ROUND(E27/营业收入表!E17,4) | F31: =ROUND(F27/营业收入表!F17,4) | G31: =ROUND(G27/营业收入表!G17,4) | H31: =ROUND(H27/营业收入表!H17,4) | I31: =ROUND(I27/营业收入表!I17,4) | J31: =ROUND(J27/营业收入表!J17,4) | ... M31: =ROUND(M27/营业收入表!M17,4)

Sheet 增值税表
A1: 增值税预测表 | N1: =HYPERLINK("#目录1!A1","返回目录")
A2: 评估基准日：{{VALUATION_BASE_DATE}}
A3: ="被评估单位："&项目信息!B5&"" | M3: ="金额单位："&项目信息!B8&""
A4: 类别 | B4: 税率 | C4: 历史数据 | G4: 未来预测
C5: 2022年度 | D5: 2023年度 | E5: 2024年度 | F5: 2025年1-6月 | G5: 2025年7-12月 | H5: 2026年度 | I5: 2027年度 | J5: 2028年度 | K5: 2029年度 | L5: 2030年度 | M5: 永续年度
A6: 主营业务收入：
A7: 金额 | M7: =L7
A8: 销项税 | B8: 13.00% | C8: =ROUND($B8*C7,2) | D8: =ROUND($B8*D7,2) | E8: =ROUND($B8*E7,2) | F8: =ROUND($B8*F7,2) | G8: =ROUND($B8*G7,2) | H8: =ROUND($B8*H7,2) | I8: =ROUND($B8*I7,2) | J8: =ROUND($B8*J7,2) | ... M8: =ROUND($B8*M7,2)
A9: 金额
A10: 销项税 | B10: 9.00% | C10: =ROUND($B10*C9,2) | D10: =ROUND($B10*D9,2) | E10: =ROUND($B10*E9,2) | F10: =ROUND($B10*F9,2) | G10: =ROUND($B10*G9,2) | H10: =ROUND($B10*H9,2) | I10: =ROUND($B10*I9,2) | J10: =ROUND($B10*J9,2) | ... M10: =ROUND($B10*M9,2)
A11: 金额
A12: 销项税 | B12: 6.00% | C12: =ROUND($B12*C11,2) | D12: =ROUND($B12*D11,2) | E12: =ROUND($B12*E11,2) | F12: =ROUND($B12*F11,2) | G12: =ROUND($B12*G11,2) | H12: =ROUND($B12*H11,2) | I12: =ROUND($B12*I11,2) | J12: =ROUND($B12*J11,2) | ... M12: =ROUND($B12*M11,2)
A13: 金额
A14: 销项税 | C14: =ROUND($B14*C13,2) | D14: =ROUND($B14*D13,2) | E14: =ROUND($B14*E13,2) | F14: =ROUND($B14*F13,2) | G14: =ROUND($B14*G13,2) | H14: =ROUND($B14*H13,2) | I14: =ROUND($B14*I13,2) | J14: =ROUND($B14*J13,2) | ... M14: =ROUND($B14*M13,2)
A15: 金额
A16: 销项税 | C16: =ROUND($B16*C15,2) | D16: =ROUND($B16*D15,2) | E16: =ROUND($B16*E15,2) | F16: =ROUND($B16*F15,2) | G16: =ROUND($B16*G15,2) | H16: =ROUND($B16*H15,2) | I16: =ROUND($B16*I15,2) | J16: =ROUND($B16*J15,2) | ... M16: =ROUND($B16*M15,2)
A17: 金额
A18: 销项税 | C18: =ROUND($B18*C17,2) | D18: =ROUND($B18*D17,2) | E18: =ROUND($B18*E17,2) | F18: =ROUND($B18*F17,2) | G18: =ROUND($B18*G17,2) | H18: =ROUND($B18*H17,2) | I18: =ROUND($B18*I17,2) | J18: =ROUND($B18*J17,2) | ... M18: =ROUND($B18*M17,2)
A19: 金额
A20: 销项税 | C20: =ROUND($B20*C19,2) | D20: =ROUND($B20*D19,2) | E20: =ROUND($B20*E19,2) | F20: =ROUND($B20*F19,2) | G20: =ROUND($B20*G19,2) | H20: =ROUND($B20*H19,2) | I20: =ROUND($B20*I19,2) | J20: =ROUND($B20*J19,2) | ... M20: =ROUND($B20*M19,2)
A21: 金额
A22: 销项税 | C22: =ROUND($B22*C21,2) | D22: =ROUND($B22*D21,2) | E22: =ROUND($B22*E21,2) | F22: =ROUND($B22*F21,2) | G22: =ROUND($B22*G21,2) | H22: =ROUND($B22*H21,2) | I22: =ROUND($B22*I21,2) | J22: =ROUND($B22*J21,2) | ... M22: =ROUND($B22*M21,2)
A23: 其他业务收入：
A24: 金额
A25: 销项税 | B25: 13.00% | C25: =ROUND($B25*C24,2) | D25: =ROUND($B25*D24,2) | E25: =ROUND($B25*E24,2) | F25: =ROUND($B25*F24,2) | G25: =ROUND($B25*G24,2) | H25: =ROUND($B25*H24,2) | I25: =ROUND($B25*I24,2) | J25: =ROUND($B25*J24,2) | ... M25: =ROUND($B25*M24,2)
A26: 金额
A27: 销项税 | B27: 9.00% | C27: =ROUND($B27*C26,2) | D27: =ROUND($B27*D26,2) | E27: =ROUND($B27*E26,2) | F27: =ROUND($B27*F26,2) | G27: =ROUND($B27*G26,2) | H27: =ROUND($B27*H26,2) | I27: =ROUND($B27*I26,2) | J27: =ROUND($B27*J26,2) | ... M27: =ROUND($B27*M26,2)
A28: 金额
A29: 销项税 | B29: 6.00% | C29: =ROUND($B29*C28,2) | D29: =ROUND($B29*D28,2) | E29: =ROUND($B29*E28,2) | F29: =ROUND($B29*F28,2) | G29: =ROUND($B29*G28,2) | H29: =ROUND($B29*H28,2) | I29: =ROUND($B29*I28,2) | J29: =ROUND($B29*J28,2) | ... M29: =ROUND($B29*M28,2)
A30: 金额
A31: 销项税 | C31: =ROUND($B31*C30,2) | D31: =ROUND($B31*D30,2) | E31: =ROUND($B31*E30,2) | F31: =ROUND($B31*F30,2) | G31: =ROUND($B31*G30,2) | H31: =ROUND($B31*H30,2) | I31: =ROUND($B31*I30,2) | J31: =ROUND($B31*J30,2) | ... M31: =ROUND($B31*M30,2)
A32: 金额
A33: 销项税 | C33: =ROUND($B33*C32,2) | D33: =ROUND($B33*D32,2) | E33: =ROUND($B33*E32,2) | F33: =ROUND($B33*F32,2) | G33: =ROUND($B33*G32,2) | H33: =ROUND($B33*H32,2) | I33: =ROUND($B33*I32,2) | J33: =ROUND($B33*J32,2) | ... M33: =ROUND($B33*M32,2)
A34: 金额
A35: 销项税 | C35: =ROUND($B35*C34,2) | D35: =ROUND($B35*D34,2) | E35: =ROUND($B35*E34,2) | F35: =ROUND($B35*F34,2) | G35: =ROUND($B35*G34,2) | H35: =ROUND($B35*H34,2) | I35: =ROUND($B35*I34,2) | J35: =ROUND($B35*J34,2) | ... M35: =ROUND($B35*M34,2)
A36: 金额
A37: 销项税 | C37: =ROUND($B37*C36,2) | D37: =ROUND($B37*D36,2) | E37: =ROUND($B37*E36,2) | F37: =ROUND($B37*F36,2) | G37: =ROUND($B37*G36,2) | H37: =ROUND($B37*H36,2) | I37: =ROUND($B37*I36,2) | J37: =ROUND($B37*J36,2) | ... M37: =ROUND($B37*M36,2)
A38: 金额
A39: 销项税 | C39: =ROUND($B39*C38,2) | D39: =ROUND($B39*D38,2) | E39: =ROUND($B39*E38,2) | F39: =ROUND($B39*F38,2) | G39: =ROUND($B39*G38,2) | H39: =ROUND($B39*H38,2) | I39: =ROUND($B39*I38,2) | J39: =ROUND($B39*J38,2) | ... M39: =ROUND($B39*M38,2)
A40: 销项税合计 | C40: =SUMIF($A6:$A39,$A8,C6:C39) | D40: =SUMIF($A6:$A39,$A8,D6:D39) | E40: =SUMIF($A6:$A39,$A8,E6:E39) | F40: =SUMIF($A6:$A39,$A8,F6:F39) | G40: =SUMIF($A6:$A39,$A8,G6:G39) | H40: =SUMIF($A6:$A39,$A8,H6:H39) | I40: =SUMIF($A6:$A39,$A8,I6:I39) | J40: =SUMIF($A6:$A39,$A8,J6:J39) | ... M40: =SUMIF($A6:$A39,$A8,M6:M39)
A41: 主营业务成本：
A42: 金额 | M42: =L42
A43: 进项税 | B43: 13.00% | C43: =ROUND($B43*C42,2) | D43: =ROUND($B43*D42,2) | E43: =ROUND($B43*E42,2) | F43: =ROUND($B43*F42,2) | G43: =ROUND($B43*G42,2) | H43: =ROUND($B43*H42,2) | I43: =ROUND($B43*I42,2) | J43: =ROUND($B43*J42,2) | ... M43: =ROUND($B43*M42,2)
A44: 金额 | M44: =L44
A45: 进项税 | B45: 9.00% | C45: =ROUND($B45*C44,2) | D45: =ROUND($B45*D44,2) | E45: =ROUND($B45*E44,2) | F45: =ROUND($B45*F44,2) | G45: =ROUND($B45*G44,2) | H45: =ROUND($B45*H44,2) | I45: =ROUND($B45*I44,2) | J45: =ROUND($B45*J44,2) | ... M45: =ROUND($B45*M44,2)
A46: 金额
A47: 进项税 | B47: 6.00% | C47: =ROUND($B47*C46,2) | D47: =ROUND($B47*D46,2) | E47: =ROUND($B47*E46,2) | F47: =ROUND($B47*F46,2) | G47: =ROUND($B47*G46,2) | H47: =ROUND($B47*H46,2) | I47: =ROUND($B47*I46,2) | J47: =ROUND($B47*J46,2) | ... M47: =ROUND($B47*M46,2)
A48: 金额 | M48: =L48
A49: 进项税 | C49: =ROUND($B49*C48,2) | D49: =ROUND($B49*D48,2) | E49: =ROUND($B49*E48,2) | F49: =ROUND($B49*F48,2) | G49: =ROUND($B49*G48,2) | H49: =ROUND($B49*H48,2) | I49: =ROUND($B49*I48,2) | J49: =ROUND($B49*J48,2) | ... M49: =ROUND($B49*M48,2)
A50: 金额
A51: 进项税 | C51: =ROUND($B51*C50,2) | D51: =ROUND($B51*D50,2) | E51: =ROUND($B51*E50,2) | F51: =ROUND($B51*F50,2) | G51: =ROUND($B51*G50,2) | H51: =ROUND($B51*H50,2) | I51: =ROUND($B51*I50,2) | J51: =ROUND($B51*J50,2) | ... M51: =ROUND($B51*M50,2)
A52: 金额
A53: 进项税 | C53: =ROUND($B53*C52,2) | D53: =ROUND($B53*D52,2) | E53: =ROUND($B53*E52,2) | F53: =ROUND($B53*F52,2) | G53: =ROUND($B53*G52,2) | H53: =ROUND($B53*H52,2) | I53: =ROUND($B53*I52,2) | J53: =ROUND($B53*J52,2) | ... M53: =ROUND($B53*M52,2)
A54: 金额
A55: 进项税 | C55: =ROUND($B55*C54,2) | D55: =ROUND($B55*D54,2) | E55: =ROUND($B55*E54,2) | F55: =ROUND($B55*F54,2) | G55: =ROUND($B55*G54,2) | H55: =ROUND($B55*H54,2) | I55: =ROUND($B55*I54,2) | J55: =ROUND($B55*J54,2) | ... M55: =ROUND($B55*M54,2)
A56: 金额
A57: 进项税 | C57: =ROUND($B57*C56,2) | D57: =ROUND($B57*D56,2) | E57: =ROUND($B57*E56,2) | F57: =ROUND($B57*F56,2) | G57: =ROUND($B57*G56,2) | H57: =ROUND($B57*H56,2) | I57: =ROUND($B57*I56,2) | J57: =ROUND($B57*J56,2) | ... M57: =ROUND($B57*M56,2)
A58: 其他业务成本：
A59: 金额
A60: 进项税 | B60: 13.00% | C60: =ROUND($B60*C59,2) | D60: =ROUND($B60*D59,2) | E60: =ROUND($B60*E59,2) | F60: =ROUND($B60*F59,2) | G60: =ROUND($B60*G59,2) | H60: =ROUND($B60*H59,2) | I60: =ROUND($B60*I59,2) | J60: =ROUND($B60*J59,2) | ... M60: =ROUND($B60*M59,2)
A61: 金额
A62: 进项税 | B62: 9.00% | C62: =ROUND($B62*C61,2) | D62: =ROUND($B62*D61,2) | E62: =ROUND($B62*E61,2) | F62: =ROUND($B62*F61,2) | G62: =ROUND($B62*G61,2) | H62: =ROUND($B62*H61,2) | I62: =ROUND($B62*I61,2) | J62: =ROUND($B62*J61,2) | ... M62: =ROUND($B62*M61,2)
A63: 金额
A64: 进项税 | B64: 6.00% | C64: =ROUND($B64*C63,2) | D64: =ROUND($B64*D63,2) | E64: =ROUND($B64*E63,2) | F64: =ROUND($B64*F63,2) | G64: =ROUND($B64*G63,2) | H64: =ROUND($B64*H63,2) | I64: =ROUND($B64*I63,2) | J64: =ROUND($B64*J63,2) | ... M64: =ROUND($B64*M63,2)
A65: 金额
A66: 进项税 | C66: =ROUND($B66*C65,2) | D66: =ROUND($B66*D65,2) | E66: =ROUND($B66*E65,2) | F66: =ROUND($B66*F65,2) | G66: =ROUND($B66*G65,2) | H66: =ROUND($B66*H65,2) | I66: =ROUND($B66*I65,2) | J66: =ROUND($B66*J65,2) | ... M66: =ROUND($B66*M65,2)
A67: 金额
A68: 进项税 | C68: =ROUND($B68*C67,2) | D68: =ROUND($B68*D67,2) | E68: =ROUND($B68*E67,2) | F68: =ROUND($B68*F67,2) | G68: =ROUND($B68*G67,2) | H68: =ROUND($B68*H67,2) | I68: =ROUND($B68*I67,2) | J68: =ROUND($B68*J67,2) | ... M68: =ROUND($B68*M67,2)
A69: 金额
A70: 进项税 | C70: =ROUND($B70*C69,2) | D70: =ROUND($B70*D69,2) | E70: =ROUND($B70*E69,2) | F70: =ROUND($B70*F69,2) | G70: =ROUND($B70*G69,2) | H70: =ROUND($B70*H69,2) | I70: =ROUND($B70*I69,2) | J70: =ROUND($B70*J69,2) | ... M70: =ROUND($B70*M69,2)
A71: 金额
A72: 进项税 | C72: =ROUND($B72*C71,2) | D72: =ROUND($B72*D71,2) | E72: =ROUND($B72*E71,2) | F72: =ROUND($B72*F71,2) | G72: =ROUND($B72*G71,2) | H72: =ROUND($B72*H71,2) | I72: =ROUND($B72*I71,2) | J72: =ROUND($B72*J71,2) | ... M72: =ROUND($B72*M71,2)
A73: 金额
A74: 进项税 | C74: =ROUND($B74*C73,2) | D74: =ROUND($B74*D73,2) | E74: =ROUND($B74*E73,2) | F74: =ROUND($B74*F73,2) | G74: =ROUND($B74*G73,2) | H74: =ROUND($B74*H73,2) | I74: =ROUND($B74*I73,2) | J74: =ROUND($B74*J73,2) | ... M74: =ROUND($B74*M73,2)
A75: 制造费用：
A76: 金额
A77: 进项税 | B77: 13.00% | C77: =ROUND($B77*C76,2) | D77: =ROUND($B77*D76,2) | E77: =ROUND($B77*E76,2) | F77: =ROUND($B77*F76,2) | G77: =ROUND($B77*G76,2) | H77: =ROUND($B77*H76,2) | I77: =ROUND($B77*I76,2) | J77: =ROUND($B77*J76,2) | ... M77: =ROUND($B77*M76,2)
A78: 金额
A79: 进项税 | B79: 9.00% | C79: =ROUND($B79*C78,2) | D79: =ROUND($B79*D78,2) | E79: =ROUND($B79*E78,2) | F79: =ROUND($B79*F78,2) | G79: =ROUND($B79*G78,2) | H79: =ROUND($B79*H78,2) | I79: =ROUND($B79*I78,2) | J79: =ROUND($B79*J78,2) | ... M79: =ROUND($B79*M78,2)
A80: 金额
A81: 进项税 | B81: 6.00% | C81: =ROUND($B81*C80,2) | D81: =ROUND($B81*D80,2) | E81: =ROUND($B81*E80,2) | F81: =ROUND($B81*F80,2) | G81: =ROUND($B81*G80,2) | H81: =ROUND($B81*H80,2) | I81: =ROUND($B81*I80,2) | J81: =ROUND($B81*J80,2) | ... M81: =ROUND($B81*M80,2)
A82: 金额
A83: 进项税 | C83: =ROUND($B83*C82,2) | D83: =ROUND($B83*D82,2) | E83: =ROUND($B83*E82,2) | F83: =ROUND($B83*F82,2) | G83: =ROUND($B83*G82,2) | H83: =ROUND($B83*H82,2) | I83: =ROUND($B83*I82,2) | J83: =ROUND($B83*J82,2) | ... M83: =ROUND($B83*M82,2)
A84: 金额
A85: 进项税 | C85: =ROUND($B85*C84,2) | D85: =ROUND($B85*D84,2) | E85: =ROUND($B85*E84,2) | F85: =ROUND($B85*F84,2) | G85: =ROUND($B85*G84,2) | H85: =ROUND($B85*H84,2) | I85: =ROUND($B85*I84,2) | J85: =ROUND($B85*J84,2) | ... M85: =ROUND($B85*M84,2)
A86: 金额
A87: 进项税 | C87: =ROUND($B87*C86,2) | D87: =ROUND($B87*D86,2) | E87: =ROUND($B87*E86,2) | F87: =ROUND($B87*F86,2) | G87: =ROUND($B87*G86,2) | H87: =ROUND($B87*H86,2) | I87: =ROUND($B87*I86,2) | J87: =ROUND($B87*J86,2) | ... M87: =ROUND($B87*M86,2)
A88: 金额
A89: 进项税 | C89: =ROUND($B89*C88,2) | D89: =ROUND($B89*D88,2) | E89: =ROUND($B89*E88,2) | F89: =ROUND($B89*F88,2) | G89: =ROUND($B89*G88,2) | H89: =ROUND($B89*H88,2) | I89: =ROUND($B89*I88,2) | J89: =ROUND($B89*J88,2) | ... M89: =ROUND($B89*M88,2)
A90: 金额
A91: 进项税 | C91: =ROUND($B91*C90,2) | D91: =ROUND($B91*D90,2) | E91: =ROUND($B91*E90,2) | F91: =ROUND($B91*F90,2) | G91: =ROUND($B91*G90,2) | H91: =ROUND($B91*H90,2) | I91: =ROUND($B91*I90,2) | J91: =ROUND($B91*J90,2) | ... M91: =ROUND($B91*M90,2)
A92: 销售费用：
A93: 金额
A94: 进项税 | B94: 13.00% | C94: =ROUND($B94*C93,2) | D94: =ROUND($B94*D93,2) | E94: =ROUND($B94*E93,2) | F94: =ROUND($B94*F93,2) | G94: =ROUND($B94*G93,2) | H94: =ROUND($B94*H93,2) | I94: =ROUND($B94*I93,2) | J94: =ROUND($B94*J93,2) | ... M94: =ROUND($B94*M93,2)
A95: 金额
A96: 进项税 | B96: 9.00% | C96: =ROUND($B96*C95,2) | D96: =ROUND($B96*D95,2) | E96: =ROUND($B96*E95,2) | F96: =ROUND($B96*F95,2) | G96: =ROUND($B96*G95,2) | H96: =ROUND($B96*H95,2) | I96: =ROUND($B96*I95,2) | J96: =ROUND($B96*J95,2) | ... M96: =ROUND($B96*M95,2)
A97: 金额
A98: 进项税 | B98: 6.00% | C98: =ROUND($B98*C97,2) | D98: =ROUND($B98*D97,2) | E98: =ROUND($B98*E97,2) | F98: =ROUND($B98*F97,2) | G98: =ROUND($B98*G97,2) | H98: =ROUND($B98*H97,2) | I98: =ROUND($B98*I97,2) | J98: =ROUND($B98*J97,2) | ... M98: =ROUND($B98*M97,2)
A99: 金额
A100: 进项税 | C100: =ROUND($B100*C99,2) | D100: =ROUND($B100*D99,2) | E100: =ROUND($B100*E99,2) | F100: =ROUND($B100*F99,2) | G100: =ROUND($B100*G99,2) | H100: =ROUND($B100*H99,2) | I100: =ROUND($B100*I99,2) | J100: =ROUND($B100*J99,2) | ... M100: =ROUND($B100*M99,2)
...

Sheet 销售费用表
A1: 销售费用分析预测表 | N1: =HYPERLINK("#目录1!A1","返回目录")
A2: 评估基准日：{{VALUATION_BASE_DATE}}
A3: ="被评估单位："&项目信息!B5&"" | M3: ="金额单位："&项目信息!B8&""
A4: 项目 | C4: 历史数据 | G4: 未来预测
C5: 2022年度 | D5: 2023年度 | E5: 2024年度 | F5: 2025年1-6月 | G5: 2025年7-12月 | H5: 2026年度 | I5: 2027年度 | J5: 2028年度 | K5: 2029年度 | L5: 2030年度 | M5: 永续年度
A6: 人工
A7: 折旧 | G7: =折旧摊销、资本性支出表!G11 | H7: =折旧摊销、资本性支出表!H11 | I7: =折旧摊销、资本性支出表!I11 | J7: =折旧摊销、资本性支出表!J11 | K7: =折旧摊销、资本性支出表!K11 | L7: =折旧摊销、资本性支出表!L11 | M7: =折旧摊销、资本性支出表!M11
A8: 摊销 | G8: =折旧摊销、资本性支出表!G12 | H8: =折旧摊销、资本性支出表!H12 | I8: =折旧摊销、资本性支出表!I12 | J8: =折旧摊销、资本性支出表!J12 | K8: =折旧摊销、资本性支出表!K12 | L8: =折旧摊销、资本性支出表!L12 | M8: =折旧摊销、资本性支出表!M12
A9: 业务招待费
A10: 使用权资产折旧
A11: 房屋租赁费
A62: 合计 | C62: =SUM(C6:C61) | D62: =SUM(D6:D61) | E62: =SUM(E6:E61) | F62: =SUM(F6:F61) | G62: =SUM(G6:G61) | H62: =SUM(H6:H61) | I62: =SUM(I6:I61) | J62: =SUM(J6:J61) | ... M62: =SUM(M6:M61)
A64: 【HD】核对 | C64: =C62-历利调整后表!D25 | D64: =D62-历利调整后表!G25 | E64: =E62-历利调整后表!J25 | F64: =F62-历利调整后表!M25
A65: 占营业收入比例（%） | C65: =ROUND(C62/营业收入表!C17,4) | D65: =ROUND(D62/营业收入表!D17,4) | E65: =ROUND(E62/营业收入表!E17,4) | F65: =ROUND(F62/营业收入表!F17,4) | G65: =ROUND(G62/营业收入表!G17,4) | H65: =ROUND(H62/营业收入表!H17,4) | I65: =ROUND(I62/营业收入表!I17,4) | J65: =ROUND(J62/营业收入表!J17,4) | ... M65: =ROUND(M62/营业收入表!M17,4)
A66: 人工核对 | C66: =C6-人工成本表!C29 | D66: =D6-人工成本表!D29 | E66: =E6-人工成本表!E29 | F66: =F6-人工成本表!F29 | G66: =G6-人工成本表!G29 | H66: =H6-人工成本表!H29 | I66: =I6-人工成本表!I29 | J66: =J6-人工成本表!J29 | ... M66: =M6-人工成本表!M29

Sheet 管理费用表
A1: 管理费用分析预测表 | N1: =HYPERLINK("#目录1!A1","返回目录")
A2: 评估基准日：{{VALUATION_BASE_DATE}}
A3: ="被评估单位："&项目信息!B5&"" | M3: ="金额单位："&项目信息!B8&""
A4: 项目 | C4: 历史数据 | G4: 未来预测
C5: 2022年度 | D5: 2023年度 | E5: 2024年度 | F5: 2025年1-6月 | G5: 2025年7-12月 | H5: 2026年度 | I5: 2027年度 | J5: 2028年度 | K5: 2029年度 | L5: 2030年度 | M5: 永续年度
A6: 人工
A7: 折旧 | G7: =折旧摊销、资本性支出表!G13 | H7: =折旧摊销、资本性支出表!H13 | I7: =折旧摊销、资本性支出表!I13 | J7: =折旧摊销、资本性支出表!J13 | K7: =折旧摊销、资本性支出表!K13 | L7: =折旧摊销、资本性支出表!L13 | M7: =折旧摊销、资本性支出表!M13
A8: 摊销 | G8: =折旧摊销、资本性支出表!G14 | H8: =折旧摊销、资本性支出表!H14 | I8: =折旧摊销、资本性支出表!I14 | J8: =折旧摊销、资本性支出表!J14 | K8: =折旧摊销、资本性支出表!K14 | L8: =折旧摊销、资本性支出表!L14 | M8: =折旧摊销、资本性支出表!M14
A9: 业务招待费
A10: 使用权资产折旧
A11: 房屋租赁费
A12: 其他 | M12: =L12
A62: 合计 | C62: =SUM(C6:C61) | D62: =SUM(D6:D61) | E62: =SUM(E6:E61) | F62: =SUM(F6:F61) | G62: =SUM(G6:G61) | H62: =SUM(H6:H61) | I62: =SUM(I6:I61) | J62: =SUM(J6:J61) | ... M62: =SUM(M6:M61)
A64: 【HD】核对 | C64: =C62-历利调整后表!D26 | D64: =D62-历利调整后表!G26 | E64: =E62-历利调整后表!J26 | F64: =F62-历利调整后表!M26
A65: 占营业收入比例（%） | C65: =ROUND(C62/营业收入表!C17,4) | D65: =ROUND(D62/营业收入表!D17,4) | E65: =ROUND(E62/营业收入表!E17,4) | F65: =ROUND(F62/营业收入表!F17,4) | G65: =ROUND(G62/营业收入表!G17,4) | H65: =ROUND(H62/营业收入表!H17,4) | I65: =ROUND(I62/营业收入表!I17,4) | J65: =ROUND(J62/营业收入表!J17,4) | ... M65: =ROUND(M62/营业收入表!M17,4)
A66: 人工核对 | C66: =C6-人工成本表!C30 | D66: =D6-人工成本表!D30 | E66: =E6-人工成本表!E30 | F66: =F6-人工成本表!F30 | G66: =G6-人工成本表!G30 | H66: =H6-人工成本表!H30 | I66: =I6-人工成本表!I30 | J66: =J6-人工成本表!J30 | ... M66: =M6-人工成本表!M30

Sheet 研发费用表
A1: 研发费用分析预测表 | N1: =HYPERLINK("#目录1!A1","返回目录")
A2: 评估基准日：{{VALUATION_BASE_DATE}}
A3: ="被评估单位："&项目信息!B5&"" | M3: ="金额单位："&项目信息!B8&""
A4: 项目 | C4: 历史数据 | G4: 未来预测
C5: 2022年度 | D5: 2023年度 | E5: 2024年度 | F5: 2025年1-6月 | G5: 2025年7-12月 | H5: 2026年度 | I5: 2027年度 | J5: 2028年度 | K5: 2029年度 | L5: 2030年度 | M5: 永续年度
A6: 人工
A7: 材料
A8: 折旧 | G8: =折旧摊销、资本性支出表!G15 | H8: =折旧摊销、资本性支出表!H15 | I8: =折旧摊销、资本性支出表!I15 | J8: =折旧摊销、资本性支出表!J15 | K8: =折旧摊销、资本性支出表!K15 | L8: =折旧摊销、资本性支出表!L15 | M8: =折旧摊销、资本性支出表!M15
A9: 摊销 | G9: =折旧摊销、资本性支出表!G16 | H9: =折旧摊销、资本性支出表!H16 | I9: =折旧摊销、资本性支出表!I16 | J9: =折旧摊销、资本性支出表!J16 | K9: =折旧摊销、资本性支出表!K16 | L9: =折旧摊销、资本性支出表!L16 | M9: =折旧摊销、资本性支出表!M16
A10: 业务招待费
A11: 使用权资产折旧
A12: 房屋租赁费
A63: 合计 | C63: =SUM(C6:C62) | D63: =SUM(D6:D62) | E63: =SUM(E6:E62) | F63: =SUM(F6:F62) | G63: =SUM(G6:G62) | H63: =SUM(H6:H62) | I63: =SUM(I6:I62) | J63: =SUM(J6:J62) | ... M63: =SUM(M6:M62)
A65: 【HD】核对 | C65: =C63-历利调整后表!D27 | D65: =D63-历利调整后表!G27 | E65: =E63-历利调整后表!J27 | F65: =F63-历利调整后表!M27
A66: 占营业收入比例（%） | C66: =ROUND(C63/营业收入表!C17,4) | D66: =ROUND(D63/营业收入表!D17,4) | E66: =ROUND(E63/营业收入表!E17,4) | F66: =ROUND(F63/营业收入表!F17,4) | G66: =ROUND(G63/营业收入表!G17,4) | H66: =ROUND(H63/营业收入表!H17,4) | I66: =ROUND(I63/营业收入表!I17,4) | J66: =ROUND(J63/营业收入表!J17,4) | ... M66: =ROUND(M63/营业收入表!M17,4)
A67: 人工核对 | C67: =C6-人工成本表!C31 | D67: =D6-人工成本表!D31 | E67: =E6-人工成本表!E31 | F67: =F6-人工成本表!F31 | G67: =G6-人工成本表!G31 | H67: =H6-人工成本表!H31 | I67: =I6-人工成本表!I31 | J67: =J6-人工成本表!J31 | ... M67: =M6-人工成本表!M31

Sheet 财务费用表
A1: 财务费用分析预测表 | N1: =HYPERLINK("#目录1!A1","返回目录")
A2: 评估基准日：{{VALUATION_BASE_DATE}}
A3: ="被评估单位："&项目信息!B5&"" | M3: ="金额单位："&项目信息!B8&""
A4: 项目 | C4: 历史数据 | G4: 未来预测
C5: 2022年度 | D5: 2023年度 | E5: 2024年度 | F5: 2025年1-6月 | G5: 2025年7-12月 | H5: 2026年度 | I5: 2027年度 | J5: 2028年度 | K5: 2029年度 | L5: 2030年度 | M5: 永续年度
A6: 利息支出
A7: 利息收入
A8: 汇兑损益
A9: 手续费
A10: 贴现息
A11: 未确认融资费用
A15: 合计 | C15: =SUM(C6:C14) | D15: =SUM(D6:D14) | E15: =SUM(E6:E14) | F15: =SUM(F6:F14) | G15: =SUM(G6:G14) | H15: =SUM(H6:H14) | I15: =SUM(I6:I14) | J15: =SUM(J6:J14) | ... M15: =SUM(M6:M14)
A17: 【HD】核对 | C17: =C15-历利调整后表!D28 | D17: =D15-历利调整后表!G28 | E17: =E15-历利调整后表!J28 | F17: =F15-历利调整后表!M28
A18: 占营业收入比例（%） | C18: =ROUND(C15/营业收入表!C17,4) | D18: =ROUND(D15/营业收入表!D17,4) | E18: =ROUND(E15/营业收入表!E17,4) | F18: =ROUND(F15/营业收入表!F17,4) | G18: =ROUND(G15/营业收入表!G17,4) | H18: =ROUND(H15/营业收入表!H17,4) | I18: =ROUND(I15/营业收入表!I17,4) | J18: =ROUND(J15/营业收入表!J17,4) | ... M18: =ROUND(M15/营业收入表!M17,4)

Sheet 其他收益表
A1: 其他收益分析预测表 | N1: =HYPERLINK("#目录1!A1","返回目录")
A2: 评估基准日：{{VALUATION_BASE_DATE}}
A3: ="被评估单位："&项目信息!B5&"" | M3: ="金额单位："&项目信息!B8&""
A4: 项目 | C4: 历史数据 | G4: 未来预测
C5: 2022年度 | D5: 2023年度 | E5: 2024年度 | F5: 2025年1-6月 | G5: 2025年7-12月 | H5: 2026年度 | I5: 2027年度 | J5: 2028年度 | K5: 2029年度 | L5: 2030年度 | M5: 永续年度
A9: 合计 | C9: =SUM(C6:C8) | D9: =SUM(D6:D8) | E9: =SUM(E6:E8) | F9: =SUM(F6:F8) | G9: =SUM(G6:G8) | H9: =SUM(H6:H8) | I9: =SUM(I6:I8) | J9: =SUM(J6:J8) | ... M9: =SUM(M6:M8)
A11: 【HD】核对 | C11: =C9-历利调整后表!D31 | D11: =D9-历利调整后表!G31 | E11: =E9-历利调整后表!J31 | F11: =F9-历利调整后表!M31
A12: 增长率（%） | D12: =ROUND((D9-C9)/C9,4) | E12: =ROUND((E9-D9)/D9,4) | F12: =ROUND((F9/6*12-E9)/E9,4) | G12: =ROUND((G9+F9-E9)/E9,4) | H12: =ROUND((H9-(G9+F9))/(G9+F9),4) | I12: =ROUND((I9-H9)/H9,4) | J12: =ROUND((J9-I9)/I9,4) | K12: =ROUND((K9-J9)/J9,4) | L12: =ROUND((L9-K9)/K9,4) | M12: =ROUND((M9-L9)/L9,4)

Sheet 投资收益表
A1: 投资收益分析预测表 | N1: =HYPERLINK("#目录1!A1","返回目录")
A2: 评估基准日：{{VALUATION_BASE_DATE}}
A3: ="被评估单位："&项目信息!B5&"" | M3: ="金额单位："&项目信息!B8&""
A4: 项目 | C4: 历史数据 | G4: 未来预测
C5: 2022年度 | D5: 2023年度 | E5: 2024年度 | F5: 2025年1-6月 | G5: 2025年7-12月 | H5: 2026年度 | I5: 2027年度 | J5: 2028年度 | K5: 2029年度 | L5: 2030年度 | M5: 永续年度
A9: 合计 | C9: =SUM(C6:C8) | D9: =SUM(D6:D8) | E9: =SUM(E6:E8) | F9: =SUM(F6:F8) | G9: =SUM(G6:G8) | H9: =SUM(H6:H8) | I9: =SUM(I6:I8) | J9: =SUM(J6:J8) | ... M9: =SUM(M6:M8)
A11: 【HD】核对 | C11: =C9-历利调整后表!D32 | D11: =D9-历利调整后表!G32 | E11: =E9-历利调整后表!J32 | F11: =F9-历利调整后表!M32
A12: 增长率（%） | D12: =ROUND((D9-C9)/C9,4) | E12: =ROUND((E9-D9)/D9,4) | F12: =ROUND((F9/6*12-E9)/E9,4) | G12: =ROUND((G9+F9-E9)/E9,4) | H12: =ROUND((H9-(G9+F9))/(G9+F9),4) | I12: =ROUND((I9-H9)/H9,4) | J12: =ROUND((J9-I9)/I9,4) | K12: =ROUND((K9-J9)/J9,4) | L12: =ROUND((L9-K9)/K9,4) | M12: =ROUND((M9-L9)/L9,4)

Sheet 汇兑收益表
A1: 汇兑收益分析预测表 | N1: =HYPERLINK("#目录1!A1","返回目录")
A2: 评估基准日：{{VALUATION_BASE_DATE}}
A3: ="被评估单位："&项目信息!B5&"" | M3: ="金额单位："&项目信息!B8&""
A4: 项目 | C4: 历史数据 | G4: 未来预测
C5: 2022年度 | D5: 2023年度 | E5: 2024年度 | F5: 2025年1-6月 | G5: 2025年7-12月 | H5: 2026年度 | I5: 2027年度 | J5: 2028年度 | K5: 2029年度 | L5: 2030年度 | M5: 永续年度
A9: 合计 | C9: =SUM(C6:C8) | D9: =SUM(D6:D8) | E9: =SUM(E6:E8) | F9: =SUM(F6:F8) | G9: =SUM(G6:G8) | H9: =SUM(H6:H8) | I9: =SUM(I6:I8) | J9: =SUM(J6:J8) | ... M9: =SUM(M6:M8)
A11: 【HD】核对 | C11: =C9-历利调整后表!D35 | D11: =D9-历利调整后表!G35 | E11: =E9-历利调整后表!J35 | F11: =F9-历利调整后表!M35
A12: 增长率（%） | D12: =ROUND((D9-C9)/C9,4) | E12: =ROUND((E9-D9)/D9,4) | F12: =ROUND((F9/6*12-E9)/E9,4) | G12: =ROUND((G9+F9-E9)/E9,4) | H12: =ROUND((H9-(G9+F9))/(G9+F9),4) | I12: =ROUND((I9-H9)/H9,4) | J12: =ROUND((J9-I9)/I9,4) | K12: =ROUND((K9-J9)/J9,4) | L12: =ROUND((L9-K9)/K9,4) | M12: =ROUND((M9-L9)/L9,4)

Sheet 净敞口套期收益表
A1: 净敞口套期收益分析预测表 | N1: =HYPERLINK("#目录1!A1","返回目录")
A2: 评估基准日：{{VALUATION_BASE_DATE}}
A3: ="被评估单位："&项目信息!B5&"" | M3: ="金额单位："&项目信息!B8&""
A4: 项目 | C4: 历史数据 | G4: 未来预测
C5: 2022年度 | D5: 2023年度 | E5: 2024年度 | F5: 2025年1-6月 | G5: 2025年7-12月 | H5: 2026年度 | I5: 2027年度 | J5: 2028年度 | K5: 2029年度 | L5: 2030年度 | M5: 永续年度
A9: 合计 | C9: =SUM(C6:C8) | D9: =SUM(D6:D8) | E9: =SUM(E6:E8) | F9: =SUM(F6:F8) | G9: =SUM(G6:G8) | H9: =SUM(H6:H8) | I9: =SUM(I6:I8) | J9: =SUM(J6:J8) | ... M9: =SUM(M6:M8)
A11: 【HD】核对 | C11: =C9-历利调整后表!D36 | D11: =D9-历利调整后表!G36 | E11: =E9-历利调整后表!J36 | F11: =F9-历利调整后表!M36
A12: 增长率（%） | D12: =ROUND((D9-C9)/C9,4) | E12: =ROUND((E9-D9)/D9,4) | F12: =ROUND((F9/6*12-E9)/E9,4) | G12: =ROUND((G9+F9-E9)/E9,4) | H12: =ROUND((H9-(G9+F9))/(G9+F9),4) | I12: =ROUND((I9-H9)/H9,4) | J12: =ROUND((J9-I9)/I9,4) | K12: =ROUND((K9-J9)/J9,4) | L12: =ROUND((L9-K9)/K9,4) | M12: =ROUND((M9-L9)/L9,4)

Sheet 公允价值变动收益表
A1: 公允价值变动收益分析预测表 | N1: =HYPERLINK("#目录1!A1","返回目录")
A2: 评估基准日：{{VALUATION_BASE_DATE}}
A3: ="被评估单位："&项目信息!B5&"" | M3: ="金额单位："&项目信息!B8&""
A4: 项目 | C4: 历史数据 | G4: 未来预测
C5: 2022年度 | D5: 2023年度 | E5: 2024年度 | F5: 2025年1-6月 | G5: 2025年7-12月 | H5: 2026年度 | I5: 2027年度 | J5: 2028年度 | K5: 2029年度 | L5: 2030年度 | M5: 永续年度
A9: 合计 | C9: =SUM(C6:C8) | D9: =SUM(D6:D8) | E9: =SUM(E6:E8) | F9: =SUM(F6:F8) | G9: =SUM(G6:G8) | H9: =SUM(H6:H8) | I9: =SUM(I6:I8) | J9: =SUM(J6:J8) | ... M9: =SUM(M6:M8)
A11: 【HD】核对 | C11: =C9-历利调整后表!D37 | D11: =D9-历利调整后表!G37 | E11: =E9-历利调整后表!J37 | F11: =F9-历利调整后表!M37
A12: 增长率（%） | D12: =ROUND((D9-C9)/C9,4) | E12: =ROUND((E9-D9)/D9,4) | F12: =ROUND((F9/6*12-E9)/E9,4) | G12: =ROUND((G9+F9-E9)/E9,4) | H12: =ROUND((H9-(G9+F9))/(G9+F9),4) | I12: =ROUND((I9-H9)/H9,4) | J12: =ROUND((J9-I9)/I9,4) | K12: =ROUND((K9-J9)/J9,4) | L12: =ROUND((L9-K9)/K9,4) | M12: =ROUND((M9-L9)/L9,4)

Sheet 信用减值损失表
A1: 信用减值损失分析预测表 | N1: =HYPERLINK("#目录1!A1","返回目录")
A2: 评估基准日：{{VALUATION_BASE_DATE}}
A3: ="被评估单位："&项目信息!B5&"" | M3: ="金额单位："&项目信息!B8&""
A4: 项目 | C4: 历史数据 | G4: 未来预测
C5: 2022年度 | D5: 2023年度 | E5: 2024年度 | F5: 2025年1-6月 | G5: 2025年7-12月 | H5: 2026年度 | I5: 2027年度 | J5: 2028年度 | K5: 2029年度 | L5: 2030年度 | M5: 永续年度
A9: 合计 | C9: =SUM(C6:C8) | D9: =SUM(D6:D8) | E9: =SUM(E6:E8) | F9: =SUM(F6:F8) | G9: =SUM(G6:G8) | H9: =SUM(H6:H8) | I9: =SUM(I6:I8) | J9: =SUM(J6:J8) | ... M9: =SUM(M6:M8)
A11: 【HD】核对 | C11: =C9+历利调整后表!D38 | D11: =D9+历利调整后表!G38 | E11: =E9+历利调整后表!J38 | F11: =F9+历利调整后表!M38
A12: 增长率（%） | D12: =ROUND((D9-C9)/C9,4) | E12: =ROUND((E9-D9)/D9,4) | F12: =ROUND((F9/6*12-E9)/E9,4) | G12: =ROUND((G9+F9-E9)/E9,4) | H12: =ROUND((H9-(G9+F9))/(G9+F9),4) | I12: =ROUND((I9-H9)/H9,4) | J12: =ROUND((J9-I9)/I9,4) | K12: =ROUND((K9-J9)/J9,4) | L12: =ROUND((L9-K9)/K9,4) | M12: =ROUND((M9-L9)/L9,4)

Sheet 资产减值损失表
A1: 资产减值损失分析预测表 | N1: =HYPERLINK("#目录1!A1","返回目录")
A2: 评估基准日：{{VALUATION_BASE_DATE}}
A3: ="被评估单位："&项目信息!B5&"" | M3: ="金额单位："&项目信息!B8&""
A4: 项目 | C4: 历史数据 | G4: 未来预测
C5: 2022年度 | D5: 2023年度 | E5: 2024年度 | F5: 2025年1-6月 | G5: 2025年7-12月 | H5: 2026年度 | I5: 2027年度 | J5: 2028年度 | K5: 2029年度 | L5: 2030年度 | M5: 永续年度
A9: 合计 | C9: =SUM(C6:C8) | D9: =SUM(D6:D8) | E9: =SUM(E6:E8) | F9: =SUM(F6:F8) | G9: =SUM(G6:G8) | H9: =SUM(H6:H8) | I9: =SUM(I6:I8) | J9: =SUM(J6:J8) | ... M9: =SUM(M6:M8)
A11: 【HD】核对 | C11: =C9+历利调整后表!D39 | D11: =D9+历利调整后表!G39 | E11: =E9+历利调整后表!J39 | F11: =F9+历利调整后表!M39
A12: 增长率（%） | D12: =ROUND((D9-C9)/C9,4) | E12: =ROUND((E9-D9)/D9,4) | F12: =ROUND((F9/6*12-E9)/E9,4) | G12: =ROUND((G9+F9-E9)/E9,4) | H12: =ROUND((H9-(G9+F9))/(G9+F9),4) | I12: =ROUND((I9-H9)/H9,4) | J12: =ROUND((J9-I9)/I9,4) | K12: =ROUND((K9-J9)/J9,4) | L12: =ROUND((L9-K9)/K9,4) | M12: =ROUND((M9-L9)/L9,4)

Sheet 资产处置收益表
A1: 资产处置收益分析预测表 | N1: =HYPERLINK("#目录1!A1","返回目录")
A2: 评估基准日：{{VALUATION_BASE_DATE}}
A3: ="被评估单位："&项目信息!B5&"" | M3: ="金额单位："&项目信息!B8&""
A4: 项目 | C4: 历史数据 | G4: 未来预测
C5: 2022年度 | D5: 2023年度 | E5: 2024年度 | F5: 2025年1-6月 | G5: 2025年7-12月 | H5: 2026年度 | I5: 2027年度 | J5: 2028年度 | K5: 2029年度 | L5: 2030年度 | M5: 永续年度
A9: 合计 | C9: =SUM(C6:C8) | D9: =SUM(D6:D8) | E9: =SUM(E6:E8) | F9: =SUM(F6:F8) | G9: =SUM(G6:G8) | H9: =SUM(H6:H8) | I9: =SUM(I6:I8) | J9: =SUM(J6:J8) | ... M9: =SUM(M6:M8)
A11: 【HD】核对 | C11: =C9-历利调整后表!D40 | D11: =D9-历利调整后表!G40 | E11: =E9-历利调整后表!J40 | F11: =F9-历利调整后表!M40
A12: 增长率（%） | D12: =ROUND((D9-C9)/C9,4) | E12: =ROUND((E9-D9)/D9,4) | F12: =ROUND((F9/6*12-E9)/E9,4) | G12: =ROUND((G9+F9-E9)/E9,4) | H12: =ROUND((H9-(G9+F9))/(G9+F9),4) | I12: =ROUND((I9-H9)/H9,4) | J12: =ROUND((J9-I9)/I9,4) | K12: =ROUND((K9-J9)/J9,4) | L12: =ROUND((L9-K9)/K9,4) | M12: =ROUND((M9-L9)/L9,4)

Sheet 营业外收入表
A1: 营业外收入分析预测表 | N1: =HYPERLINK("#目录1!A1","返回目录")
A2: 评估基准日：{{VALUATION_BASE_DATE}}
A3: ="被评估单位："&项目信息!B5&"" | M3: ="金额单位："&项目信息!B8&""
A4: 项目 | C4: 历史数据 | G4: 未来预测
C5: 2022年度 | D5: 2023年度 | E5: 2024年度 | F5: 2025年1-6月 | G5: 2025年7-12月 | H5: 2026年度 | I5: 2027年度 | J5: 2028年度 | K5: 2029年度 | L5: 2030年度 | M5: 永续年度
A9: 合计 | C9: =SUM(C6:C8) | D9: =SUM(D6:D8) | E9: =SUM(E6:E8) | F9: =SUM(F6:F8) | G9: =SUM(G6:G8) | H9: =SUM(H6:H8) | I9: =SUM(I6:I8) | J9: =SUM(J6:J8) | ... M9: =SUM(M6:M8)
A11: 【HD】核对 | C11: =C9-历利调整后表!D42 | D11: =D9-历利调整后表!G42 | E11: =E9-历利调整后表!J42 | F11: =F9-历利调整后表!M42
A12: 增长率（%） | D12: =ROUND((D9-C9)/C9,4) | E12: =ROUND((E9-D9)/D9,4) | F12: =ROUND((F9/6*12-E9)/E9,4) | G12: =ROUND((G9+F9-E9)/E9,4) | H12: =ROUND((H9-(G9+F9))/(G9+F9),4) | I12: =ROUND((I9-H9)/H9,4) | J12: =ROUND((J9-I9)/I9,4) | K12: =ROUND((K9-J9)/J9,4) | L12: =ROUND((L9-K9)/K9,4) | M12: =ROUND((M9-L9)/L9,4)

Sheet 营业外支出表
A1: 营业外支出分析预测表 | N1: =HYPERLINK("#目录1!A1","返回目录")
A2: 评估基准日：{{VALUATION_BASE_DATE}}
A3: ="被评估单位："&项目信息!B5&"" | M3: ="金额单位："&项目信息!B8&""
A4: 项目 | C4: 历史数据 | G4: 未来预测
C5: 2022年度 | D5: 2023年度 | E5: 2024年度 | F5: 2025年1-6月 | G5: 2025年7-12月 | H5: 2026年度 | I5: 2027年度 | J5: 2028年度 | K5: 2029年度 | L5: 2030年度 | M5: 永续年度
A9: 合计 | C9: =SUM(C6:C8) | D9: =SUM(D6:D8) | E9: =SUM(E6:E8) | F9: =SUM(F6:F8) | G9: =SUM(G6:G8) | H9: =SUM(H6:H8) | I9: =SUM(I6:I8) | J9: =SUM(J6:J8) | ... M9: =SUM(M6:M8)
A11: 【HD】核对 | C11: =C9-历利调整后表!D43 | D11: =D9-历利调整后表!G43 | E11: =E9-历利调整后表!J43 | F11: =F9-历利调整后表!M43
A12: 增长率（%） | D12: =ROUND((D9-C9)/C9,4) | E12: =ROUND((E9-D9)/D9,4) | F12: =ROUND((F9/6*12-E9)/E9,4) | G12: =ROUND((G9+F9-E9)/E9,4) | H12: =ROUND((H9-(G9+F9))/(G9+F9),4) | I12: =ROUND((I9-H9)/H9,4) | J12: =ROUND((J9-I9)/I9,4) | K12: =ROUND((K9-J9)/J9,4) | L12: =ROUND((L9-K9)/K9,4) | M12: =ROUND((M9-L9)/L9,4)

Sheet 所得税表
A1: 所得税费用预测明细表 | N1: =HYPERLINK("#目录1!A1","返回目录")
A2: 评估基准日：{{VALUATION_BASE_DATE}}
A3: ="被评估单位："&项目信息!B5&"" | M3: ="金额单位："&项目信息!B8&""
A4: 一、业务招待费纳税调整
A5: 项目 | C5: 历史数据 | G5: 未来预测
C6: 2022年度 | D6: 2023年度 | E6: 2024年度 | F6: 2025年1-6月 | G6: 2025年7-12月 | H6: 2026年度 | I6: 2027年度 | J6: 2028年度 | K6: 2029年度 | L6: 2030年度 | M6: 永续年度
A7: 销售费用-业务招待费 | C7: =销售费用表!C9 | D7: =销售费用表!D9 | E7: =销售费用表!E9 | F7: =销售费用表!F9 | G7: =销售费用表!G9 | H7: =销售费用表!H9 | I7: =销售费用表!I9 | J7: =销售费用表!J9 | ... M7: =销售费用表!M9
A8: 管理费用-业务招待费 | C8: =管理费用表!C9 | D8: =管理费用表!D9 | E8: =管理费用表!E9 | F8: =管理费用表!F9 | G8: =管理费用表!G9 | H8: =管理费用表!H9 | I8: =管理费用表!I9 | J8: =管理费用表!J9 | ... M8: =管理费用表!M9
A9: 研发费用-业务招待费 | C9: =研发费用表!C10 | D9: =研发费用表!D10 | E9: =研发费用表!E10 | F9: =研发费用表!F10 | G9: =研发费用表!G10 | H9: =研发费用表!H10 | I9: =研发费用表!I10 | J9: =研发费用表!J10 | ... M9: =研发费用表!M10
A10: 制造费用-业务招待费 | C10: =制造费用表!C10 | D10: =制造费用表!D10 | E10: =制造费用表!E10 | F10: =制造费用表!F10 | G10: =制造费用表!G10 | H10: =制造费用表!H10 | I10: =制造费用表!I10 | J10: =制造费用表!J10 | ... M10: =制造费用表!M10
A12: 业务招待费 | G12: =SUM(G7:G11) | H12: =SUM(H7:H11) | I12: =SUM(I7:I11) | J12: =SUM(J7:J11) | K12: =SUM(K7:K11) | L12: =SUM(L7:L11) | M12: =SUM(M7:M11)
A13: 业务招待费的60% | G13: =ROUND(G12*0.6,2) | H13: =ROUND(H12*0.6,2) | I13: =ROUND(I12*0.6,2) | J13: =ROUND(J12*0.6,2) | K13: =ROUND(K12*0.6,2) | L13: =ROUND(L12*0.6,2) | M13: =ROUND(M12*0.6,2)
A14: 收入的0.5% | G14: =ROUND(营业收入表!G17*0.005,2) | H14: =ROUND(营业收入表!H17*0.005,2) | I14: =ROUND(营业收入表!I17*0.005,2) | J14: =ROUND(营业收入表!J17*0.005,2) | K14: =ROUND(营业收入表!K17*0.005,2) | L14: =ROUND(营业收入表!L17*0.005,2) | M14: =ROUND(营业收入表!M17*0.005,2)
A15: 调增部分 | G15: =IF(G13-G14>0,G13-G14,0) | H15: =IF(H13-H14>0,H13-H14,0) | I15: =IF(I13-I14>0,I13-I14,0) | J15: =IF(J13-J14>0,J13-J14,0) | K15: =IF(K13-K14>0,K13-K14,0) | L15: =IF(L13-L14>0,L13-L14,0) | M15: =IF(M13-M14>0,M13-M14,0)
A16: 纳税调增 | G16: =G12*0.4+G15 | H16: =H12*0.4+H15 | I16: =I12*0.4+I15 | J16: =J12*0.4+J15 | K16: =K12*0.4+K15 | L16: =L12*0.4+L15 | M16: =M12*0.4+M15
A18: 二、研发费用纳税调整
A19: 项目 | C19: 历史数据 | G19: 未来预测
C20: 2022年度 | D20: 2023年度 | E20: 2024年度 | F20: 2025年1-6月 | G20: 2025年7-12月 | H20: 2026年度 | I20: 2027年度 | J20: 2028年度 | K20: 2029年度 | L20: 2030年度 | M20: 永续年度
A21: 研发费用实际发生数 | C21: =研发费用表!C63 | D21: =研发费用表!D63 | E21: =研发费用表!E63 | F21: =研发费用表!F63 | G21: =研发费用表!G63 | H21: =研发费用表!H63 | I21: =研发费用表!I63 | J21: =研发费用表!J63 | ... M21: =研发费用表!M63
A22: 允许扣除比例（%）
A23: 允许扣除的研发费用 | C23: =ROUND(C21*C22,2) | D23: =ROUND(D21*D22,2) | E23: =ROUND(E21*E22,2) | F23: =ROUND(F21*F22,2) | G23: =ROUND(G21*G22,2) | H23: =ROUND(H21*H22,2) | I23: =ROUND(I21*I22,2) | J23: =ROUND(J21*J22,2) | ... M23: =ROUND(M21*M22,2)
A24: 加计扣除比例（%）
A25: 加计扣除金额 | C25: =ROUND(C23*C24,2) | D25: =ROUND(D23*D24,2) | E25: =ROUND(E23*E24,2) | F25: =ROUND(F23*F24,2) | G25: =ROUND(G23*G24,2) | H25: =ROUND(H23*H24,2) | I25: =ROUND(I23*I24,2) | J25: =ROUND(J23*J24,2) | ... M25: =ROUND(M23*M24,2)
A27: 三、所得税计算表
A28: 项目 | C28: 历史数据 | G28: 未来预测
C29: 2022年度 | D29: 2023年度 | E29: 2024年度 | F29: 2025年1-6月 | G29: 2025年7-12月 | H29: 2026年度 | I29: 2027年度 | J29: 2028年度 | K29: 2029年度 | L29: 2030年度 | M29: 永续年度
A30: 利润总额 | C30: =净现金流计算表!C26 | D30: =净现金流计算表!D26 | E30: =净现金流计算表!E26 | F30: =净现金流计算表!F26 | G30: =净现金流计算表!G26 | H30: =净现金流计算表!H26 | I30: =净现金流计算表!I26 | J30: =净现金流计算表!J26 | ... M30: =净现金流计算表!M26
A31: 加：业务招待费调增 | G31: =G16 | H31: =H16 | I31: =I16 | J31: =J16 | K31: =K16 | L31: =L16 | M31: =M16
A32: 罚款、滞纳金
A33: 资产减值损失
A35: 纳税调增小计 | G35: =SUM(G31:G34) | H35: =SUM(H31:H34) | I35: =SUM(I31:I34) | J35: =SUM(J31:J34) | K35: =SUM(K31:K34) | L35: =SUM(L31:L34) | M35: =SUM(M31:M34)
A36: 减：免税收入
A37: 研发费用加计扣除 | G37: =G25 | H37: =H25 | I37: =I25 | J37: =J25 | K37: =K25 | L37: =L25 | M37: =M25
A39: 纳税调减小计 | G39: =SUM(G36:G38) | H39: =SUM(H36:H38) | I39: =SUM(I36:I38) | J39: =SUM(J36:J38) | K39: =SUM(K36:K38) | L39: =SUM(L36:L38) | M39: =SUM(M36:M38)
A40: 应纳税所得额 | G40: =G30+G35-G39 | H40: =H30+H35-H39 | I40: =I30+I35-I39 | J40: =J30+J35-J39 | K40: =K30+K35-K39 | L40: =L30+L35-L39 | M40: =M30+M35-M39
A41: 补亏后应纳税所得额
A42: 税率（%）
A43: 所得税 | C43: =历利调整后表!D45 | D43: =历利调整后表!G45 | E43: =历利调整后表!J45 | F43: =历利调整后表!M45 | G43: =ROUND(G41*G42,2) | H43: =ROUND(H41*H42,2) | I43: =ROUND(I41*I42,2) | J43: =ROUND(J41*J42,2) | K43: =ROUND(K41*K42,2) | L43: =ROUND(L41*L42,2) | M43: =ROUND(M41*M42,2)
A45: 【HD】核对 | C45: =C43-历利调整后表!D45 | D45: =D43-历利调整后表!G45 | E45: =E43-历利调整后表!J45 | F45: =F43-历利调整后表!M45
E47: 重要提示：如“应纳税所得额”有所变化，需清空补亏瀑布表的数据，点击按钮重新进行计算。
F48: 2024弥补后 | G48: 2025弥补后 | H48: 2026弥补后 | I48: 2027弥补后 | J48: 2028弥补后 | K48: 2029弥补后 | L48: 2030弥补后 | M48: 永续年度弥补后
E49: 2020年
E50: 2021年
E51: 2022年
E52: 2023年
E53: 2024年
E54: 2025年
E55: 2026年
E56: 2027年
E57: 2028年
E58: 2029年
E59: 2030年
E60: 永续年度

Sheet 折旧摊销、资本性支出表
A1: 折旧摊销资本性支出计算汇总 | N1: =HYPERLINK("#目录1!A1","返回目录")
A2: 评估基准日：{{VALUATION_BASE_DATE}}
A3: ="被评估单位："&项目信息!B5&"" | M3: ="金额单位："&项目信息!B8&""
A4: 一、折旧摊销预测分类汇总
A5: 类别 | B5: 项目 | C5: 历史数据 | G5: 未来预测
C6: 2022年度 | D6: 2023年度 | E6: 2024年度 | F6: 2025年1-6月 | G6: 2025年7-12月 | H6: 2026年度 | I6: 2027年度 | J6: 2028年度 | K6: 2029年度 | L6: 2030年度 | M6: 永续年度
A7: 生产成本 | B7: 折旧 | M7: =L7
B8: 摊销
A9: 制造费用 | B9: 折旧 | C9: =制造费用表!C8 | D9: =制造费用表!D8 | E9: =制造费用表!E8 | F9: =制造费用表!F8
B10: 摊销 | C10: =制造费用表!C9 | D10: =制造费用表!D9 | E10: =制造费用表!E9 | F10: =制造费用表!F9
A11: 销售费用 | B11: 折旧 | C11: =销售费用表!C7 | D11: =销售费用表!D7 | E11: =销售费用表!E7 | F11: =销售费用表!F7
B12: 摊销 | C12: =销售费用表!C8 | D12: =销售费用表!D8 | E12: =销售费用表!E8 | F12: =销售费用表!F8
A13: 管理费用 | B13: 折旧 | C13: =管理费用表!C7 | D13: =管理费用表!D7 | E13: =管理费用表!E7 | F13: =管理费用表!F7
B14: 摊销 | C14: =管理费用表!C8 | D14: =管理费用表!D8 | E14: =管理费用表!E8 | F14: =管理费用表!F8
A15: 研发费用 | B15: 折旧 | C15: =研发费用表!C8 | D15: =研发费用表!D8 | E15: =研发费用表!E8 | F15: =研发费用表!F8
B16: 摊销 | C16: =研发费用表!C9 | D16: =研发费用表!D9 | E16: =研发费用表!E9 | F16: =研发费用表!F9
A17: 合计 | B17: 折旧 | C17: =SUMIF($B7:$B16,$B7,C7:C16) | D17: =SUMIF($B7:$B16,$B7,D7:D16) | E17: =SUMIF($B7:$B16,$B7,E7:E16) | F17: =SUMIF($B7:$B16,$B7,F7:F16) | G17: =SUMIF($B7:$B16,$B7,G7:G16) | H17: =SUMIF($B7:$B16,$B7,H7:H16) | I17: =SUMIF($B7:$B16,$B7,I7:I16) | J17: =SUMIF($B7:$B16,$B7,J7:J16) | ... M17: =SUMIF($B7:$B16,$B7,M7:M16)
B18: 摊销 | C18: =SUMIF($B7:$B16,$B8,C7:C16) | D18: =SUMIF($B7:$B16,$B8,D7:D16) | E18: =SUMIF($B7:$B16,$B8,E7:E16) | F18: =SUMIF($B7:$B16,$B8,F7:F16) | G18: =SUMIF($B7:$B16,$B8,G7:G16) | H18: =SUMIF($B7:$B16,$B8,H7:H16) | I18: =SUMIF($B7:$B16,$B8,I7:I16) | J18: =SUMIF($B7:$B16,$B8,J7:J16) | ... M18: =SUMIF($B7:$B16,$B8,M7:M16)
B19: 总计 | C19: =SUM(C17:C18) | D19: =SUM(D17:D18) | E19: =SUM(E17:E18) | F19: =SUM(F17:F18) | G19: =SUM(G17:G18) | H19: =SUM(H17:H18) | I19: =SUM(I17:I18) | J19: =SUM(J17:J18) | ... M19: =SUM(M17:M18)
A21: 折旧核对 | G21: =G17-折旧摊销附表!H30 | H21: =H17-折旧摊销附表!I30 | I21: =I17-折旧摊销附表!J30 | J21: =J17-折旧摊销附表!K30 | K21: =K17-折旧摊销附表!L30 | L21: =L17-折旧摊销附表!M30 | M21: =M17-折旧摊销附表!N30
A22: 摊销核对 | G22: =G18-折旧摊销附表!H60 | H22: =H18-折旧摊销附表!I60 | I22: =I18-折旧摊销附表!J60 | J22: =J18-折旧摊销附表!K60 | K22: =K18-折旧摊销附表!L60 | L22: =L18-折旧摊销附表!M60 | M22: =M18-折旧摊销附表!N60
A24: 二、资本性支出预测汇总
A25: 项目 | C25: 历史数据 | G25: 未来预测
C26: 2022年度 | D26: 2023年度 | E26: 2024年度 | F26: 2025年1-6月 | G26: 2025年7-12月 | H26: 2026年度 | I26: 2027年度 | J26: 2028年度 | K26: 2029年度 | L26: 2030年度 | M26: 永续年度
A27: 新增资本性支出 | C27: =SUM(资本性支出附表!C19,资本性支出附表!C24,资本性支出附表!C29) | D27: =SUM(资本性支出附表!D19,资本性支出附表!D24,资本性支出附表!D29) | E27: =SUM(资本性支出附表!E19,资本性支出附表!E24,资本性支出附表!E29) | F27: =SUM(资本性支出附表!F19,资本性支出附表!F24,资本性支出附表!F29) | G27: =SUM(资本性支出附表!G19,资本性支出附表!G24,资本性支出附表!G29) | H27: =SUM(资本性支出附表!H19,资本性支出附表!H24,资本性支出附表!H29) | I27: =SUM(资本性支出附表!I19,资本性支出附表!I24,资本性支出附表!I29) | J27: =SUM(资本性支出附表!J19,资本性支出附表!J24,资本性支出附表!J29) | ... M27: =SUM(资本性支出附表!M19,资本性支出附表!M24,资本性支出附表!M29)
A28: 更新资本性支出 | C28: =资本性支出附表!C14 | D28: =资本性支出附表!D14 | E28: =资本性支出附表!E14 | F28: =资本性支出附表!F14 | G28: =资本性支出附表!G14 | H28: =资本性支出附表!H14 | I28: =资本性支出附表!I14 | J28: =资本性支出附表!J14 | ... M28: =资本性支出附表!M14
A29: 合计 | C29: =SUM(C27:C28) | D29: =SUM(D27:D28) | E29: =SUM(E27:E28) | F29: =SUM(F27:F28) | G29: =SUM(G27:G28) | H29: =SUM(H27:H28) | I29: =SUM(I27:I28) | J29: =SUM(J27:J28) | ... M29: =SUM(M27:M28)
A31: 核对 | C31: =C29-资本性支出附表!C30 | D31: =D29-资本性支出附表!D30 | E31: =E29-资本性支出附表!E30 | F31: =F29-资本性支出附表!F30 | G31: =G29-资本性支出附表!G30 | H31: =H29-资本性支出附表!H30 | I31: =I29-资本性支出附表!I30 | J31: =J29-资本性支出附表!J30 | ... M31: =M29-资本性支出附表!M30

Sheet 折旧摊销附表
A1: 折旧摊销分析预测表 | O1: =HYPERLINK("#目录1!A1","返回目录")
A2: 评估基准日：{{VALUATION_BASE_DATE}}
A3: ="被评估单位："&项目信息!B5&"" | N3: ="金额单位："&项目信息!B8&""
A4: 一、折旧预测表
A5: 资产类别 | B5: 资产项目 | C5: 折旧总年限 | D5: 残值率（%） | E5: 账面原值 | F5: 基准日账面净值 | G5: 年折旧额 | H5: 2025年7-12月 | I5: 2026年度 | J5: 2027年度 | K5: 2028年度 | L5: 2029年度 | M5: 2030年度 | N5: 永续年度
A6: 房屋建筑物 | E6: =SUM(E7:E9) | F6: =SUM(F7:F9) | G6: =SUM(G7:G9) | H6: =SUM(H7:H9) | I6: =SUM(I7:I9) | J6: =SUM(J7:J9) | K6: =SUM(K7:K9) | L6: =SUM(L7:L9) | ... N6: =SUM(N7:N9)
G7: =IFERROR(E7*(1-D7)/C7,0)
G8: =IFERROR(E8*(1-D8)/C8,0)
G9: =IFERROR(E9*(1-D9)/C9,0)
A10: 机器设备 | E10: =SUM(E11:E13) | F10: =SUM(F11:F13) | G10: =SUM(G11:G13) | H10: =SUM(H11:H13) | I10: =SUM(I11:I13) | J10: =SUM(J11:J13) | K10: =SUM(K11:K13) | L10: =SUM(L11:L13) | ... N10: =SUM(N11:N13)
G11: =IFERROR(E11*(1-D11)/C11,0)
G12: =IFERROR(E12*(1-D12)/C12,0)
G13: =IFERROR(E13*(1-D13)/C13,0)
A14: 运输设备 | E14: =SUM(E15:E17) | F14: =SUM(F15:F17) | G14: =SUM(G15:G17) | H14: =SUM(H15:H17) | I14: =SUM(I15:I17) | J14: =SUM(J15:J17) | K14: =SUM(K15:K17) | L14: =SUM(L15:L17) | ... N14: =SUM(N15:N17)
G15: =IFERROR(E15*(1-D15)/C15,0)
G16: =IFERROR(E16*(1-D16)/C16,0)
G17: =IFERROR(E17*(1-D17)/C17,0)
A18: 电子设备和其他设备 | E18: =SUM(E19:E21) | F18: =SUM(F19:F21) | G18: =SUM(G19:G21) | H18: =SUM(H19:H21) | I18: =SUM(I19:I21) | J18: =SUM(J19:J21) | K18: =SUM(K19:K21) | L18: =SUM(L19:L21) | ... N18: =SUM(N19:N21)
G19: =IFERROR(E19*(1-D19)/C19,0)
G20: =IFERROR(E20*(1-D20)/C20,0)
G21: =IFERROR(E21*(1-D21)/C21,0)
A22: 投资性房地产 | E22: =SUM(E23:E25) | F22: =SUM(F23:F25) | G22: =SUM(G23:G25) | H22: =SUM(H23:H25) | I22: =SUM(I23:I25) | J22: =SUM(J23:J25) | K22: =SUM(K23:K25) | L22: =SUM(L23:L25) | ... N22: =SUM(N23:N25)
G23: =IFERROR(E23*(1-D23)/C23,0)
G24: =IFERROR(E24*(1-D24)/C24,0)
G25: =IFERROR(E25*(1-D25)/C25,0)
A26: 其他资产 | E26: =SUM(E27:E29) | F26: =SUM(F27:F29) | G26: =SUM(G27:G29) | H26: =SUM(H27:H29) | I26: =SUM(I27:I29) | J26: =SUM(J27:J29) | K26: =SUM(K27:K29) | L26: =SUM(L27:L29) | ... N26: =SUM(N27:N29)
G27: =IFERROR(E27*(1-D27)/C27,0)
G28: =IFERROR(E28*(1-D28)/C28,0)
G29: =IFERROR(E29*(1-D29)/C29,0)
A30: 折旧合计 | E30: =E6+E10+E14+E18+E22+E26 | F30: =F6+F10+F14+F18+F22+F26 | G30: =G6+G10+G14+G18+G22+G26 | H30: =H6+H10+H14+H18+H22+H26 | I30: =I6+I10+I14+I18+I22+I26 | J30: =J6+J10+J14+J18+J22+J26 | K30: =K6+K10+K14+K18+K22+K26 | L30: =L6+L10+L14+L18+L22+L26 | ... N30: =N6+N10+N14+N18+N22+N26
A33: 二、摊销预测表
A34: 资产类别 | B34: 资产项目 | C34: 摊销总年限 | D34: 残值率（%） | E34: 账面原值 | F34: 基准日账面净值 | G34: 年摊销额 | H34: 2025年7-12月 | I34: 2026年度 | J34: 2027年度 | K34: 2028年度 | L34: 2029年度 | M34: 2030年度 | N34: 永续年度
A35: 无形资产 | E35: =E36+E40+E44+E48 | F35: =F36+F40+F44+F48 | G35: =G36+G40+G44+G48 | H35: =H36+H40+H44+H48 | I35: =I36+I40+I44+I48 | J35: =J36+J40+J44+J48 | K35: =K36+K40+K44+K48 | L35: =L36+L40+L44+L48 | ... N35: =N36+N40+N44+N48
A36: 土地使用权 | E36: =SUM(E37:E39) | F36: =SUM(F37:F39) | G36: =SUM(G37:G39) | H36: =SUM(H37:H39) | I36: =SUM(I37:I39) | J36: =SUM(J37:J39) | K36: =SUM(K37:K39) | L36: =SUM(L37:L39) | ... N36: =SUM(N37:N39)
G37: =IFERROR(E37*(1-D37)/C37,0)
G38: =IFERROR(E38*(1-D38)/C38,0)
G39: =IFERROR(E39*(1-D39)/C39,0)
A40: 商标 | E40: =SUM(E41:E43) | F40: =SUM(F41:F43) | G40: =SUM(G41:G43) | H40: =SUM(H41:H43) | I40: =SUM(I41:I43) | J40: =SUM(J41:J43) | K40: =SUM(K41:K43) | L40: =SUM(L41:L43) | ... N40: =SUM(N41:N43)
G41: =IFERROR(E41*(1-D41)/C41,0)
G42: =IFERROR(E42*(1-D42)/C42,0)
G43: =IFERROR(E43*(1-D43)/C43,0)
A44: 专利 | E44: =SUM(E45:E47) | F44: =SUM(F45:F47) | G44: =SUM(G45:G47) | H44: =SUM(H45:H47) | I44: =SUM(I45:I47) | J44: =SUM(J45:J47) | K44: =SUM(K45:K47) | L44: =SUM(L45:L47) | ... N44: =SUM(N45:N47)
G45: =IFERROR(E45*(1-D45)/C45,0)
G46: =IFERROR(E46*(1-D46)/C46,0)
G47: =IFERROR(E47*(1-D47)/C47,0)
A48: 专有技术 | E48: =SUM(E49:E51) | F48: =SUM(F49:F51) | G48: =SUM(G49:G51) | H48: =SUM(H49:H51) | I48: =SUM(I49:I51) | J48: =SUM(J49:J51) | K48: =SUM(K49:K51) | L48: =SUM(L49:L51) | ... N48: =SUM(N49:N51)
G49: =IFERROR(E49*(1-D49)/C49,0)
G50: =IFERROR(E50*(1-D50)/C50,0)
G51: =IFERROR(E51*(1-D51)/C51,0)
A52: 长期待摊费用 | E52: =SUM(E53:E55) | F52: =SUM(F53:F55) | G52: =SUM(G53:G55) | H52: =SUM(H53:H55) | I52: =SUM(I53:I55) | J52: =SUM(J53:J55) | K52: =SUM(K53:K55) | L52: =SUM(L53:L55) | ... N52: =SUM(N53:N55)
G53: =IFERROR(E53*(1-D53)/C53,0)
G54: =IFERROR(E54*(1-D54)/C54,0)
G55: =IFERROR(E55*(1-D55)/C55,0)
A56: 其他资产 | E56: =SUM(E57:E59) | F56: =SUM(F57:F59) | G56: =SUM(G57:G59) | H56: =SUM(H57:H59) | I56: =SUM(I57:I59) | J56: =SUM(J57:J59) | K56: =SUM(K57:K59) | L56: =SUM(L57:L59) | ... N56: =SUM(N57:N59)
G57: =IFERROR(E57*(1-D57)/C57,0)
G58: =IFERROR(E58*(1-D58)/C58,0)
G59: =IFERROR(E59*(1-D59)/C59,0)
A60: 摊销合计 | E60: =E35+E52+E56 | F60: =F35+F52+F56 | G60: =G35+G52+G56 | H60: =H35+H52+H56 | I60: =I35+I52+I56 | J60: =J35+J52+J56 | K60: =K35+K52+K56 | L60: =L35+L52+L56 | ... N60: =N35+N52+N56

Sheet 资本性支出附表
A1: 资本性支出分析预测表 | N1: =HYPERLINK("#目录1!A1","返回目录")
A2: 评估基准日：{{VALUATION_BASE_DATE}}
A3: ="被评估单位："&项目信息!B5&"" | M3: ="金额单位："&项目信息!B8&""
A4: 类别 | B4: 项目 | C4: 历史数据 | G4: 未来预测
C5: 2022年度 | D5: 2023年度 | E5: 2024年度 | F5: 2025年1-6月 | G5: 2025年7-12月 | H5: 2026年度 | I5: 2027年度 | J5: 2028年度 | K5: 2029年度 | L5: 2030年度 | M5: 永续年度
A6: 存量资产更新：
B7: 房屋建筑物
B8: 机器设备 | M8: =折旧摊销、资本性支出表!M17
B9: 运输设备
B10: 电子设备和其他设备
B11: 存量无形资产及其它资产
B12: 存量长期待摊费用
B14: 存量资产更新合计 | G14: =SUM(G7:G13) | H14: =SUM(H7:H13) | I14: =SUM(I7:I13) | J14: =SUM(J7:J13) | K14: =SUM(K7:K13) | L14: =SUM(L7:L13) | M14: =SUM(M7:M13)
A15: 在建工程后续支出：
B16: 在建工程--土建后续支出
B17: 在建工程--设备后续支出
B19: 在建工程后续支出合计 | G19: =SUM(G16:G18) | H19: =SUM(H16:H18) | I19: =SUM(I16:I18) | J19: =SUM(J16:J18) | K19: =SUM(K16:K18) | L19: =SUM(L16:L18) | M19: =SUM(M16:M18)
A20: 新增资产（改良、改造、扩产）：
B24: 新增资产合计 | G24: =SUM(G21:G23) | H24: =SUM(H21:H23) | I24: =SUM(I21:I23) | J24: =SUM(J21:J23) | K24: =SUM(K21:K23) | L24: =SUM(L21:L23) | M24: =SUM(M21:M23)
A25: 新增资产更新：
B29: 新增资产更新合计 | G29: =SUM(G26:G28) | H29: =SUM(H26:H28) | I29: =SUM(I26:I28) | J29: =SUM(J26:J28) | K29: =SUM(K26:K28) | L29: =SUM(L26:L28) | M29: =SUM(M26:M28)
A30: 合计 | G30: =G14+G19+G24+G29 | H30: =H14+H19+H24+H29 | I30: =I14+I19+I24+I29 | J30: =J14+J19+J24+J29 | K30: =K14+K19+K24+K29 | L30: =L14+L19+L24+L29 | M30: =M14+M19+M24+M29

Sheet 营运资金表
A1: 营运资金计算表 | N1: =HYPERLINK("#目录1!A1","返回目录")
A2: 评估基准日：{{VALUATION_BASE_DATE}}
A3: ="被评估单位："&项目信息!B5&"" | M3: ="金额单位："&项目信息!B8&""
A4: 一、周转率计算表
A5: 周转率 | C5: 历史数据 | G5: 未来预测
C6: 2022年度 | D6: 2023年度 | E6: 2024年度 | F6: 2025年1-6月 | G6: 2025年7-12月 | H6: 2026年度 | I6: 2027年度 | J6: 2028年度 | K6: 2029年度 | L6: 2030年度 | M6: 永续年度
A7: 最低现金保有量
A8: 受限货币资金（如应付票据保证金）
A9: A应收款项 | C9: =ROUND(历利调整后表!D7/(历资调整后表!D12+历资调整后表!D13+历资调整后表!D14+历资调整后表!D22-历资调整后表!D56-历资调整后表!D57-历资调整后表!D69),2) | D9: =ROUND(历利调整后表!G7/(历资调整后表!G12+历资调整后表!G13+历资调整后表!G14+历资调整后表!G22-历资调整后表!G56-历资调整后表!G57-历资调整后表!G69),2) | E9: =ROUND(历利调整后表!J7/(历资调整后表!J12+历资调整后表!J13+历资调整后表!J14+历资调整后表!J22-历资调整后表!J56-历资调整后表!J57-历资调整后表!J69),2) | F9: =ROUND((历利调整后表!M7/6*12)/(历资调整后表!M12+历资调整后表!M13+历资调整后表!M14+历资调整后表!M22-历资调整后表!M56-历资调整后表!M57-历资调整后表!M69),2) | H9: =G9 | I9: =H9 | J9: =I9 | K9: =J9 | L9: =K9 | M9: =L9
A10: a应收票据 | C10: =ROUND(历利调整后表!D7/历资调整后表!D12,2) | D10: =ROUND(历利调整后表!G7/历资调整后表!G12,2) | E10: =ROUND(历利调整后表!J7/历资调整后表!J12,2) | F10: =ROUND((历利调整后表!M7/6*12)/历资调整后表!M12,2)
A11: a应收账款 | C11: =ROUND(历利调整后表!D7/历资调整后表!D13,2) | D11: =ROUND(历利调整后表!G7/历资调整后表!G13,2) | E11: =ROUND(历利调整后表!J7/历资调整后表!J13,2) | F11: =ROUND((历利调整后表!M7/6*12)/历资调整后表!M13,2)
A12: a应收款项融资 | C12: =ROUND(历利调整后表!D7/历资调整后表!D14,2) | D12: =ROUND(历利调整后表!G7/历资调整后表!G14,2) | E12: =ROUND(历利调整后表!J7/历资调整后表!J14,2) | F12: =ROUND((历利调整后表!M7/6*12)/历资调整后表!M14,2)
A13: a合同资产 | C13: =ROUND(历利调整后表!D7/历资调整后表!D22,2) | D13: =ROUND(历利调整后表!G7/历资调整后表!G22,2) | E13: =ROUND(历利调整后表!J7/历资调整后表!J22,2) | F13: =ROUND((历利调整后表!M7/6*12)/历资调整后表!M22,2)
A14: b预付款项 | C14: =ROUND(历利调整后表!D14/历资调整后表!D15,2) | D14: =ROUND(历利调整后表!G14/历资调整后表!G15,2) | E14: =ROUND(历利调整后表!J14/历资调整后表!J15,2) | F14: =ROUND((历利调整后表!M14/6*12)/历资调整后表!M15,2)
A15: 其他应收款（经营性）
A16: 存货 | C16: =ROUND(历利调整后表!D14/历资调整后表!D21,2) | D16: =ROUND(历利调整后表!G14/历资调整后表!G21,2) | E16: =ROUND(历利调整后表!J14/历资调整后表!J21,2) | F16: =ROUND((历利调整后表!M14/6*12)/历资调整后表!M21,2) | H16: =G16 | I16: =H16 | J16: =I16 | K16: =J16 | L16: =K16 | M16: =L16
A17: 其他流动资产（不含待抵扣进项税）
A18: 待抵扣进项税
A19: B应付款项 | C19: =ROUND(历利调整后表!D14/(历资调整后表!D54+历资调整后表!D55-历资调整后表!D15),2) | D19: =ROUND(历利调整后表!G14/(历资调整后表!G54+历资调整后表!G55-历资调整后表!G15),2) | E19: =ROUND(历利调整后表!J14/(历资调整后表!J54+历资调整后表!J55-历资调整后表!J15),2) | F19: =ROUND((历利调整后表!M14/6*12)/(历资调整后表!M54+历资调整后表!M55-历资调整后表!M15),2) | H19: =G19 | I19: =H19 | J19: =I19 | K19: =J19 | L19: =K19 | M19: =L19
A20: b应付票据 | C20: =ROUND(历利调整后表!D14/历资调整后表!D54,2) | D20: =ROUND(历利调整后表!G14/历资调整后表!G54,2) | E20: =ROUND(历利调整后表!J14/历资调整后表!J54,2) | F20: =ROUND((历利调整后表!M14/6*12)/历资调整后表!M54,2)
A21: b应付账款 | C21: =ROUND(历利调整后表!D14/历资调整后表!D55,2) | D21: =ROUND(历利调整后表!G14/历资调整后表!G55,2) | E21: =ROUND(历利调整后表!J14/历资调整后表!J55,2) | F21: =ROUND((历利调整后表!M14/6*12)/历资调整后表!M55,2)
A22: a预收款项 | C22: =ROUND(历利调整后表!D7/历资调整后表!D56,2) | D22: =ROUND(历利调整后表!G7/历资调整后表!G56,2) | E22: =ROUND(历利调整后表!J7/历资调整后表!J56,2) | F22: =ROUND((历利调整后表!M7/6*12)/历资调整后表!M56,2)
A23: a合同负债 | C23: =ROUND(历利调整后表!D7/历资调整后表!D57,2) | D23: =ROUND(历利调整后表!G7/历资调整后表!G57,2) | E23: =ROUND(历利调整后表!J7/历资调整后表!J57,2) | F23: =ROUND((历利调整后表!M7/6*12)/历资调整后表!M57,2)
A24: 应付职工薪酬
A25: 应交税费
A26: 其他应付款（经营性）
A27: a其他流动负债（合同负债对应的增值税）
A30: 二、最低现金保有量预测表
A31: 项目 | C31: 历史数据 | G31: 未来预测
C32: 2022年度 | D32: 2023年度 | E32: 2024年度 | F32: 2025年1-6月 | G32: 2025年7-12月 | H32: 2026年度 | I32: 2027年度 | J32: 2028年度 | K32: 2029年度 | L32: 2030年度 | M32: 永续年度
A33: 营业收入 | C33: =营业收入表!C17 | D33: =营业收入表!D17 | E33: =营业收入表!E17 | F33: =营业收入表!F17 | G33: =营业收入表!G17 | H33: =营业收入表!H17 | I33: =营业收入表!I17 | J33: =营业收入表!J17 | ... M33: =营业收入表!M17
A34: 营业成本 | C34: =营业成本表!C17 | D34: =营业成本表!D17 | E34: =营业成本表!E17 | F34: =营业成本表!F17 | G34: =营业成本表!G17 | H34: =营业成本表!H17 | I34: =营业成本表!I17 | J34: =营业成本表!J17 | ... M34: =营业成本表!M17
A35: 税金及附加 | C35: =税金及附加表!C27 | D35: =税金及附加表!D27 | E35: =税金及附加表!E27 | F35: =税金及附加表!F27 | G35: =税金及附加表!G27 | H35: =税金及附加表!H27 | I35: =税金及附加表!I27 | J35: =税金及附加表!J27 | ... M35: =税金及附加表!M27
A36: 销售费用 | C36: =销售费用表!C62 | D36: =销售费用表!D62 | E36: =销售费用表!E62 | F36: =销售费用表!F62 | G36: =销售费用表!G62 | H36: =销售费用表!H62 | I36: =销售费用表!I62 | J36: =销售费用表!J62 | ... M36: =销售费用表!M62
A37: 管理费用 | C37: =管理费用表!C62 | D37: =管理费用表!D62 | E37: =管理费用表!E62 | F37: =管理费用表!F62 | G37: =管理费用表!G62 | H37: =管理费用表!H62 | I37: =管理费用表!I62 | J37: =管理费用表!J62 | ... M37: =管理费用表!M62
A38: 研发费用 | C38: =研发费用表!C63 | D38: =研发费用表!D63 | E38: =研发费用表!E63 | F38: =研发费用表!F63 | G38: =研发费用表!G63 | H38: =研发费用表!H63 | I38: =研发费用表!I63 | J38: =研发费用表!J63 | ... M38: =研发费用表!M63
A39: 财务费用 | C39: =财务费用表!C15 | D39: =财务费用表!D15 | E39: =财务费用表!E15 | F39: =财务费用表!F15 | G39: =财务费用表!G15 | H39: =财务费用表!H15 | I39: =财务费用表!I15 | J39: =财务费用表!J15 | ... M39: =财务费用表!M15
A40: 所得税费用 | C40: =所得税表!C43 | D40: =所得税表!D43 | E40: =所得税表!E43 | F40: =所得税表!F43 | G40: =所得税表!G43 | H40: =所得税表!H43 | I40: =所得税表!I43 | J40: =所得税表!J43 | ... M40: =所得税表!M43
A41: 增值税 | G41: =IF(增值税表!G162>0,增值税表!G162,0) | H41: =IF(增值税表!H162>0,增值税表!H162,0) | I41: =IF(增值税表!I162>0,增值税表!I162,0) | J41: =IF(增值税表!J162>0,增值税表!J162,0) | K41: =IF(增值税表!K162>0,增值税表!K162,0) | L41: =IF(增值税表!L162>0,增值税表!L162,0) | M41: =IF(增值税表!M162>0,增值税表!M162,0)
A42: 完全成本 | C42: =SUM(C34:C41) | D42: =SUM(D34:D41) | E42: =SUM(E34:E41) | F42: =SUM(F34:F41) | G42: =SUM(G34:G41) | H42: =SUM(H34:H41) | I42: =SUM(I34:I41) | J42: =SUM(J34:J41) | ... M42: =SUM(M34:M41)
A43: 减：折旧/摊销 | C43: =折旧摊销、资本性支出表!C19 | D43: =折旧摊销、资本性支出表!D19 | E43: =折旧摊销、资本性支出表!E19 | F43: =折旧摊销、资本性支出表!F19 | G43: =折旧摊销、资本性支出表!G19 | H43: =折旧摊销、资本性支出表!H19 | I43: =折旧摊销、资本性支出表!I19 | J43: =折旧摊销、资本性支出表!J19 | ... M43: =折旧摊销、资本性支出表!M19
A44: 付现成本 | C44: =C42-C43 | D44: =D42-D43 | E44: =E42-E43 | F44: =F42-F43 | G44: =G42-G43 | H44: =H42-H43 | I44: =I42-I43 | J44: =J42-J43 | ... M44: =M42-M43
A45: 安全资金的月数
A46: 安全运营现金（最低现金保有量） | C46: =ROUND((C44)/12*C45,2) | D46: =ROUND((D44)/12*D45,2) | E46: =ROUND((E44)/12*E45,2) | F46: =ROUND((F44)/6*F45,2) | G46: =ROUND((F44+G44)/12*G45,2) | H46: =ROUND((H44)/12*H45,2) | I46: =ROUND((I44)/12*I45,2) | J46: =ROUND((J44)/12*J45,2) | K46: =ROUND((K44)/12*K45,2) | L46: =ROUND((L44)/12*L45,2) | M46: =ROUND((M44)/12*M45,2)
A49: 三、营运资金预测表
A50: 项目 | C50: 历史数据 | G50: 未来预测
C51: 2022年度 | D51: 2023年度 | E51: 2024年度 | F51: 2025年1-6月 | G51: 2025年7-12月 | H51: 2026年度 | I51: 2027年度 | J51: 2028年度 | K51: 2029年度 | L51: 2030年度 | M51: 永续年度
A52: 流动资产：
A53: 最低现金保有量 | F53: =F46 | G53: =G46 | H53: =H46 | I53: =I46 | J53: =J46 | K53: =K46 | L53: =L46
A54: 受限货币资金（如应付票据保证金）
A55: A应收款项 | C55: =历资调整后表!D12+历资调整后表!D13+历资调整后表!D14+历资调整后表!D22-历资调整后表!D56-历资调整后表!D57-历资调整后表!D69 | D55: =历资调整后表!G12+历资调整后表!G13+历资调整后表!G14+历资调整后表!G22-历资调整后表!G56-历资调整后表!G57-历资调整后表!G69 | E55: =历资调整后表!J12+历资调整后表!J13+历资调整后表!J14+历资调整后表!J22-历资调整后表!J56-历资调整后表!J57-历资调整后表!J69 | F55: =历资调整后表!M12+历资调整后表!M13+历资调整后表!M14+历资调整后表!M22-历资调整后表!M56-历资调整后表!M57-历资调整后表!M69 | G55: =IFERROR(ROUND((G33+F33)/G9,2),0) | H55: =IFERROR(ROUND((H33)/H9,2),0) | I55: =IFERROR(ROUND((I33)/I9,2),0) | J55: =IFERROR(ROUND((J33)/J9,2),0) | K55: =IFERROR(ROUND((K33)/K9,2),0) | L55: =IFERROR(ROUND((L33)/L9,2),0)
A56: a应收票据 | C56: =历资调整后表!D12 | D56: =历资调整后表!G12 | E56: =历资调整后表!J12 | F56: =历资调整后表!M12 | G56: =IFERROR(ROUND((G33+F33)/G10,2),0) | H56: =IFERROR(ROUND((H33)/H10,2),0) | I56: =IFERROR(ROUND((I33)/I10,2),0) | J56: =IFERROR(ROUND((J33)/J10,2),0) | K56: =IFERROR(ROUND((K33)/K10,2),0) | L56: =IFERROR(ROUND((L33)/L10,2),0)
A57: a应收账款 | C57: =历资调整后表!D13 | D57: =历资调整后表!G13 | E57: =历资调整后表!J13 | F57: =历资调整后表!M13 | G57: =IFERROR(ROUND((G33+F33)/G11,2),0) | H57: =IFERROR(ROUND((H33)/H11,2),0) | I57: =IFERROR(ROUND((I33)/I11,2),0) | J57: =IFERROR(ROUND((J33)/J11,2),0) | K57: =IFERROR(ROUND((K33)/K11,2),0) | L57: =IFERROR(ROUND((L33)/L11,2),0)
A58: a应收款项融资 | C58: =历资调整后表!D14 | D58: =历资调整后表!G14 | E58: =历资调整后表!J14 | F58: =历资调整后表!M14 | G58: =IFERROR(ROUND((G33+F33)/G12,2),0) | H58: =IFERROR(ROUND((H33)/H12,2),0) | I58: =IFERROR(ROUND((I33)/I12,2),0) | J58: =IFERROR(ROUND((J33)/J12,2),0) | K58: =IFERROR(ROUND((K33)/K12,2),0) | L58: =IFERROR(ROUND((L33)/L12,2),0)
A59: a合同资产 | C59: =历资调整后表!D22 | D59: =历资调整后表!G22 | E59: =历资调整后表!J22 | F59: =历资调整后表!M22 | G59: =IFERROR(ROUND((G33+F33)/G13,2),0) | H59: =IFERROR(ROUND((H33)/H13,2),0) | I59: =IFERROR(ROUND((I33)/I13,2),0) | J59: =IFERROR(ROUND((J33)/J13,2),0) | K59: =IFERROR(ROUND((K33)/K13,2),0) | L59: =IFERROR(ROUND((L33)/L13,2),0)
A60: b预付款项 | C60: =历资调整后表!D15 | D60: =历资调整后表!G15 | E60: =历资调整后表!J15 | G60: =IFERROR(ROUND((G34+F34)/G14,2),0) | H60: =IFERROR(ROUND((H34)/H14,2),0) | I60: =IFERROR(ROUND((I34)/I14,2),0) | J60: =IFERROR(ROUND((J34)/J14,2),0) | K60: =IFERROR(ROUND((K34)/K14,2),0) | L60: =IFERROR(ROUND((L34)/L14,2),0)
A61: 其他应收款（经营性） | C61: =历资调整后表!D19 | D61: =历资调整后表!G19 | E61: =历资调整后表!J19 | F61: =历资调整后表!M19
A62: 存货 | C62: =历资调整后表!D21 | D62: =历资调整后表!G21 | E62: =历资调整后表!J21 | F62: =历资调整后表!M21 | G62: =IFERROR(ROUND((G34+F34)/G16,2),0) | H62: =IFERROR(ROUND((H34)/H16,2),0) | I62: =IFERROR(ROUND((I34)/I16,2),0) | J62: =IFERROR(ROUND((J34)/J16,2),0) | K62: =IFERROR(ROUND((K34)/K16,2),0) | L62: =IFERROR(ROUND((L34)/L16,2),0)
A63: 其他流动资产（不含待抵扣进项税）
A64: 待抵扣进项税
A65: 流动资产合计 | C65: =SUM(C53:C54,C56:C64) | D65: =SUM(D53:D54,D56:D64) | E65: =SUM(E53:E54,E56:E64) | F65: =SUM(F53:F54,F56:F64) | G65: =SUM(G53:G64) | H65: =SUM(H53:H64) | I65: =SUM(I53:I64) | J65: =SUM(J53:J64) | K65: =SUM(K53:K64) | L65: =SUM(L53:L64)
A66: 流动负债：
A67: B应付款项 | C67: =历资调整后表!D54+历资调整后表!D55-历资调整后表!D15 | D67: =历资调整后表!G54+历资调整后表!G55-历资调整后表!G15 | E67: =历资调整后表!J54+历资调整后表!J55-历资调整后表!J15 | F67: =历资调整后表!M54+历资调整后表!M55-历资调整后表!M15 | G67: =IFERROR(ROUND((G34+F34)/G19,2),0) | H67: =IFERROR(ROUND((H34)/H19,2),0) | I67: =IFERROR(ROUND((I34)/I19,2),0) | J67: =IFERROR(ROUND((J34)/J19,2),0) | K67: =IFERROR(ROUND((K34)/K19,2),0) | L67: =IFERROR(ROUND((L34)/L19,2),0)
A68: b应付票据 | C68: =历资调整后表!D54 | D68: =历资调整后表!G54 | E68: =历资调整后表!J54 | F68: =历资调整后表!M54 | G68: =IFERROR(ROUND((G34+F34)/G20,2),0) | H68: =IFERROR(ROUND((H34)/H20,2),0) | I68: =IFERROR(ROUND((I34)/I20,2),0) | J68: =IFERROR(ROUND((J34)/J20,2),0) | K68: =IFERROR(ROUND((K34)/K20,2),0) | L68: =IFERROR(ROUND((L34)/L20,2),0)
A69: b应付账款 | C69: =历资调整后表!D55 | D69: =历资调整后表!G55 | E69: =历资调整后表!J55 | G69: =IFERROR(ROUND((G34+F34)/G21,2),0) | H69: =IFERROR(ROUND((H34)/H21,2),0) | I69: =IFERROR(ROUND((I34)/I21,2),0) | J69: =IFERROR(ROUND((J34)/J21,2),0) | K69: =IFERROR(ROUND((K34)/K21,2),0) | L69: =IFERROR(ROUND((L34)/L21,2),0)
A70: a预收款项 | C70: =历资调整后表!D56 | D70: =历资调整后表!G56 | E70: =历资调整后表!J56 | F70: =历资调整后表!M56 | G70: =IFERROR(ROUND((G33+F33)/G22,2),0) | H70: =IFERROR(ROUND((H33)/H22,2),0) | I70: =IFERROR(ROUND((I33)/I22,2),0) | J70: =IFERROR(ROUND((J33)/J22,2),0) | K70: =IFERROR(ROUND((K33)/K22,2),0) | L70: =IFERROR(ROUND((L33)/L22,2),0)
A71: a合同负债 | C71: =历资调整后表!D57 | D71: =历资调整后表!G57 | E71: =历资调整后表!J57 | F71: =历资调整后表!M57 | G71: =IFERROR(ROUND((G33+F33)/G23,2),0) | H71: =IFERROR(ROUND((H33)/H23,2),0) | I71: =IFERROR(ROUND((I33)/I23,2),0) | J71: =IFERROR(ROUND((J33)/J23,2),0) | K71: =IFERROR(ROUND((K33)/K23,2),0) | L71: =IFERROR(ROUND((L33)/L23,2),0)
A72: 应付职工薪酬 | C72: =历资调整后表!D62 | D72: =历资调整后表!G62 | E72: =历资调整后表!J62 | F72: =历资调整后表!M62
A73: 应交税费 | C73: =历资调整后表!D63 | D73: =历资调整后表!G63 | E73: =历资调整后表!J63 | F73: =历资调整后表!M63-5.286299 | G73: =ROUND(G41/6+G35/6+G40/2,4) | H73: =ROUND(H41/12+H35/12+H40/4,4) | I73: =ROUND(I41/12+I35/12+I40/4,4) | J73: =ROUND(J41/12+J35/12+J40/4,4) | K73: =ROUND(K41/12+K35/12+K40/4,4) | L73: =ROUND(L41/12+L35/12+L40/4,4)
A74: 其他应付款（经营性） | C74: =历资调整后表!D64 | D74: =历资调整后表!G64 | E74: =历资调整后表!J64 | F74: =历资调整后表!M64
A75: a其他流动负债（合同负债对应的增值税） | C75: =历资调整后表!D69 | D75: =历资调整后表!G69 | E75: =历资调整后表!J69 | F75: =历资调整后表!M69
A76: 流动负债合计 | C76: =SUM(C68:C75) | D76: =SUM(D68:D75) | E76: =SUM(E68:E75) | F76: =SUM(F67:F75) | G76: =SUM(G67:G75) | H76: =SUM(H67:H75) | I76: =SUM(I67:I75) | J76: =SUM(J67:J75) | K76: =SUM(K67:K75) | L76: =SUM(L67:L75)
A77: 营运资本 | C77: =C65-C76 | D77: =D65-D76 | E77: =E65-E76 | F77: =F65-F76 | G77: =G65-G76 | H77: =H65-H76 | I77: =I65-I76 | J77: =J65-J76 | ... L77: =L65-L76 | M77: =L77
A78: 营运资本增加额 | C78: =C77-B77 | D78: =D77-C77 | E78: =E77-D77 | F78: =F77-E77 | G78: =G77-F77 | H78: =H77-G77 | I78: =I77-H77 | J78: =J77-I77 | ... M78: =M77-L77
A80: 占营业收入比例（%） | C80: =ROUND(C77/营业收入表!C17,4) | D80: =ROUND(D77/营业收入表!D17,4) | E80: =ROUND(E77/营业收入表!E17,4) | F80: =ROUND(F77/营业收入表!F17,4) | G80: =ROUND(G77/营业收入表!G17,4) | H80: =ROUND(H77/营业收入表!H17,4) | I80: =ROUND(I77/营业收入表!I17,4) | J80: =ROUND(J77/营业收入表!J17,4) | ... M80: =ROUND(M77/营业收入表!M17,4)
A81: 最低现金保有量核对 | F81: =IF(历资表!E7<营运资金表!F52,(历资表!E7-营运资金表!F52)-溢余资产、非经营资产负债表!E26,0)

Sheet 折现率计算表
A1: 折现率计算表 | F1: =HYPERLINK("#目录1!A1","返回目录")
A2: 评估基准日：{{VALUATION_BASE_DATE}}
A3: ="被评估单位："&项目信息!B5&"" | E3: ="金额单位："&项目信息!B8&""
A4: 项目 | C4: 值 | D4: 取整位数 | E4: 说明
A5: 经营性资产现值之和 | C5: =净现金流计算表!G40
A6: D | E6: 被评估企业债务资本市场价值
A7: E | E7: 被评估企业权益资本市场价值
A8: T | E8: 被评估企业所得税率
A10: βu | E10: 行业可比公司βu
A11: D/E | C11: =ROUND(C22/C23,4) | E11: 可比公司资本结构均值
A12: βL | C12: =ROUND(C10*(1+(1-C8)*C11),4) | E12: βL=βu×(1+(1-T)×D/E)
A14: Rf | E14: 基准日近期十年期国债平均收益率
A15: ERP | E15: 市场风险超额回报率
A16: 企业特定风险 | E16: 企业特定风险=企业关键合同风险+企业关键人风险+其他企业特定风险
A17: 权益资本成本Re | C17: =ROUND(C14+C12*C15+C16,4) | E17: CAPM
A19: 税前债务资本成本 | E19: 基准日5年期贷款利率
A20: 税后债务资本成本Rd | C20: =ROUND(C19*(1-C8),4)
A22: D/(D+E) | E22: 可比公司债务资本权重均值
A23: E/(D+E) | C23: =ROUND(1-C22,4) | E23: 可比公司权益资本权重均值
A24: 加权平均资本成本 | C24: =ROUND(C17*C23+C20*C22,D24) | E24: WACC
A27: 说明：
A28: 1、如使用“被评估企业资本结构”需使用菜单栏的【迭代计算按钮】迭代计算折现率，直到“经营性资产现值之和”和“折现率”收敛到固定值；
A29: 2、如项目类型为“财报”且折现率的计算方式为“迭代（税前估值=税后估值）”，需在计算出WACC后使用菜单栏的【折现率求解按钮】计算税前折现率；
A30: 3、如采用“变动折现率/分段折现”，需在C列计算出每一期（通常为改变税率）的折现率后按预测期复制到G列开始的右侧表中。

Sheet 溢余资产、非经营资产负债表
A1: 溢余（非经营）资产、负债 | G1: =HYPERLINK("#目录1!A1","返回目录")
A2: 评估基准日：{{VALUATION_BASE_DATE}}
A3: ="被评估单位："&项目信息!B5&"" | F3: ="金额单位："&项目信息!B8&""
A4: 类别 | B4: 科目 | C4: 内容 | D4: 账面金额 | E4: 评估价值 | F4: 备注
A5: 溢余资产：
B6: 货币资金 | C6: 溢余资金
B26: 溢余资产合计 | D26: =SUM(D6:D25) | E26: =SUM(E6:E25)
A27: 非经营性资产：
B28: 其他应收 | C28: 汇算清缴退税
B48: 非经营性资产合计 | D48: =SUM(D28:D47) | E48: =SUM(E28:E47)
A49: 非经营性负债：
B50: 应付股利
B70: 非经营性负债合计 | D70: =SUM(D50:D69) | E70: =SUM(E50:E69)
A71: 非经营性资产、负债净值 | D71: =D48-D70 | E71: =E48-E70

Sheet 长期股权投资表
A1: 长期股权投资 | F1: =HYPERLINK("#目录1!A1","返回目录")
A2: 评估基准日：{{VALUATION_BASE_DATE}}
A3: ="被评估单位："&项目信息!B5&"" | E3: ="金额单位："&项目信息!B8&""
A4: 被投资单位 | B4: 核算方法 | C4: 账面金额 | D4: 评估价值 | E4: 备注
B5: 权益法
A55: 合计 | C55: =SUM(C5:C54) | D55: =SUM(D5:D54)

Sheet 付息负债明细表
A1: 付息负债明细表 | J1: =HYPERLINK("#目录1!A1","返回目录")
A2: 评估基准日：{{VALUATION_BASE_DATE}}
A3: ="被评估单位："&项目信息!B5&"" | I3: ="金额单位："&项目信息!B8&""
A4: 负债类型 | B4: 负债具体明细项 | C4: 借款日期 | D4: 借款期限(月） | E4: 借款利率（%） | F4: 借款合同金额 | G4: 借款截止基准日余额 | H4: 借款主要用途 | I4: 备注
A5: 银行借款：
B66: 银行借款合计 | F66: =SUM(F6:F65) | G66: =SUM(G6:G65)
A67: 公司债券：
B118: 公司债券合计 | F118: =SUM(F68:F117) | G118: =SUM(G68:G117)
A119: 其他机构融资：
B160: 其他机构融资合计 | F160: =SUM(F120:F159) | G160: =SUM(G120:G159)
A161: 其他：
B192: 其他合计 | F192: =SUM(F162:F191) | G192: =SUM(G162:G191)
A193: 负息负债净值 | F193: =F66+F118+F160+F192 | G193: =G66+G118+G160+G192
